Workbook

Sheet Morocco Prices
N1: Soufiane
B2: PRODUCT / SPECIFICATIONS | C2: FRANÇAIS | D2: PICTURE | E2: UNIT | F2: QUANTITY | G2: PRICE IN TURKEY (without kdv) + LOCAL TRANSP 'USD' | H2: KDV POSSIBILITY | I2: SHIPMENT*40HC* KONYA-TANGER | J2: COSTUMES (TURKEY) | L2: PRICE IN MOROCCO AZUR (without TVA) 'DH' | M2: PRICE IN MOROCCO ECO (without TVA) 'DH' | O2: PRICE IN MOROCCO AZUR | Q2: PRICE IN MOROCCO (-) | R2: made in morocco
A3: MECHANICAL PARTS
A4: CABINS | B4: CABIN ( 6 PERSONS. STAINLESS STEEL + PVC FLOOR ) + PACKING + ARCADE | C4: CABINE STANDARD INOX 1200/1100 + EMBALLAGE | E4: SET | F4: 1 | G4: 1475 | H4: NO | I4: 1400 | J4: 155 | L4: 18500 | M4: 15500 | O4: 0 | Q4: 16000 | R4: 12000
B5: CABIN STANDARD | C5: CABINE INOX 1200/1100 + EMBALLAGE | G5: 1000 | O5: 0
B6: CABIN PERSONILEZD | C6: CABINE INOX 1200/1100 + EMBALLAGE | G6: 1400 | O6: 0 | Q6: 8500 | R6: 6000
B7: CABIN FRAME + ROPE ATTACHEMNT + ROPE CONNECTORS + CONTRE POIDS | C7: ARCADE CABINE /DEG 1200 + ARCADE CONTRE-POIDS + TIRANDS + COULISSEAUX | G7: 450 | H7: NO | L7: 7700 | M7: 7800 | N7: HURAS BRAND | O7: 8500 | P7: ALYANS BRAND | Q7: 7500
A8: DOORS | B8: CABIN DOOR (DEAS) STAINLESS STEEL 70/80/90 CM | C8: PORTES CABINE / OPERATEUR *DEAS* INOX | E8: Pc | F8: 1 | G8: 330 | H8: NO | K8: HURAS BRAND | L8: 8500 | M8: 7800 | O8: 4600 | Q8: 4100
B9: LANDING DOOR (DEAS) STAINLESS STEEL 70/80/90 CM | C9: PORTES PALIERE AUTOMATIQUE INOX | E9: Pc | F9: 1 | G9: 225 | H9: NO | L9: 4600 | M9: 4700 | O9: 3500 | Q9: 3100
B10: LANDING DOOR (DEAS) RAL PAINTED 70/80/90 CM | C10: PORTES PALIERE AUTOMATIQUE PEINTURE EPOXY | E10: Pc | F10: 1 | G10: 185 | H10: NO | L10: 3500 | M10: 2900 | O10: 0 | Q10: 2600
A11: MANUEL DOORS+PARTS | B11: MANUEL DOOR RAL PAINTED 70/80/90 | C11: SEMI AUTOMATIC PORTES 70/80/90 | E11: Pc | F11: 1 | G11: 110 | H11: NO | L11: 0 | M11: 2500 | O11: 0 | Q11: 0
B12: MANUEL DOOR LOCK | C12: SERRURE (DOOR LOCK) | E12: Pc | F12: 1 | G12: 18 | H12: NO | L12: 0 | M12: 600 | O12: 1200 | Q12: 1200
B13: MANUEL DOOR GAM | C13: CAME DC 220V / 60V | E13: Pc | F13: 1 | G13: 44 | H13: NO | L13: 0 | M13: 1000 | O13: 0 | Q13: 0
B14: Door Shock Absorber | C14: DICTATOR | E14: Pc | F14: 1 | G14: 6.8 | H14: NO | L14: 0 | M14: 260 | O14: 19800 | Q14: 19000
A15: MOTOR | B15: MOTOR AKIŞ VVVF MF1 PROE 5.5KW 400KG/630KG +ENCODER | C15: Moteur AKIS VVVF 400KG/630KG +ENCODEUR | E15: Pc | F15: 1 | G15: 752 | H15: yes | L15: 0 | M15: 0 | O15: 0 | Q15: 0
B16: MOTOR AKIŞ VVVF MF1 PROE 7.5KW 500KG/800KG +ENCODER | C16: Moteur AKIS VVVF 500KG/800KG +ENCODEUR | E16: Pc | F16: 1 | G16: 762 | H16: yes | L16: 0 | M16: 0 | O16: 0 | Q16: 19500
B17: MOTOR AKIŞ MUGEN M2 SERİSİ GEARBOX 2 SPEED 480 KG | C17: Moteur AKIS 2 VITESSE 480KG | E17: Pc | F17: 1 | G17: 975 | H17: yes | L17: 0 | M17: 0 | O17: 0 | Q17: 0
B18: MOTOR AKIŞ MUGEN M2 SERİSİ GEARBOX 2 SPEED 720 KG | C18: Moteur AKIS 2 VITESSE 720KG | E18: Pc | F18: 1 | G18: 1070 | H18: yes | L18: 0 | M18: 0 | O18: 0 | Q18: 14
A19: RAILS/ CONSOLS/ BOLTS | B19: CONSOL 5*7cm | C19: CLASSIC BRACKET 60X60 patate | E19: Pc | F19: 1 | G19: 0.6 | H19: NO | L19: 25 | M19: 22 | O19: 0 | Q19: 16
B20: CONSOL 5*10cm | C20: CLASSIC BRACKET 60X80 | E20: Pc | F20: 1 | G20: 0.9 | H20: NO | L20: 31 | M20: 28 | O20: 9 | Q20: 15
B21: RAIL CLIPS 50 | C21: CROMPO 50 | E21: Pc | F21: 1 | G21: 0.28 | H21: NO | L21: 6.5 | M21: 13 | O21: 7
B22: RAIL CLIPS 70 | C22: CROMPO 70 | E22: Pc | F22: 1 | G22: 0.37 | H22: NO | L22: 7.5 | O22: 0 | Q22: 2.3
B23: M8*30 BOLT | C23: BOULON 8/30 | E23: Pc | F23: 1 | G23: 0.07 | H23: YES | L23: 0 | M23: 1.5 | O23: 0 | Q23: 3.2
B24: M12*40 BOLT | C24: BOULON 12/30 COMPLET | E24: Pc | F24: 1 | G24: 0.2 | H24: YES | L24: 0 | M24: 2.5 | O24: 0 | Q24: 5
B25: M14*70 BOLT | C25: BOULON 14/70 | E25: Pc | F25: 1 | G25: 0.3 | H25: YES | L25: 0 | M25: 0 | O25: 0 | Q25: 6
B26: WEDGE ANCHOR M12*110 | C26: CHEVEILLE 12/100 | E26: Pc | F26: 1 | G26: 0.21 | H26: NO | L26: 5.8 | M26: 6 | O26: 0 | Q26: 1050
B27: RAIL 50*50*5mm + FİSH PLATE (5M) | C27: GUIDE RAIL 50 | E27: SET | F27: 1 | G27: 16.4 | H27: NO | L27: 400 | M27: 400 | O27: 0
B28: RAIL 70*65*9mm + FİSH PLATE (5M) | C28: GUIDE RAIL 70 | G28: 32.6 | L28: 800 | M28: 800
A29: ROPES | B29: ROPE 10 MM | C29: Cable traction (10) | E29: M | F29: 1 | G29: 0.92 | H29: YES | L29: 18 | M29: 22 | O29: 0 | Q29: 18 | R29: Cable traction (10mm)
B30: ROPE 6 MM | C30: cable regulateur | E30: M | F30: 1 | G30: 0.28 | H30: YES | L30: 8 | M30: 10 | O30: 0 | Q30: 8 | R30: cable regulateur (6mm)
B31: ROPE ATTACHMENT 10MM | C31: Tirands 10MM | E31: Pc | F31: 1 | G31: 2.15 | H31: NO | L31: 0 | M31: 110 | O31: 0 | Q31: 90 | R31: Tirands 10MM
B32: ROPE CONNECTOR 10MM | C32: SERRE CABLE DIAM 10 * | E32: Pc | F32: 1 | G32: 0.2 | H32: NO | L32: 0 | M32: 0 | O32: 0 | Q32: 8 | R32: SERRE CABLE DIAM 10 *
B33: ROPE CONNECTOR 6MM | C33: SERRE CABLE DIAM 6 * | E33: Pc | F33: 1 | G33: 0.1 | H33: NO | L33: 0 | M33: 0 | O33: 0 | Q33: 5 | R33: SERRE CABLE DIAM 6 *
A34: OTHERS | B34: WEIGHT 96CM /50 KG PLASTIC | C34: CONTERWEIGHT BLOCK 96 CM (50 KG) | E34: Pc | F34: 1 | G34: 6 | H34: NO | L34: 340 | M34: 0 | O34: 0 | Q34: 30 | R34: CONTERWEIGHT BLOCK 96 CM (50 KG)
B35: OIL COLLECTION SET | C35: Collecteur D'huile | E35: Pc | F35: 1 | G35: 0.25 | H35: NO | L35: 0 | M35: 0 | O35: 0 | Q35: 0 | R35: Collecteur D'huile
B36: LUBRICATOR BOX | C36: BOITE DE LUBRIFICATION | E36: Pc | F36: 1 | G36: 1 | H36: NO | L36: 0 | M36: 0 | O36: 0 | Q36: 180 | R36: BOITE DE LUBRIFICATION
B37: GUIDE SHOE | C37: coulisseaux CABIN | E37: Pc | F37: 1 | G37: 0 | H37: NO | L37: 0 | M37: 0 | O37: 0 | Q37: 230 | R37: coulisseaux CABIN
B38: GUIDE SHOE PLASTIC | C38: Garniture coulisseau | E38: Pc | F38: 1 | G38: 0.5 | H38: NO | L38: 0 | M38: 0 | O38: 70 | Q38: 70 | R38: Garniture coulisseau
B39: PULLEY 5*10 | C39: POULIE RENVOI 5*10 | E39: Pc | F39: 1 | G39: 60 | H39: NO | L39: 0 | M39: 1800 | O39: 1500 | Q39: 1300 | R39: POULIE RENVOI 5*10
B40: BUFFER cabin/c.p | C40: BUFFER cabin/c.p / Les boudins - ressort dyal l7ofra | E40: SET | F40: 1 | G40: 33 | H40: NO | L40: 255 | M40: 0 | O40: 0 | Q40: 0 | R40: BUFFER cabin/c.p / Les boudins - ressort dyal l7ofra
A41: CABLES | B41: CABLE 0.75MM | C41: cable 0.75mm | E41: M | F41: 1 | G41: 0.023 | H41: NO | L41: 0 | M41: 0 | O41: 0 | Q41: 1.35 | R41: cable 0.75mm
B42: CABLE 4MM | C42: Cable 4MM | E42: M | F42: 1 | G42: 0.107 | H42: NO | L42: 0 | M42: 0 | O42: 0 | Q42: 0 | R42: Cable 4MM
B43: DT-13 DIGITAL CABLE | C43: câble numérique DT/13 | E43: M | F43: 1 | G43: 0.122 | H43: NO | L43: 0 | M43: 0 | O43: 0 | Q43: 0 | R43: câble numérique DT/13
B44: TTR CABLE 3*075MM | C44: TTR CABLE 3*075MM | E44: M | F44: 1 | G44: 0.137 | H44: NO | L44: 0 | M44: 0 | O44: 0 | Q44: 0 | R44: TTR CABLE 3*075MM
B45: FLEXIBLE CABLE 36LIK | C45: cable souple 36 - 24 (plus utilisé) 36 -> 75 dh / 24 -> 55 à 60 dh | E45: M | F45: 1 | G45: 1.5433 | H45: NO | L45: 68 | M45: 68 | O45: 46 | Q45: 45 | R45: cable souple 36 - 24 (plus utilisé) 36 -> 75 dh / 24 -> 55 à 60 dh
B46: FLEXIBLE CABLE WEDGE | C46: support cable souple (40 à 50 Dh) | E46: M | F46: 1 | G46: 0.8 | H46: NO | L46: 0 | M46: 100 | O46: 0 | Q46: 0 | R46: support cable souple (40 à 50 Dh)
B47: CABLE CHANNEL | C47: WIRE DUCT GOULLOTTE 40X40 | E47: M | F47: 1 | G47: 0.4 | H47: NO | L47: 26 | M47: 18 | O47: 0 | Q47: 0 | R47: WIRE DUCT GOULLOTTE 40X40
B48: SPIRAL HOSE 14mm | C48: Tube spiralé 14mm | E48: M | F48: 1 | G48: 0.09 | H48: NO | L48: 0 | M48: 0 | O48: 0 | Q48: 0 | R48: Tube spiralé 14mm
A49: BUTON | B49: COP 6 STOPS STAINLESS STEEL + INTERCOM 7 SEGMENT SCREEN * FULL SIZE 2M * | C49: Boutons De Cabine D’Ascenseur 2m | E49: Pc | F49: 1 | G49: 77.5 | H49: NO | L49: 0 | M49: 0 | O49: 0 | Q49: 1200 | R49: Boutons De Cabine D’Ascenseur 2m
B50: COP 6 STOPS STAINLESS STEEL + INTERCOM 7 SEGMENT SCREEN * HALF SIZE 1M * | C50: Boutons De Cabine D’Ascenseur 1m | E50: Pc | F50: 1 | G50: 67.5 | H50: NO | L50: 1450 | M50: 0 | O50: 0 | Q50: 1200 | R50: Boutons De Cabine D’Ascenseur 1m
B51: LOP STAINLESS STEEL 7 SEGMENT SCREEN | C51: Bouton palier avec afficheur | D51: #VALUE! | E51: Pc | F51: 1 | G51: 6.4 | H51: NO | L51: 260 | M51: 250 | O51: 0 | Q51: 270 | R51: Bouton palier avec afficheur
B52: LOP STAINLESS STEEL without screen | C52: Bouton palier | D52: #VALUE! | E52: Pc | F52: 1 | G52: 4.1 | H52: NO | L52: 140 | M52: 100 | O52: 0 | Q52: 170 | R52: Bouton palier
B53: UP DOOR SCREEN | C53: Indicateurs D’Atterissage | D53: #VALUE! | E53: Pc | F53: 1 | G53: 7.8 | H53: NO | L53: 0 | M53: 200 | O53: 0 | Q53: 0 | R53: Indicateurs D’Atterissage
A54: OTHERS | B54: ALARM BOX | C54: BOÎTE D'ALARME | E54: Pc | F54: 1 | G54: 0 | H54: NO | L54: 0 | M54: 0 | O54: 0 | Q54: 50 | R54: BOÎTE D'ALARME
B55: EMERGENCY BUTTON | C55: STOP COUP POING | E55: Pc | F55: 1 | G55: 1.6 | H55: NO | L55: 0 | M55: 0 | Q55: 50 | R55: STOP COUP POING
B56: ROLLER SWITCH | C56: ROLLER SWITCH | E56: Pc | F56: 1 | G56: 0 | H56: NO | L56: 0 | M56: 0 | O56: 0 | Q56: 0 | R56: ROLLER SWITCH
B57: LIMIT SWITCH | C57: LIMIT SWITCH | E57: Pc | F57: 1 | G57: 0 | H57: NO | L57: 0 | M57: 0 | O57: 0 | Q57: 0 | R57: LIMIT SWITCH
B58: PHOTOCELL | C58: Photocellule | E58: Pc | F58: 1 | G58: 53 | H58: NO | L58: 0 | M58: 0 | O58: 1200 | Q58: 1200 | R58: Photocellule
B59: DOOR CARD ARKEL KM-10 | C59: OPERATEUR CARTE ARKEL KM-10 | E59: Pc | F59: 1 | G59: 60 | H59: NO | L59: 0 | M59: 0 | O59: 600 | Q59: 600
B60: DOOR CARD ARKEL KM-10 COPY EOM | C60: OPERATEUR CARTE KM-10 COPY | E60: Pc | F60: 1 | G60: 36 | H60: yes 20% | L60: 0 | M60: 0 | O60: 1400 | Q60: 1300 | R60: OPERATEUR CARTE ARKEL KM-10 | T60: 1000 | V60: 0 | W60: OPERATEUR CARTE KM-10 COPY
B61: SPEED GOVERNOR VVVF | C61: REGULATEUR DE VITESSE VVVF 1.0M/S-0.8M/S | E61: Pc | F61: 1 | G61: 60 | H61: NO | L61: 2280 | M61: 1300 | O61: 1300 | Q61: 1200 | R61: REGULATEUR DE VITESSE VVVF 1.0M/S-0.8M/S
B62: SPEED GOVERNOR 2 SPEED | C62: REGULATEUR DE VITESSE 2 VITESSE | E62: Pc | F62: 1 | G62: 56.5 | H62: NO | L62: 1300 | M62: 0 | O62: 1300 | Q62: 1200 | R62: REGULATEUR DE VITESSE 2 VITESSE
A63: CONTROLLERS | B63: CONTROLLER EEM-MONARCH A3 VVVF 7.5KW + REVIZYON BOX | C63: ARMOIRE VVVF EEM MONARCH+ boite inspection | D63: #VALUE! | E63: Pc | F63: 1 | G63: 600 | H63: NO | L63: 10500 | M63: 12000 | O63: 10500 | Q63: 10000 | R63: ARMOIRE VVVF EEM MONARCH+ boite inspection
B64: CONTROLLER EEM 2 SPEED | C64: ARMOIRE 2 VITESSE KONEL | E64: Pc | F64: 1 | G64: 375 | H64: NO | L64: 6500 | M64: 5300 | O64: 5000 | Q64: 5000 | R64: ARMOIRE 2 VITESSE KONEL
B65: UPS PRICE | C65: UPS | E65: Pc | F65: 1 | G65: 75 | H65: YES | L65: 0 | M65: 1700 | O65: 0 | Q65: 2500 | R65: UPS
C66: CHASSIS MOTEUR STANDARD GEARBOX AVEC CYLINBLOC
C67: ARCADE COMPLET 100CM
C68: TABLEAU 2V EEM
C69: OUPERATEUR GAUCHE 60CM
C70: CABINE 90*62CM
C71: CALIBTEURS FIN DE COURSE
C72: GOSE 76CM - 31KG
B153: CABIN + PARTS | J153: DOORS
C154: UNIT | D154: PRICE | E154: UNIT | F154: PRICE | K154: UNIT | L154: PRICE | M154: UNIT | N154: PRICE | O154: UNIT | P154: PRICE | Q154: UNIT | R154: PRICE
B155: CABIN INOX | C155: pc (HMED AZUR) | D155: 18500DH | E155: SERCOLIFT HAMID | F155: 15500 | J155: HÜRAS
B156: CABIN FRAME | C156: pc (HMED AZUR) 1.1M | D156: 7700DH | E156: SERCOLIFT HAMID | F156: 7800 | J156: LANDING DOOR INOX | K156: pc (HMED AZUR) | L156: 4600DH
B157: WEIGHT FRAME | C157: pc (HMED AZUR) | D157: 2800DH | J157: LANDING DOOR RAL PAINTED | K157: pc (HMED AZUR) | L157: 3500DH
J158: CABIN DOOR INOC | K158: pc (HMED AZUR) | L158: 8500DH
B159: CABIN INOX | C159: DEMSAN | D159: 15000DH
B160: CABIN FRAME | C160: DEMSAN | D160: 7700DH | J160: ALYANS
B161: WEIGHT FRAME | C161: DEMSAN | D161: 2800DH | J161: LANDING DOOR INOX | M161: SERCOLIFT HAMID | N161: 5500 | Q161: ses kayidi hamid | R161: 4700
B162: CABIN FRAME | C162: AYHAN | D162: 7500DH | J162: LANDING DOOR RAL PAINTED | O162: mondialift HAMID | P162: 3350 | R162: 2900
B163: WEIGHT FRAME | C163: AYHAN | J163: CABIN DOOR INOC | M163: SERCOLIFT HAMID | N163: 8500 | O163: SERCOLIFT HAMID | P163: 7800 | R163: 7800
B165: CABIN WOOD | D165: 14000DH | J165: FERMATOR
B166: CABIN FRAME | J166: LANDING DOOR INOX | K166: pc (HMED AZUR) | L166: 6300DH
B167: WEIGHT FRAME | J167: LANDING DOOR RAL PAINTED | K167: pc (HMED AZUR) | L167: 4100DH
J168: CABIN DOOR INOX 700MM | K168: pc (HMED AZUR) | L168: 10700DH
J169: CABIN DOOR INOX 800MM | K169: AZUR HAMID | L169: 11200
B170: MACHINE FRAME | C170: pc (HMED AZUR) | D170: 1100DH | E170: SERCOLIFT HAMID | F170: 700
J171: MANUEL DOOR 700 RAL PAINTED
B172: PATEN 70/90
B173: PATEN 50LIK
B174: ELECTRONIC OVERLOAD MEC. | J174: CABLES
B175: ELECTRONIC OVERLOAD ELEC. | K175: UNIT | L175: PRICE | M175: UNIT | N175: PRICE
B176: BUFFER | C176: pc (HMED AZUR) | D176: 255DH | J176: TTR CABLE
B177: MACHINE BASE PLAT | C177: pc (HMED AZUR) | D177: 45DH | J177: 0.75mm CABLE
B178: CONTERWEIGHT BLOCK 96CM | C178: 50KG 1PC (HMED AZUR) | D178: 340DH | J178: 4mm CABLE
B179: ERKAN PARSHUT | D179: 2300DH | J179: DT13 CABLE | K179: 1M | L179: 14DH
B180: PULLEY | C180: 400MM | D180: 1600DH | J180: DIJITAL CABLE
B181: PATEN PLASTIC | D181: 35DH | J181: FLEXIBLE CABLE 20
...

Sheet Bolt Sara Adana
B6: Cost/Ton : | D6: Electrozinc plate
D7: Flat bolt
D8: 1400 Euros/ton | E8: Casa
D9: 1380 Euros/ton | E9: Adana | F9: Hex nuts only | H9: $ to Euros
B10: M8*30 BOLT | D10: BOULON 8/30 | E10: 0.07 | F10: 0.02 | G10: =+E10/F10*1000 -> 3500 | H10: =+G10*0.85 -> 2975
B11: M12*40 BOLT | D11: BOULON 12/30 COMPLET | E11: 0.2 | F11: 0.05 | G11: =+E11/F11*1000 -> 4000 | H11: =+G11*0.85 -> 3400
B12: M14*70 BOLT | D12: BOULON 14/70 | E12: 0.3 | F12: 0.09 | G12: =+E12/F12*1000 -> 3333.3333 | H12: =+G12*0.85 -> 2833.3333

Sheet Pricing Turkey
A2: Réf. | B2: FRANÇAIS | C2: Composante | D2: UNIT | E2: Poids | F2: Acier (O/N) | G2: PRICE IN TURKEY (without kdv) + LOCAL TRANSP 'USD' | H2: KDV POSSIBILITY | J2: USD / MAD | K2: 9.8 | L2: Comment
A3: IT.1 | B3: SET CABINE STANDARD INOX 1200/1100 + ARCADES & ACCESSOIRES GEARBOX | C3: CABINE & ARCADE | D3: SET | E3: 650 | F3: INOX | G3: 1500 | H3: NO
A4: IT.1-1 | B4: CABINE INOX 1000/900 STANDARD | C4: CABINE & ARCADE | D4: Pc | E4: 350 | F4: INOX | G4: 950 | L4: Without GRANITE
A5: IT.1-2 | B5: CABINE INOX 1000/900 PERSONALISÉE | C5: CABINE & ARCADE | D5: Pc | E5: 350 | F5: INOX | G5: 1200 | L5: Without GRANITE | Q5: ORD1 | R5: ORD2 | S5: ORD3 | T5: ORD4 | U5: ORD5 | V5: ORD6 | W5: ORD7 | X5: ORD8 | Y5: ORD9 | Z5: ORD10 | AA5: ORD11 | AB5: ORD12 | AC5: ORD13 | AD5: ORD14 | AE5: ORD15 | AF5: ORD16 | AG5: ORD17 | AH5: ORD18 | AI5: ORD19 | AJ5: ORD20 | AK5: ORD21 | AL5: ORD22 | AM5: ORD23 | AN5: ORD24 | AO5: ORD25 | AP5: ORD26 | AQ5: ORD27 | AR5: ORD28 | AS5: ORD29 | AT5: ORD30
A6: IT.1-3 | B6: CABINE INOX 1100/1000 STANDARD | C6: CABINE & ARCADE | D6: Pc | E6: 350 | F6: INOX | G6: 1020 | L6: Without GRANITE | Q6: 150 | R6: 150 | S6: 150 | T6: 150 | U6: 150 | V6: 150 | W6: 150 | X6: 150
A7: IT.1-4 | B7: CABINE INOX 1100/1000 PERSONALISÉE | C7: CABINE & ARCADE | D7: Pc | E7: 350 | F7: INOX | G7: 1320 | L7: Without GRANITE | Q7: 46038
A8: IT.1-5 | B8: CABINE INOX 1200/1100 STANDARD | C8: CABINE & ARCADE | D8: Pc | E8: 350 | F8: INOX | G8: 1090 | L8: Without GRANITE | Q8: 1400$ | S8: FROM 900 TO 1200 CABIN + ARCADES
A9: IT.1-6 | B9: CABINE INOX 1200/1100 PERSONALISÉE | C9: CABINE & ARCADE | D9: Pc | E9: 350 | F9: INOX | G9: 1390 | L9: Without GRANITE | Q9: 150$ | S9: PERSONALISATION
A10: IT.1-13 | B10: CABINE INOX 1400/1300 STANDARD | C10: CABINE & ARCADE | D10: SET | E10: 350 | F10: STEEL | G10: 1340 | L10: Without GRANITE
A11: IT.1-14 | B11: CABINE INOX 1400/1300 PERSONALISÉE | C11: CABINE & ARCADE | D11: SET | E11: 350 | F11: STEEL | G11: 1740 | L11: Without GRANITE
A12: IT.1-17 | B12: CABINE 1000/900 PANORAMIQUE | C12: CABINE & ARCADE | D12: Pc | E12: 350 | F12: INOX | G12: 1600
A13: IT.1-18 | B13: CABINE 1100/1000 PANORAMIQUE | C13: CABINE & ARCADE | D13: Pc | E13: 350 | F13: INOX | G13: 1700
A14: IT.1-19 | B14: CABINE 1200/1100 PANORAMIQUE | C14: CABINE & ARCADE | D14: Pc | E14: 350 | F14: INOX | G14: 1850
A15: IT.1-20 | B15: CABINE INOX 1300/1200 STANDARD | C15: CABINE & ARCADE | D15: Pc | E15: 350 | F15: INOX | G15: 1160
A16: IT.1-21 | B16: CABINE INOX 1300/1200 PERSONALISÉE | C16: CABINE & ARCADE | D16: Pc | E16: 350 | F16: INOX | G16: 1460
A17: IT.1-22 | B17: CABINE 1300/1200 PANORAMIQUE | C17: CABINE & ARCADE | D17: Pc | E17: 350 | F17: INOX | G17: 2050
A18: IT.1-23 | B18: CABINE 1400/1300 PANORAMIQUE | C18: CABINE & ARCADE | D18: Pc | E18: 350 | F18: INOX | G18: 2300
A19: IT.1-7 | B19: ARCADE CABINE 1000/900 + ARCADE CONTRE-POIDS + TIRANDS + COULISSEAUX GEARBOX | C19: CABINE & ARCADE | D19: SET | E19: 200 | F19: STEEL | G19: 450
A20: IT.1-8 | B20: ARCADE CABINE 1000/900 + ARCADE CONTRE-POIDS + TIRANDS + COULISSEAUX GEARLESS | C20: CABINE & ARCADE | D20: SET | E20: 200 | F20: STEEL | G20: 700
A21: IT.1-9 | B21: ARCADE CABINE 1100/1000 + ARCADE CONTRE-POIDS + TIRANDS + COULISSEAUX GEARBOX | C21: CABINE & ARCADE | D21: SET | E21: 200 | F21: STEEL | G21: 470
A22: IT.1-10 | B22: ARCADE CABINE 1100/1000 + ARCADE CONTRE-POIDS + TIRANDS + COULISSEAUX GEARLESS | C22: CABINE & ARCADE | D22: SET | E22: 200 | F22: STEEL | G22: 720
A23: IT.1-11 | B23: ARCADE CABINE 1200/1100 + ARCADE CONTRE-POIDS + TIRANDS + COULISSEAUX GEARBOX | C23: CABINE & ARCADE | D23: SET | E23: 200 | F23: STEEL | G23: 490 | H23: NO
A24: IT.1-12 | B24: ARCADE CABINE 1200/1100 + ARCADE CONTRE-POIDS + TIRANDS + COULISSEAUX GEARLESS | C24: CABINE & ARCADE | D24: SET | E24: 200 | F24: STEEL | G24: 740
A25: IT.1-15 | B25: ARCADE CABINE 1400/1300 + ARCADE CONTRE-POIDS + TIRANDS + COULISSEAUX GEARBOX | C25: CABINE & ARCADE | D25: SET | E25: 201 | F25: STEEL | G25: 590
A26: IT.1-16 | B26: ARCADE CABINE 1400/1300 + ARCADE CONTRE-POIDS + TIRANDS + COULISSEAUX GEARLESS | C26: CABINE & ARCADE | D26: SET | E26: 202 | F26: STEEL | G26: 940 | H26: NO
A27: IT.1-17 | B27: SET ARCADE TYPE L VVVF 2V | C27: CABINE & ARCADE | D27: SET | E27: 203 | F27: STEEL | G27: 1000
A28: IT.1-18 | B28: SET ARCADE TYPE L GEARLESS | C28: CABINE & ARCADE | D28: SET | E28: 204 | F28: STEEL | G28: 1200
A29: HYD1-1 | B29: SET SYSTÈME HYDRAULIQUE MAX4 STANDARD 0,15M/S 10M COURSE (4 NIVEAUX) | C29: HYDRAULIQUE | D29: SET | E29: 200 | F29: STEEL | G29: 1500
A30: HYD1-2 | B30: SET SYSTÈME HYDRAULIQUE MAX4 STANDARD 0,15M/S 7M COURSE (3 NIVEAUX) | C30: HYDRAULIQUE | D30: SET | E30: 198 | F30: STEEL
A31: HYD1-3 | B31: SET SYSTÈME HYDRAULIQUE MAX4 STANDARD 0,15M/S 4M COURSE (2 NIVEAUX) | C31: HYDRAULIQUE | D31: SET | E31: 199 | F31: STEEL
A32: HYD2-1 | B32: SET SYSTÈME HYDRAULIQUE MAX4 GMV 0,62M/S 10M COURSE (4 NIVEAUX) | C32: HYDRAULIQUE | D32: SET | E32: 200 | F32: STEEL | G32: =3000*1.1 -> 3300
A33: HYD2-2 | B33: SET SYSTÈME HYDRAULIQUE MAX4 GMV 0,62M/S 7M COURSE (3 NIVEAUX) | C33: HYDRAULIQUE | D33: SET | E33: 200 | F33: STEEL | G33: 3000
A34: HYD2-3 | B34: SET SYSTÈME HYDRAULIQUE MAX4 GMV 0,62M/S 4M COURSE (2 NIVEAUX) | C34: HYDRAULIQUE | D34: SET | E34: 200 | F34: STEEL | G34: 2700
A35: HYD3 | B35: SET COMPOSANTES ELECTRIQUES POUR SYSTEME HYDRAULIQUE | C35: HYDRAULIQUE | D35: SET | E35: 200 | F35: STEEL | G35: 800
A36: HYD4 | B36: HUILE HYDRAULIQUE | C36: HYDRAULIQUE | D36: L | E36: 1 | F36: OIL | G36: 4
A37: IT.2 | B37: PORTE PALIERE AUTOMATIQUE INOX ATERYA 70/80 | C37: PORTE | D37: Pc | E37: 145 | F37: INOX | G37: 252.7436 | H37: NO | K37: Fournisseur au Maroc
A38: IT.3 | B38: PORTE PALIERE AUTOMATIQUE EPOXY ATERYA 70/80 | C38: PORTE | D38: Pc | E38: 140 | F38: STEEL | G38: 186.23213 | H38: NO | K38: Fournisseur au Maroc
A39: IT.4 | B39: OPERATEUR INOX ATERYA 70/80 | C39: OPÉRATEUR | D39: Pc | E39: 38 | F39: INOX | G39: 419.02228 | H39: NO | K39: Fournisseur au Maroc
A40: IT.5 | B40: SEMI AUTOMATIC PORTE EPOXY 70/80 | C40: PORTE | D40: Pc | E40: 90 | F40: STEEL | G40: 110 | H40: NO
A41: IT.6 | B41: SEMI AUTOMATIC PORTE INOX 70/80 | C41: PORTE | D41: Pc | E41: 90 | F41: INOX | G41: 110 | H41: yes
A42: IT.7 | B42: SERRURE (DOOR LOCK) | C42: AUTRES | D42: Pc | E42: 3 | F42: STEEL | G42: 18 | H42: yes
A43: IT.8 | B43: CAME DC 220V / 60V | C43: AUTRES | D43: Pc | E43: 4 | F43: N | G43: 44 | H43: yes
A44: IT.9 | B44: DICTATOR | C44: AUTRES | D44: Pc | E44: 2 | F44: N | G44: 6.8 | H44: yes
A45: IT.10 | B45: MOTEUR AKİŞ VOLPİ GEARLESS 3,9KW MAX4 MAX6 240*5*6,5MM 1,0M/S VVVF +ENCODEUR | C45: MOTEUR | D45: Pc | E45: 180 | F45: N | G45: 1020 | H45: NO | J45: Type des composantes :
A46: IT.11 | B46: MOTEUR AKİŞ VOLPİ GEARLESS 4,9KW MAX8 MAX10 240*7*6,5MM 1,0M/S VVVF +ENCODEUR | C46: MOTEUR | D46: Pc | E46: 240 | F46: N | G46: 1079 | H46: NO | J46: ARMOIRE
A47: IT.12 | B47: MOTEUR AKİŞ 2V MAX4 MAX6 | C47: MOTEUR | D47: Pc | E47: 320 | F47: N | G47: 1000 | H47: NO | J47: MOTEUR
A48: IT.13 | B48: MOTEUR AKİŞ 2V MAX8 | C48: MOTEUR | D48: Pc | E48: 380 | F48: N | G48: 1070 | H48: NO | J48: PORTE | Y48: Réf IT | Z48: Désignation FR normalisée | AA48: Dimension / Type | AB48: Matière | AC48: Prix $ | AD48: OUR NAME | AE48: TURKISH NAME | AG48: PREVIOUS PRICE | AH48: ACTUAL PRICE | AI48: Difference
A49: IT.14 | B49: CLASSIC BRACKET 60X60 (PATE) | C49: RAILS & ACCESSOIRES | D49: Pc | E49: 0.5 | F49: STEEL | G49: 0.6 | J49: OPÉRATEUR | Y49: IT,14 | Z49: Support classique 60×60 | AA49: PATE | AB49: ACIER GALVA | AC49: 0.94875 | AD49: CLASSIC BRACKET 60X60 (PATE) | AE49: 6*6*18 KONSOL (4mm) | AF49: 0.8602 | AG49: 0.6 | AH49: =+AF49/1.1 -> 0.782 | AI49: =+AH49/AG49 -> 1.3033333
A50: IT.15 | B50: CLASSIC BRACKET 60X80 (PATE) | C50: RAILS & ACCESSOIRES | D50: Pc | E50: 0.65 | F50: STEEL | G50: 0.9 | J50: CABINE & ARCADE | Y50: IT,15 | Z50: Support classique 60×80 | AA50: PATE | AB50: ACIER GALVA | AC50: 0.99935 | AD50: CLASSIC BRACKET 60X80 (PATE) | AE50: 6*8*18 KONSOL (4mm) | AF50: 0.99935 | AG50: 0.9 | AH50: =+AF50/1.1 -> 0.9085 | AI50: =+AH50/AG50 -> 1.0094444
A51: IT.16 | B51: CROMPO 50 | C51: RAILS & ACCESSOIRES | D51: Pc | E51: 0.11 | F51: GALVA | G51: 0.28 | J51: RAILS & ACCESSOIRES | Y51: IT,16 | Z51: Coulisseau rail 50 | AA51: T50 | AB51: ACIER GALVA | AC51: 0.3036 | AD51: CROMPO 50 | AE51: =+LOOKUP(A51,Y$49:Y$89,Z$49:Z$89) -> Interrupteur de fin de course | AF51: 0.3542 | AG51: 0.28 | AH51: =+AF51/1.1 -> 0.322 | AI51: =+AH51/AG51 -> 1.15
A52: IT.17 | B52: CROMPO 70 | C52: RAILS & ACCESSOIRES | D52: Pc | E52: 0.12 | F52: GALVA | G52: 0.37 | H52: YES | J52: CABLES & ACCESSOIRES | Y52: IT,17 | Z52: Coulisseau rail 70 | AA52: T70 | AB52: ACIER GALVA | AC52: 0.44275 | AD52: CROMPO 70 | AE52: =+LOOKUP(A52,Y$49:Y$89,Z$49:Z$89) -> Interrupteur de fin de course | AF52: 0.4807 | AG52: 0.37 | AH52: =+AF52/1.1 -> 0.437 | AI52: =+AH52/AG52 -> 1.1810811
A53: IT.18 | B53: SET BRACKET U | C53: RAILS & ACCESSOIRES | D53: SET | E53: 30 | F53: GALVA | G53: 35 | J53: CABLES ELECTRIQUES & ACCESSOIRES | Y53: IT,19 | Z53: Coulisseau rail 90 | AA53: T90 | AB53: ACIER GALVA | AC53: 0.44275 | AD53: - | AH53: =+AF53/1.1 -> 0
A54: IT.19 | B54: CROMPO 90 | C54: RAILS & ACCESSOIRES | D54: Pc | E54: 0.17 | F54: GALVA | G54: 0.47 | H54: YES | J54: BOUTONS | Y54: IT,21 | Z54: Boulon 8×30 | AA54: – | AB54: ACIER | AC54: – | AD54: CROMPO 90 | AE54: =+LOOKUP(A54,Y$49:Y$89,Z$49:Z$89) -> Interrupteur de fin de course | AF54: 0.61985 | AG54: 0.47 | AH54: =+AF54/1.1 -> 0.5635 | AI54: =+AH54/AG54 -> 1.1989362
A55: IT.20 | B55: SET BRACKET TYPE L | C55: RAILS & ACCESSOIRES | D55: SET | E55: 30 | F55: GALVA | G55: 50 | H55: YES | J55: GOSE | Y55: IT,22 | Z55: Boulon 12×25 | AA55: – | AB55: ACIER | AC55: – | AD55: - | AG55: 0.75 | AH55: =+AF55/1.1 -> 0
A56: IT.21 | B56: BOULON 8/30 | C56: RAILS & ACCESSOIRES | D56: Pc | E56: 0.02 | F56: GALVA | G56: 0.07 | H56: NO | J56: AUTRES | Y56: IT,23 | Z56: Boulon 12×40 | AA56: – | AB56: ACIER | AC56: – | AD56: BOULON 8/30 | AE56: =+LOOKUP(A56,Y$49:Y$89,Z$49:Z$89) -> Interrupteur de fin de course | AG56: 0.07 | AH56: =+AF56/1.1 -> 0
A57: IT.22 | B57: BOULON 12/25 | C57: RAILS & ACCESSOIRES | D57: Pc | E57: 0.04 | F57: GALVA | G57: 0.18 | H57: NO | Y57: IT,24 | Z57: Boulon 14×70 | AA57: – | AB57: ACIER | AC57: – | AD57: BOULON 12/25 | AE57: =+LOOKUP(A57,Y$49:Y$89,Z$49:Z$89) -> Interrupteur de fin de course | AG57: 0.18 | AH57: =+AF57/1.1 -> 0
A58: IT.23 | B58: BOULON 12/40 | C58: RAILS & ACCESSOIRES | D58: Pc | E58: 0.05 | F58: GALVA | G58: 0.2 | Y58: IT,25 | Z58: Cheville métallique 12×100 | AA58: – | AB58: ACIER GALVA | AC58: 0.3289 | AD58: BOULON 12/40 | AE58: =+LOOKUP(A58,Y$49:Y$89,Z$49:Z$89) -> Interrupteur de fin de course | AG58: 0.2 | AH58: =+AF58/1.1 -> 0
A59: IT.24 | B59: BOULON 14/70 | C59: RAILS & ACCESSOIRES | D59: Pc | F59: GALVA | G59: 0.3 | Y59: IT,26 | Z59: Guide rail ascenseur 50 | AA59: – | AB59: ACIER | AC59: – | AD59: BOULON 14/70 | AE59: =+LOOKUP(A59,Y$49:Y$89,Z$49:Z$89) -> Interrupteur de fin de course | AG59: 0.3 | AH59: =+AF59/1.1 -> 0
A60: IT.25 | B60: CHEVEILLE 12/100 | C60: RAILS & ACCESSOIRES | D60: Pc | E60: 0.09 | F60: GALVA | G60: 0.21 | Y60: IT,27 | Z60: Guide rail ascenseur 70 | AA60: – | AB60: ACIER | AC60: – | AD60: CHEVEILLE 12/100 | AE60: KLİPSLİ ÇELİK DÜBEL M-12*109 | AF60: 0.29095 | AG60: 0.21 | AH60: =+AF60/1.1 -> 0.2645 | AI60: =+AH60/AG60 -> 1.2595238
A61: IT.26 | B61: GUIDE RAIL 50 | C61: RAILS & ACCESSOIRES | D61: Pc | E61: 27 | F61: STEEL | G61: 17.4 | Y61: IT,28 | Z61: Kit rail 50+70 | AA61: – | AB61: ACIER | AC61: – | AD61: GUIDE RAIL 50 | AE61: =+LOOKUP(A61,Y$49:Y$89,Z$49:Z$89) -> Interrupteur de fin de course | AG61: 17.4 | AH61: =+AF61/1.1 -> 0 | AI61: =+AH61/AG61 -> 0
A62: IT.27 | B62: GUIDE RAIL 70 | C62: RAILS & ACCESSOIRES | D62: Pc | E62: 51 | F62: STEEL | G62: 34.6 | H62: YES | Y62: IT,29 | Z62: Guide rail ascenseur 90 | AA62: – | AB62: ACIER | AC62: – | AD62: GUIDE RAIL 70 | AE62: =+LOOKUP(A62,Y$49:Y$89,Z$49:Z$89) -> Interrupteur de fin de course | AG62: 34.6 | AH62: =+AF62/1.1 -> 0 | AI62: =+AH62/AG62 -> 0
A63: IT.28 | B63: SET RAIL : 50 + 70 | C63: RAILS & ACCESSOIRES | D63: SET | E63: 0.36 | F63: STEEL | G63: 52 | H63: YES | Y63: IT,30 | Z63: Garniture coulisseau 50 | AA63: – | AB63: POLYURÉTHANE | AC63: 1.1385 | AD63: SET RAIL : 50 + 70 | AE63: =+LOOKUP(A63,Y$49:Y$89,Z$49:Z$89) -> Interrupteur de fin de course | AG63: 52 | AH63: =+AF63/1.1 -> 0 | AI63: =+AH63/AG63 -> 0
A64: IT.29 | B64: GUIDE RAIL 90 | C64: RAILS & ACCESSOIRES | D64: Pc | F64: STEEL | G64: 65 | Y64: IT,31 | Z64: Câble traction Ø10mm | AA64: – | AB64: ACIER | AC64: 1.0373 | AD64: GUIDE RAIL 90 | AE64: =+LOOKUP(A64,Y$49:Y$89,Z$49:Z$89) -> Interrupteur de fin de course | AG64: 65 | AH64: =+AF64/1.1 -> 0 | AI64: =+AH64/AG64 -> 0
A65: IT.30 | B65: GARNITURE COULISSEAU 50 | C65: RAILS & ACCESSOIRES | D65: SET | E65: 0.14 | F65: N | G65: 0.5 | H65: NO | Y65: IT,32 | Z65: Câble gearless Ø6,5mm | AA65: – | AB65: ACIER | AC65: 0.82225 | AD65: GARNITURE COULISSEAU 50 | AE65: PLASTİK PATEN T50 5mm | AF65: 0.759 | AG65: 0.5 | AH65: =+AF65/1.1 -> 0.69 | AI65: =+AH65/AG65 -> 1.38
A66: IT.31 | B66: CABLE TRACTION (10mm) | C66: CABLES & ACCESSOIRES | D66: M | E66: 0.4 | F66: STEEL | G66: 0.92 | H66: NO | Y66: IT,33 | Z66: Câble régulateur Ø6mm | AA66: – | AB66: ACIER | AC66: 0.31625 | AD66: CABLE TRACTION (10mm) | AE66: =+LOOKUP(A66,Y$49:Y$89,Z$49:Z$89) -> Interrupteur de fin de course | AF66: =IF(AE66<>"",LOOKUP(A66,Y$49:Y$89,AC$49:AC$89),"") -> 2.783 | AG66: 0.92 | AH66: =+AF66/1.1 -> 2.53 | AI66: =+AH66/AG66 -> 2.75
A67: IT.32 | B67: CABLE GEARLESS (6,5mm) | C67: CABLES & ACCESSOIRES | D67: M | G67: 0.87 | H67: NO | Y67: IT,34 | Z67: Tige filetée Ø10mm | AA67: – | AB67: ACIER | AC67: – | AD67: CABLE GEARLESS (6,5mm) | AE67: =+LOOKUP(A67,Y$49:Y$89,Z$49:Z$89) -> Interrupteur de fin de course | AF67: =IF(AE67<>"",LOOKUP(A67,Y$49:Y$89,AC$49:AC$89),"") -> 2.783 | AG67: 0.87 | AH67: =+AF67/1.1 -> 2.53 | AI67: =+AH67/AG67 -> 2.908046
A68: IT.33 | B68: CABLE REGULATEUR (6mm) | C68: CABLES & ACCESSOIRES | E68: 0.22 | F68: STEEL | G68: 0.28 | Y68: IT,35 | Z68: Tige filetée Ø6,5mm | AA68: – | AB68: ACIER | AC68: – | AD68: CABLE REGULATEUR (6mm) | AE68: =+LOOKUP(A68,Y$49:Y$89,Z$49:Z$89) -> Interrupteur de fin de course | AF68: =IF(AE68<>"",LOOKUP(A68,Y$49:Y$89,AC$49:AC$89),"") -> 2.783 | AG68: 0.28 | AH68: =+AF68/1.1 -> 2.53 | AI68: =+AH68/AG68 -> 9.0357143
A69: IT.34 | B69: TIRANDS 10MM | C69: CABLES & ACCESSOIRES | D69: Pc | E69: 1.09 | F69: GALVA | G69: 2.15 | H69: NO | Y69: IT,36 | Z69: Serre-câble Ø10mm | AA69: – | AB69: ACIER GALVA | AC69: 0.26565 | AD69: TIRANDS 10MM | AE69: =+LOOKUP(A69,Y$49:Y$89,Z$49:Z$89) -> Interrupteur de fin de course | AG69: 2.15 | AH69: =+AF69/1.1 -> 0 | AI69: =+AH69/AG69 -> 0
A70: IT.35 | B70: TIRANDS 6,5MM | C70: CABLES & ACCESSOIRES | D70: Pc | F70: GALVA | G70: 2.15 | H70: NO | Y70: IT,37 | Z70: Serre-câble Ø6,5–8mm | AA70: – | AB70: ACIER GALVA | AC70: 0.1518 | AD70: TIRANDS 6,5MM | AE70: =+LOOKUP(A70,Y$49:Y$89,Z$49:Z$89) -> Interrupteur de fin de course | AG70: 2.15 | AH70: =+AF70/1.1 -> 0 | AI70: =+AH70/AG70 -> 0
A71: IT.36 | B71: SERRE CABLE DIAM 10mm * | C71: CABLES & ACCESSOIRES | D71: Pc | E71: 0.07 | F71: GALVA | G71: 0.2 | H71: NO | Y71: IT,38 | Z71: Serre-câble Ø6mm | AA71: – | AB71: ACIER GALVA | AC71: 0.08855 | AD71: SERRE CABLE DIAM 10mm * | AE71: =+LOOKUP(A71,Y$49:Y$89,Z$49:Z$89) -> Interrupteur de fin de course | AF71: =IF(AE71<>"",LOOKUP(A71,Y$49:Y$89,AC$49:AC$89),"") -> 2.783 | AG71: 0.2 | AH71: =+AF71/1.1 -> 2.53 | AI71: =+AH71/AG71 -> 12.65
A72: IT.37 | B72: SERRE CABLE DIAM 6,5mm * | C72: CABLES & ACCESSOIRES | F72: GALVA | G72: 0.15 | H72: NO | Y72: IT,39 | Z72: Chaîne d’équilibrage 50kg | AA72: 1,5kg | AB72: ACIER | AC72: 4.4275 | AD72: SERRE CABLE DIAM 6,5mm * | AE72: =+LOOKUP(A72,Y$49:Y$89,Z$49:Z$89) -> Interrupteur de fin de course | AF72: =IF(AE72<>"",LOOKUP(A72,Y$49:Y$89,AC$49:AC$89),"") -> 2.783 | AG72: 0.15 | AH72: =+AF72/1.1 -> 2.53 | AI72: =+AH72/AG72 -> 16.866667
A73: IT.38 | B73: SERRE CABLE DIAM 6mm * | C73: CABLES & ACCESSOIRES | D73: Pc | E73: 0.01 | F73: GALVA | G73: 0.1 | H73: NO | Y73: IT,40 | Z73: Collecteur d’huile | AA73: – | AB73: ACIER | AC73: 0.4807 | AD73: SERRE CABLE DIAM 6mm * | AE73: =+LOOKUP(A73,Y$49:Y$89,Z$49:Z$89) -> Interrupteur de fin de course | AF73: =IF(AE73<>"",LOOKUP(A73,Y$49:Y$89,AC$49:AC$89),"") -> 2.783 | AG73: 0.1 | AH73: =+AF73/1.1 -> 2.53 | AI73: =+AH73/AG73 -> 25.3
A74: IT.39 | B74: GOSE 96 CM (50 KG) | C74: GOSE | D74: Pc | E74: 50 | F74: CONCRETE | G74: 6 | H74: NO | Y74: IT,41 | Z74: Boîte de lubrification | AA74: – | AB74: ACIER | AC74: 1.6445
A75: IT.40 | B75: COLLECTEUR D'HUILE | C75: AUTRES | D75: Pc | E75: 0.07 | F75: PVC | G75: 0.25 | H75: NO | Y75: IT,42 | Z75: Coulisseaux cabine | AA75: – | AB75: POLYURÉTHANE | AC75: 9.108 | AD75: COLLECTEUR D'HUILE | AE75: =+LOOKUP(A75,Y$49:Y$89,Z$49:Z$89) -> Interrupteur de fin de course | AF75: =IF(AE75<>"",LOOKUP(A75,Y$49:Y$89,AC$49:AC$89),"") -> 2.783 | AG75: 0.25 | AH75: =+AF75/1.1 -> 2.53 | AI75: =+AH75/AG75 -> 10.12
A76: IT.41 | B76: BOITE DE LUBRIFICATION | C76: AUTRES | D76: Pc | E76: 0.3 | F76: PVC | G76: 1 | H76: NO | Y76: IT,43 | Z76: Coulisseaux contre-poids | AA76: – | AB76: POLYURÉTHANE | AC76: 4.74375 | AD76: BOITE DE LUBRIFICATION | AE76: =+LOOKUP(A76,Y$49:Y$89,Z$49:Z$89) -> Interrupteur de fin de course | AF76: =IF(AE76<>"",LOOKUP(A76,Y$49:Y$89,AC$49:AC$89),"") -> 2.783 | AG76: 1 | AH76: =+AF76/1.1 -> 2.53 | AI76: =+AH76/AG76 -> 2.53
A77: IT.42 | B77: COULISSEAUX CABIN | C77: AUTRES | D77: Pc | E77: 1 | F77: STEEL | G77: 6 | H77: NO | Y77: IT,45 | Z77: Poulie renvoi 5×10 | AA77: – | AB77: ACIER | AC77: – | AD77: COULISSEAUX CABIN | AE77: ALUMİNYÜM PATEN T70 - 9mm | AF77: 8.2225 | AG77: 6 | AH77: =+AF77/1.1 -> 7.475 | AI77: =+AH77/AG77 -> 1.2458333 | AJ77: KABİN SAC PATENİ T90 - 16mm | AK77: =9.108/1.1 -> 8.28 | AL77: =+AK77/AG77 -> 1.38
A78: IT.43 | B78: COULISSEAUX CONTRE-POIDS | C78: AUTRES | D78: Pc | E78: 0.6 | F78: STEEL | G78: 3.5 | H78: NO | Y78: IT,46 | Z78: Kit tampon cabine & CP | AA78: Complet | AB78: POLYURÉTHANE | AC78: 10.373 | AD78: COULISSEAUX CONTRE-POIDS | AE78: ALUMİNYÜM PATEN T50 - 5mm | AF78: 8.2225 | AG78: 3.5 | AH78: =+AF78/1.1 -> 7.475 | AI78: =+AH78/AG78 -> 2.1357143 | AJ78: AĞIRLIK SAC PATENİ T50 - 5mm | AK78: =4.74375/1.1 -> 4.3125 | AL78: =+AK78/AG78 -> 1.2321429
A79: IT.44 | B79: GARNITURE COULISSEAU 70 | C79: AUTRES | D79: Pc | E79: 0.14 | F79: PVC | G79: 0.5 | H79: NO | Y79: IT,53 | Z79: Goulotte câble 40×40 (2m) | AA79: – | AB79: PVC | AC79: 0.4807 | AD79: GARNITURE COULISSEAU 70 | AF79: =IF(AE79<>"",LOOKUP(A79,Y$49:Y$89,AC$49:AC$89),"") | AG79: 0.5 | AH79: =+AF79/1.1 -> #VALUE! | AI79: =+AH79/AG79 -> #VALUE!
A80: IT.45 | B80: POULIE RENVOI 5*10 GEARBOX | C80: AUTRES | D80: Pc | E80: 20 | F80: GALVA | G80: 60 | H80: NO | Y80: IT,54 | Z80: Tube spiralé Ø14mm | AA80: – | AB80: PVC | AC80: 0.11385 | AD80: POULIE RENVOI 5*10 GEARBOX | AE80: =+LOOKUP(A80,Y$49:Y$89,Z$49:Z$89) -> Interrupteur de fin de course | AG80: 60 | AH80: =+AF80/1.1 -> 0 | AI80: =+AH80/AG80 -> 0
A81: IT.46 | B81: BUFFER CABIN/C,P / LES BOUDINS SET COMPLET | C81: AUTRES | D81: SET | E81: 22 | F81: GALVA | G81: 33 | H81: NO | Y81: IT,55 | Z81: Bouton cabine ascenseur 2M | AA81: – | AB81: PLASTIQUE | AC81: – | AD81: BUFFER CABIN/C,P / LES BOUDINS SET COMPLET | AE81: =+LOOKUP(A81,Y$49:Y$89,Z$49:Z$89) -> Interrupteur de fin de course | AF81: 37.95 | AG81: 33 | AH81: =+AF81/1.1 -> 34.5 | AI81: =+AH81/AG81 -> 1.0454545
A82: IT.47 | B82: CABLE 0,75MM | C82: CABLES ELECTRIQUES & ACCESSOIRES | D82: M | E82: 0.02 | F82: COPPER | G82: 0.023 | H82: NO | Y82: IT,56 | Z82: Bouton cabine ascenseur 1M | AA82: – | AB82: PLASTIQUE | AC82: – | AD82: CABLE 0,75MM | AF82: =IF(AE82<>"",LOOKUP(A82,Y$49:Y$89,AC$49:AC$89),"") | AG82: 0.023 | AH82: =+AF82/1.1 -> #VALUE! | AI82: =+AH82/AG82 -> #VALUE!
A83: IT.48 | B83: CABLE 4MM | C83: CABLES ELECTRIQUES & ACCESSOIRES | D83: M | E83: 0.03 | F83: COPPER | G83: 0.107 | H83: NO | Y83: IT,57 | Z83: Bouton palier avec afficheur | AA83: – | AB83: PLASTIQUE | AC83: – | AD83: CABLE 4MM | AF83: =IF(AE83<>"",LOOKUP(A83,Y$49:Y$89,AC$49:AC$89),"") | AG83: 0.107 | AH83: =+AF83/1.1 -> #VALUE! | AI83: =+AH83/AG83 -> #VALUE!
A84: IT.49 | B84: CÂBLE NUMÉRIQUE DT/13 | C84: CABLES ELECTRIQUES & ACCESSOIRES | D84: M | E84: 0.04 | F84: COPPER | G84: 0.122 | H84: NO | I84: =50*1.65*9.8 -> 808.5 | Y84: IT,58 | Z84: Bouton palier | AA84: – | AB84: PLASTIQUE | AC84: – | AD84: CÂBLE NUMÉRIQUE DT/13 | AF84: =IF(AE84<>"",LOOKUP(A84,Y$49:Y$89,AC$49:AC$89),"") | AG84: 0.122 | AH84: =+AF84/1.1 -> #VALUE! | AI84: =+AH84/AG84 -> #VALUE!
A85: IT.50 | B85: TTR CABLE 3*0,75MM | C85: CABLES ELECTRIQUES & ACCESSOIRES | D85: M | E85: 0.05 | F85: COPPER | G85: 0.137 | H85: NO | Y85: IT,59 | Z85: Indicateur d’étage | AA85: – | AB85: PLASTIQUE | AC85: – | AD85: TTR CABLE 3*0,75MM | AF85: =IF(AE85<>"",LOOKUP(A85,Y$49:Y$89,AC$49:AC$89),"") | AG85: 0.137 | AH85: =+AF85/1.1 -> #VALUE! | AI85: =+AH85/AG85 -> #VALUE!
A86: IT.51 | B86: CABLE SOUPLE 24 36 -> 75 DH / 24 -> 55 À 60 DH | C86: CABLES ELECTRIQUES & ACCESSOIRES | D86: M | E86: 1.2 | F86: COPPER | G86: 1.5433 | H86: NO | Y86: IT,60 | Z86: Boîte d’alarme | AA86: – | AB86: PLASTIQUE | AC86: 5.6925 | AD86: CABLE SOUPLE 24 36 -> 75 DH / 24 -> 55 À 60 DH | AF86: =IF(AE86<>"",LOOKUP(A86,Y$49:Y$89,AC$49:AC$89),"") | AG86: 1.5433 | AH86: =+AF86/1.1 -> #VALUE! | AI86: =+AH86/AG86 -> #VALUE!
A87: IT.52 | B87: SUPPORT CABLE SOUPLE TYPE RECTANGLE | C87: CABLES ELECTRIQUES & ACCESSOIRES | D87: M | E87: 0.3 | F87: COPPER | G87: 0.8 | H87: NO | Y87: IT,61 | Z87: Bouton de secours | AA87: – | AB87: PLASTIQUE | AC87: 1.6445 | AD87: SUPPORT CABLE SOUPLE TYPE RECTANGLE | AF87: =IF(AE87<>"",LOOKUP(A87,Y$49:Y$89,AC$49:AC$89),"") | AG87: 0.8 | AH87: =+AF87/1.1 -> #VALUE! | AI87: =+AH87/AG87 -> #VALUE!
A88: IT.53 | B88: WIRE DUCT GOULLOTTE 40X40 | C88: CABLES ELECTRIQUES & ACCESSOIRES | D88: M | E88: 0.5 | F88: COPPER | G88: 0.4 | H88: NO | Y88: IT,62 | Z88: Interrupteur à galet | AA88: – | AB88: ACIER | AC88: 2.84625 | AD88: WIRE DUCT GOULLOTTE 40X40 | AE88: =+LOOKUP(A88,Y$49:Y$89,Z$49:Z$89) -> Interrupteur de fin de course | AF88: =IF(AE88<>"",LOOKUP(A88,Y$49:Y$89,AC$49:AC$89),"") -> 2.783 | AG88: 0.4 | AH88: =+AF88/1.1 -> 2.53 | AI88: =+AH88/AG88 -> 6.325
A89: IT.54 | B89: TUBE SPIRALÉ 14MM | C89: CABLES ELECTRIQUES & ACCESSOIRES | D89: M | E89: 1 | F89: COPPER | G89: 0.09 | H89: NO | Y89: IT,63 | Z89: Interrupteur de fin de course | AA89: – | AB89: ACIER | AC89: 2.783 | AD89: TUBE SPIRALÉ 14MM | AE89: =+LOOKUP(A89,Y$49:Y$89,Z$49:Z$89) -> Interrupteur de fin de course | AF89: =IF(AE89<>"",LOOKUP(A89,Y$49:Y$89,AC$49:AC$89),"") -> 2.783 | AG89: 0.09 | AH89: =+AF89/1.1 -> 2.53 | AI89: =+AH89/AG89 -> 28.111111
A90: IT.55 | B90: BOUTONS DE CABINE D’ASCENSEUR 2M | C90: BOUTONS | D90: Pc | E90: 1.8 | F90: INOX | G90: 95 | H90: NO | AD90: BOUTONS DE CABINE D’ASCENSEUR 2M | AE90: =+LOOKUP(A90,Y$49:Y$89,Z$49:Z$89) -> Interrupteur de fin de course | AG90: 77.5 | AH90: =+AF90/1.1 -> 0 | AI90: =+AH90/AG90 -> 0
A91: IT.56 | B91: BOUTONS DE CABINE D’ASCENSEUR 1M | C91: BOUTONS | D91: Pc | E91: 1.2 | F91: INOX | G91: 80 | H91: NO | AD91: BOUTONS DE CABINE D’ASCENSEUR 1M | AE91: =+LOOKUP(A91,Y$49:Y$89,Z$49:Z$89) -> Interrupteur de fin de course | AG91: 67.5 | AH91: =+AF91/1.1 -> 0 | AI91: =+AH91/AG91 -> 0
A92: IT.57 | B92: BOUTON PALIER AVEC AFFICHEUR | C92: BOUTONS | D92: Pc | E92: 1.5 | F92: INOX | G92: 6.4 | H92: NO | AD92: BOUTON PALIER AVEC AFFICHEUR | AE92: =+LOOKUP(A92,Y$49:Y$89,Z$49:Z$89) -> Interrupteur de fin de course | AG92: 6.4 | AH92: =+AF92/1.1 -> 0 | AI92: =+AH92/AG92 -> 0
A93: IT.58 | B93: BOUTON PALIER | C93: BOUTONS | D93: Pc | E93: 1 | F93: INOX | G93: 4.1 | H93: NO | AD93: BOUTON PALIER | AE93: =+LOOKUP(A93,Y$49:Y$89,Z$49:Z$89) -> Interrupteur de fin de course | AG93: 4.1 | AH93: =+AF93/1.1 -> 0 | AI93: =+AH93/AG93 -> 0
A94: IT.59 | B94: INDICATEURS D’ATTERISSAGE | C94: AUTRES | D94: Pc | E94: 1.2 | F94: PVC | G94: 7.8 | H94: NO | AD94: INDICATEURS D’ATTERISSAGE | AE94: =+LOOKUP(A94,Y$49:Y$89,Z$49:Z$89) -> Interrupteur de fin de course | AG94: 7.8 | AH94: =+AF94/1.1 -> 0 | AI94: =+AH94/AG94 -> 0
A95: IT.60 | B95: BOÎTE D'ALARME | C95: AUTRES | D95: Pc | E95: 1 | F95: PVC | G95: 2 | H95: NO | AD95: BOÎTE D'ALARME | AE95: BATARYALI ALARM BUTONU | AF95: 5.6925 | AG95: 2 | AH95: =+AF95/1.1 -> 5.175 | AI95: =+AH95/AG95 -> 2.5875
A96: IT.61 | B96: BOUTON DE SECOURS | C96: AUTRES | D96: Pc | E96: 0.4 | F96: PVC | G96: 1.6 | H96: NO | AD96: BOUTON DE SECOURS | AE96: MANTAR STOP | AF96: 1.771 | AG96: 1.6 | AH96: =+AF96/1.1 -> 1.61 | AI96: =+AH96/AG96 -> 1.00625 | AJ96: ALARM BUTONU | AK96: =1.6445/1.1 -> 1.495 | AL96: =+AK96/AG96 -> 0.934375
A97: IT.62 | B97: ROLLER SWITCH | C97: AUTRES | D97: Pc | E97: 0.6 | F97: - | G97: 2.5 | H97: yes 20% | AD97: ROLLER SWITCH | AE97: MAKARALI SWİTCH | AF97: 2.84625 | AG97: 2.5 | AH97: =+AF97/1.1 -> 2.5875 | AI97: =+AH97/AG97 -> 1.035
A98: IT.63 | B98: LIMIT SWITCH | C98: AUTRES | D98: Pc | E98: 0.5 | F98: - | G98: 0 | H98: NO | AD98: LIMIT SWITCH | AE98: =+LOOKUP(A98,Y$49:Y$89,Z$49:Z$89) -> Interrupteur de fin de course | AF98: =IF(AE98<>"",LOOKUP(A98,Y$49:Y$89,AC$49:AC$89),"") -> 2.783 | AG98: 0 | AH98: =+AF98/1.1 -> 2.53 | AI98: =+AH98/AG98 -> #DIV/0!
A99: IT.64 | B99: PHOTOCELLULE | C99: AUTRES | D99: Pc | E99: 0.8 | F99: - | G99: 53 | H99: NO
A100: IT.65 | B100: OPERATEUR CARTE ARKEL KM-10 | C100: AUTRES | D100: Pc | E100: 3 | F100: - | G100: 60 | H100: NO
A101: IT.66 | B101: OPERATEUR CARTE KM-10 COPY | C101: AUTRES | D101: Pc | E101: 2.5 | F101: - | G101: 36 | H101: NO
...

Sheet Pricing sheet
B2: Items Pricing Order Lift Morocco | I2: 2835
H3: =20%*9310 -> 1862 | I3: =+G34*20.25% -> 2897.37
E4: Hypothèse : conteneur par mois de vente d'une valeur de 250000 MAD, 2 recrues full time
E5: Nombre de conteneur par mois | F5: Valeur de conteneur | G5: 1 | H5: 300000
G6: USD to MAD | I6: Aléas transport | J6: Comission vente (sur prix initial)
G7: =+'Pricing Turkey'!K2 -> 9.8 | I7: 0.15 | J7: 0.03 | K7: 0.07 | L7: 0.25
I8: Prix conteneur en USD | J8: Charges par mois
I9: 1500 | J9: =SUM(J11:J17) -> 54700
I10: Prix camion TTC | J10: Voitures amortissement
I11: 3700 | J11: 8000
I12: Déchargement | J12: RH
I13: 1000 | J13: 35000
I14: Chargement | J14: Location (bureau + stock)
I15: 1000 | J15: =4700+3500 -> 8200
I16: Frais de Port et agent maritime | J16: Comptable et autre
I17: 5000 | J17: 3500
A20: Ref | B20: Description | C20: Composante | D20: Unité | E20: Poids | F20: Acier (O/N) | G20: Prix Turquie | H20: Douane | I20: Transport & Transitaire | J20: Charge équipe/bureau | K20: Impots | L20: Marge | M20: Prix final sans stock (min) | N20: Prix final sans stock (max) | O20: Prix final stock
A21: =+'Pricing Turkey'!A3 -> IT.1 | B21: =+'Pricing Turkey'!B3 -> SET CABINE STANDARD INOX 1200/1100 + ARCADES & ACCESSOIRES GEARBOX | C21: =+'Pricing Turkey'!C3 -> CABINE & ARCADE | D21: =+'Pricing Turkey'!D3 -> SET | E21: =+'Pricing Turkey'!E3 -> 650 | F21: =+'Pricing Turkey'!F3 -> INOX | G21: ='Pricing Turkey'!G3*G$7 -> 14700 | H21: =IF(F21="STEEL",MAX(G21,E21*13)*20.25%,IF(F21="GALVA",MAX(G21,E21*24)*20.25%,IF(F21="INOX",MAX(G21,E21*40)*20.25%,IF(F21="COPPER",MAX(G21,E21*60)*20.25%,G21*20.25%)))) -> 5265 | I21: =+((I$9*G$7+I$11+I$13+I$15+I$17)*(1+I$7)+2500)/($G$5*$H$5)*G21 -> 1553.79 | J21: =(J$9+J$7*G21)/($G$5*$H$5)*G21 -> 2701.909 | K21: =K$7*G21 -> 1029 | L21: =+G21*L$7 -> 3675 | M21: =+G21+H21+I21+J21*50%+K21+L21*30% -> 25001.245 | N21: =+G21+H21+I21+J21*50%+K21+L21*50% -> 25736.245 | O21: =+SUM(H21:L21)+G21 -> 28924.699
A22: =+'Pricing Turkey'!A4 -> IT.1-1 | B22: =+'Pricing Turkey'!B4 -> CABINE INOX 1000/900 STANDARD | C22: =+'Pricing Turkey'!C4 -> CABINE & ARCADE | D22: =+'Pricing Turkey'!D4 -> Pc | E22: =+'Pricing Turkey'!E4 -> 350 | F22: =+'Pricing Turkey'!F4 -> INOX | G22: ='Pricing Turkey'!G4*G$7 -> 9310 | H22: =IF(F22="STEEL",MAX(G22,E22*13)*20.25%,IF(F22="GALVA",MAX(G22,E22*24)*20.25%,IF(F22="INOX",MAX(G22,E22*40)*20.25%,IF(F22="COPPER",MAX(G22,E22*60)*20.25%,G22*20.25%)))) -> 2835 | I22: =+((I$9*G$7+I$11+I$13+I$15+I$17)*(1+I$7)+2500)/($G$5*$H$5)*G22 -> 984.067 | J22: =(J$9+J$7*G22)/($G$5*$H$5)*G22 -> 1706.1909 | K22: =K$7*G22 -> 651.7 | L22: =+G22*L$7 -> 2327.5 | M22: =+G22+H22+I22+J22*50%+K22+L22*30% -> 15332.112 | N22: =+G22+H22+I22+J22*50%+K22+L22*50% -> 15797.612 | O22: =+SUM(H22:L22)+G22 -> 17814.458
A23: =+'Pricing Turkey'!A5 -> IT.1-2 | B23: =+'Pricing Turkey'!B5 -> CABINE INOX 1000/900 PERSONALISÉE | C23: =+'Pricing Turkey'!C5 -> CABINE & ARCADE | D23: =+'Pricing Turkey'!D5 -> Pc | E23: =+'Pricing Turkey'!E5 -> 350 | F23: =+'Pricing Turkey'!F5 -> INOX | G23: ='Pricing Turkey'!G5*G$7 -> 11760 | H23: =IF(F23="STEEL",MAX(G23,E23*13)*20.25%,IF(F23="GALVA",MAX(G23,E23*24)*20.25%,IF(F23="INOX",MAX(G23,E23*40)*20.25%,IF(F23="COPPER",MAX(G23,E23*60)*20.25%,G23*20.25%)))) -> 2835 | I23: =+((I$9*G$7+I$11+I$13+I$15+I$17)*(1+I$7)+2500)/($G$5*$H$5)*G23 -> 1243.032 | J23: =(J$9+J$7*G23)/($G$5*$H$5)*G23 -> 2158.0698 | K23: =K$7*G23 -> 823.2 | L23: =+G23*L$7 -> 2940 | M23: =+G23+H23+I23+J23*50%+K23+L23*30% -> 18622.267 | N23: =+G23+H23+I23+J23*50%+K23+L23*50% -> 19210.267 | O23: =+SUM(H23:L23)+G23 -> 21759.302
A24: =+'Pricing Turkey'!A6 -> IT.1-3 | B24: =+'Pricing Turkey'!B6 -> CABINE INOX 1100/1000 STANDARD | C24: =+'Pricing Turkey'!C6 -> CABINE & ARCADE | D24: =+'Pricing Turkey'!D6 -> Pc | E24: =+'Pricing Turkey'!E6 -> 350 | F24: =+'Pricing Turkey'!F6 -> INOX | G24: ='Pricing Turkey'!G6*G$7 -> 9996 | H24: =IF(F24="STEEL",MAX(G24,E24*13)*20.25%,IF(F24="GALVA",MAX(G24,E24*24)*20.25%,IF(F24="INOX",MAX(G24,E24*40)*20.25%,IF(F24="COPPER",MAX(G24,E24*60)*20.25%,G24*20.25%)))) -> 2835 | I24: =+((I$9*G$7+I$11+I$13+I$15+I$17)*(1+I$7)+2500)/($G$5*$H$5)*G24 -> 1056.5772 | J24: =(J$9+J$7*G24)/($G$5*$H$5)*G24 -> 1832.596 | K24: =K$7*G24 -> 699.72 | L24: =+G24*L$7 -> 2499 | M24: =+G24+H24+I24+J24*50%+K24+L24*30% -> 16253.295 | N24: =+G24+H24+I24+J24*50%+K24+L24*50% -> 16753.095 | O24: =+SUM(H24:L24)+G24 -> 18918.893
A25: =+'Pricing Turkey'!A7 -> IT.1-4 | B25: =+'Pricing Turkey'!B7 -> CABINE INOX 1100/1000 PERSONALISÉE | C25: =+'Pricing Turkey'!C7 -> CABINE & ARCADE | D25: =+'Pricing Turkey'!D7 -> Pc | E25: =+'Pricing Turkey'!E7 -> 350 | F25: =+'Pricing Turkey'!F7 -> INOX | G25: ='Pricing Turkey'!G7*G$7 -> 12936 | H25: =IF(F25="STEEL",MAX(G25,E25*13)*20.25%,IF(F25="GALVA",MAX(G25,E25*24)*20.25%,IF(F25="INOX",MAX(G25,E25*40)*20.25%,IF(F25="COPPER",MAX(G25,E25*60)*20.25%,G25*20.25%)))) -> 2835 | I25: =+((I$9*G$7+I$11+I$13+I$15+I$17)*(1+I$7)+2500)/($G$5*$H$5)*G25 -> 1367.3352 | J25: =(J$9+J$7*G25)/($G$5*$H$5)*G25 -> 2375.398 | K25: =K$7*G25 -> 905.52 | L25: =+G25*L$7 -> 3234 | M25: =+G25+H25+I25+J25*50%+K25+L25*30% -> 20201.754 | N25: =+G25+H25+I25+J25*50%+K25+L25*50% -> 20848.554 | O25: =+SUM(H25:L25)+G25 -> 23653.253
A26: =+'Pricing Turkey'!A8 -> IT.1-5 | B26: =+'Pricing Turkey'!B8 -> CABINE INOX 1200/1100 STANDARD | C26: =+'Pricing Turkey'!C8 -> CABINE & ARCADE | D26: =+'Pricing Turkey'!D8 -> Pc | E26: =+'Pricing Turkey'!E8 -> 350 | F26: =+'Pricing Turkey'!F8 -> INOX | G26: ='Pricing Turkey'!G8*G$7 -> 10682 | H26: =IF(F26="STEEL",MAX(G26,E26*13)*20.25%,IF(F26="GALVA",MAX(G26,E26*24)*20.25%,IF(F26="INOX",MAX(G26,E26*40)*20.25%,IF(F26="COPPER",MAX(G26,E26*60)*20.25%,G26*20.25%)))) -> 2835 | I26: =+((I$9*G$7+I$11+I$13+I$15+I$17)*(1+I$7)+2500)/($G$5*$H$5)*G26 -> 1129.0874 | J26: =(J$9+J$7*G26)/($G$5*$H$5)*G26 -> 1959.0952 | K26: =K$7*G26 -> 747.74 | L26: =+G26*L$7 -> 2670.5 | M26: =+G26+H26+I26+J26*50%+K26+L26*30% -> 17174.525 | N26: =+G26+H26+I26+J26*50%+K26+L26*50% -> 17708.625 | O26: =+SUM(H26:L26)+G26 -> 20023.423
A27: =+'Pricing Turkey'!A9 -> IT.1-6 | B27: =+'Pricing Turkey'!B9 -> CABINE INOX 1200/1100 PERSONALISÉE | C27: =+'Pricing Turkey'!C9 -> CABINE & ARCADE | D27: =+'Pricing Turkey'!D9 -> Pc | E27: =+'Pricing Turkey'!E9 -> 350 | F27: =+'Pricing Turkey'!F9 -> INOX | G27: ='Pricing Turkey'!G9*G$7 -> 13622 | H27: =IF(F27="STEEL",MAX(G27,E27*13)*20.25%,IF(F27="GALVA",MAX(G27,E27*24)*20.25%,IF(F27="INOX",MAX(G27,E27*40)*20.25%,IF(F27="COPPER",MAX(G27,E27*60)*20.25%,G27*20.25%)))) -> 2835 | I27: =+((I$9*G$7+I$11+I$13+I$15+I$17)*(1+I$7)+2500)/($G$5*$H$5)*G27 -> 1439.8454 | J27: =(J$9+J$7*G27)/($G$5*$H$5)*G27 -> 2502.3006 | K27: =K$7*G27 -> 953.54 | L27: =+G27*L$7 -> 3405.5 | M27: =+G27+H27+I27+J27*50%+K27+L27*30% -> 21123.186 | N27: =+G27+H27+I27+J27*50%+K27+L27*50% -> 21804.286 | O27: =+SUM(H27:L27)+G27 -> 24758.186
A28: =+'Pricing Turkey'!A10 -> IT.1-13 | B28: =+'Pricing Turkey'!B10 -> CABINE INOX 1400/1300 STANDARD | C28: =+'Pricing Turkey'!C10 -> CABINE & ARCADE | D28: =+'Pricing Turkey'!D10 -> SET | E28: =+'Pricing Turkey'!E10 -> 350 | F28: =+'Pricing Turkey'!F10 -> STEEL | G28: ='Pricing Turkey'!G10*G$7 -> 13132 | H28: =IF(F28="STEEL",MAX(G28,E28*13)*20.25%,IF(F28="GALVA",MAX(G28,E28*24)*20.25%,IF(F28="INOX",MAX(G28,E28*40)*20.25%,IF(F28="COPPER",MAX(G28,E28*60)*20.25%,G28*20.25%)))) -> 2659.23 | I28: =+((I$9*G$7+I$11+I$13+I$15+I$17)*(1+I$7)+2500)/($G$5*$H$5)*G28 -> 1388.0524 | J28: =(J$9+J$7*G28)/($G$5*$H$5)*G28 -> 2411.6463 | K28: =K$7*G28 -> 919.24 | L28: =+G28*L$7 -> 3283 | M28: =+G28+H28+I28+J28*50%+K28+L28*30% -> 20289.246 | N28: =+G28+H28+I28+J28*50%+K28+L28*50% -> 20945.846 | O28: =+SUM(H28:L28)+G28 -> 23793.169
A29: =+'Pricing Turkey'!A11 -> IT.1-14 | B29: =+'Pricing Turkey'!B11 -> CABINE INOX 1400/1300 PERSONALISÉE | C29: =+'Pricing Turkey'!C11 -> CABINE & ARCADE | D29: =+'Pricing Turkey'!D11 -> SET | E29: =+'Pricing Turkey'!E11 -> 350 | F29: =+'Pricing Turkey'!F11 -> STEEL | G29: ='Pricing Turkey'!G11*G$7 -> 17052 | H29: =IF(F29="STEEL",MAX(G29,E29*13)*20.25%,IF(F29="GALVA",MAX(G29,E29*24)*20.25%,IF(F29="INOX",MAX(G29,E29*40)*20.25%,IF(F29="COPPER",MAX(G29,E29*60)*20.25%,G29*20.25%)))) -> 3453.03 | I29: =+((I$9*G$7+I$11+I$13+I$15+I$17)*(1+I$7)+2500)/($G$5*$H$5)*G29 -> 1802.3964 | J29: =(J$9+J$7*G29)/($G$5*$H$5)*G29 -> 3138.2251 | K29: =K$7*G29 -> 1193.64 | L29: =+G29*L$7 -> 4263 | M29: =+G29+H29+I29+J29*50%+K29+L29*30% -> 26349.079 | N29: =+G29+H29+I29+J29*50%+K29+L29*50% -> 27201.679 | O29: =+SUM(H29:L29)+G29 -> 30902.291
A30: =+'Pricing Turkey'!A12 -> IT.1-17 | B30: =+'Pricing Turkey'!B12 -> CABINE 1000/900 PANORAMIQUE | C30: =+'Pricing Turkey'!C12 -> CABINE & ARCADE | D30: =+'Pricing Turkey'!D12 -> Pc | E30: =+'Pricing Turkey'!E12 -> 350 | F30: =+'Pricing Turkey'!F12 -> INOX | G30: ='Pricing Turkey'!G12*G$7 -> 15680 | H30: =IF(F30="STEEL",MAX(G30,E30*13)*20.25%,IF(F30="GALVA",MAX(G30,E30*24)*20.25%,IF(F30="INOX",MAX(G30,E30*40)*20.25%,IF(F30="COPPER",MAX(G30,E30*60)*20.25%,G30*20.25%)))) -> 3175.2 | I30: =+((I$9*G$7+I$11+I$13+I$15+I$17)*(1+I$7)+2500)/($G$5*$H$5)*G30 -> 1657.376 | J30: =(J$9+J$7*G30)/($G$5*$H$5)*G30 -> 2883.5729 | K30: =K$7*G30 -> 1097.6 | L30: =+G30*L$7 -> 3920 | M30: =+G30+H30+I30+J30*50%+K30+L30*30% -> 24227.962 | N30: =+G30+H30+I30+J30*50%+K30+L30*50% -> 25011.962 | O30: =+SUM(H30:L30)+G30 -> 28413.749
A31: =+'Pricing Turkey'!A13 -> IT.1-18 | B31: =+'Pricing Turkey'!B13 -> CABINE 1100/1000 PANORAMIQUE | C31: =+'Pricing Turkey'!C13 -> CABINE & ARCADE | D31: =+'Pricing Turkey'!D13 -> Pc | E31: =+'Pricing Turkey'!E13 -> 350 | F31: =+'Pricing Turkey'!F13 -> INOX | G31: ='Pricing Turkey'!G13*G$7 -> 16660 | H31: =IF(F31="STEEL",MAX(G31,E31*13)*20.25%,IF(F31="GALVA",MAX(G31,E31*24)*20.25%,IF(F31="INOX",MAX(G31,E31*40)*20.25%,IF(F31="COPPER",MAX(G31,E31*60)*20.25%,G31*20.25%)))) -> 3373.65 | I31: =+((I$9*G$7+I$11+I$13+I$15+I$17)*(1+I$7)+2500)/($G$5*$H$5)*G31 -> 1760.962 | J31: =(J$9+J$7*G31)/($G$5*$H$5)*G31 -> 3065.4289 | K31: =K$7*G31 -> 1166.2 | L31: =+G31*L$7 -> 4165 | M31: =+G31+H31+I31+J31*50%+K31+L31*30% -> 25743.026 | N31: =+G31+H31+I31+J31*50%+K31+L31*50% -> 26576.026 | O31: =+SUM(H31:L31)+G31 -> 30191.241
A32: =+'Pricing Turkey'!A14 -> IT.1-19 | B32: =+'Pricing Turkey'!B14 -> CABINE 1200/1100 PANORAMIQUE | C32: =+'Pricing Turkey'!C14 -> CABINE & ARCADE | D32: =+'Pricing Turkey'!D14 -> Pc | E32: =+'Pricing Turkey'!E14 -> 350 | F32: =+'Pricing Turkey'!F14 -> INOX | G32: ='Pricing Turkey'!G14*G$7 -> 18130 | H32: =IF(F32="STEEL",MAX(G32,E32*13)*20.25%,IF(F32="GALVA",MAX(G32,E32*24)*20.25%,IF(F32="INOX",MAX(G32,E32*40)*20.25%,IF(F32="COPPER",MAX(G32,E32*60)*20.25%,G32*20.25%)))) -> 3671.325 | I32: =+((I$9*G$7+I$11+I$13+I$15+I$17)*(1+I$7)+2500)/($G$5*$H$5)*G32 -> 1916.341 | J32: =(J$9+J$7*G32)/($G$5*$H$5)*G32 -> 3338.573 | K32: =K$7*G32 -> 1269.1 | L32: =+G32*L$7 -> 4532.5 | M32: =+G32+H32+I32+J32*50%+K32+L32*30% -> 28015.803 | N32: =+G32+H32+I32+J32*50%+K32+L32*50% -> 28922.303 | O32: =+SUM(H32:L32)+G32 -> 32857.839
... A36: =+'Pricing Turkey'!A18 -> IT.1-23 | B36: =+'Pricing Turkey'!B18 -> CABINE 1400/1300 PANORAMIQUE | C36: =+'Pricing Turkey'!C18 -> CABINE & ARCADE | D36: =+'Pricing Turkey'!D18 -> Pc | E36: =+'Pricing Turkey'!E18 -> 350 | F36: =+'Pricing Turkey'!F18 -> INOX | G36: ='Pricing Turkey'!G18*G$7 -> 22540 | H36: =IF(F36="STEEL",MAX(G36,E36*13)*20.25%,IF(F36="GALVA",MAX(G36,E36*24)*20.25%,IF(F36="INOX",MAX(G36,E36*40)*20.25%,IF(F36="COPPER",MAX(G36,E36*60)*20.25%,G36*20.25%)))) -> 4564.35 | I36: =+((I$9*G$7+I$11+I$13+I$15+I$17)*(1+I$7)+2500)/($G$5*$H$5)*G36 -> 2382.478 | J36: =(J$9+J$7*G36)/($G$5*$H$5)*G36 -> 4160.5985 | K36: =K$7*G36 -> 1577.8 | L36: =+G36*L$7 -> 5635 | M36: =+G36+H36+I36+J36*50%+K36+L36*30% -> 34835.427 | N36: =+G36+H36+I36+J36*50%+K36+L36*50% -> 35962.427 | O36: =+SUM(H36:L36)+G36 -> 40860.226
A37: =+'Pricing Turkey'!A19 -> IT.1-7 | B37: =+'Pricing Turkey'!B19 -> ARCADE CABINE 1000/900 + ARCADE CONTRE-POIDS + TIRANDS + COULISSEAUX GEARBOX | C37: =+'Pricing Turkey'!C19 -> CABINE & ARCADE | D37: =+'Pricing Turkey'!D19 -> SET | E37: =+'Pricing Turkey'!E19 -> 200 | F37: =+'Pricing Turkey'!F19 -> STEEL | G37: ='Pricing Turkey'!G19*G$7 -> 4410 | H37: =IF(F37="STEEL",MAX(G37,E37*13)*20.25%,IF(F37="GALVA",MAX(G37,E37*24)*20.25%,IF(F37="INOX",MAX(G37,E37*40)*20.25%,IF(F37="COPPER",MAX(G37,E37*60)*20.25%,G37*20.25%)))) -> 893.025 | I37: =+((I$9*G$7+I$11+I$13+I$15+I$17)*(1+I$7)+2500)/($G$5*$H$5)*G37 -> 466.137 | J37: =(J$9+J$7*G37)/($G$5*$H$5)*G37 -> 806.03481 | K37: =K$7*G37 -> 308.7 | L37: =+G37*L$7 -> 1102.5 | M37: =+G37+H37+I37+J37*50%+K37+L37*30% -> 6811.6294 | N37: =+G37+H37+I37+J37*50%+K37+L37*70% -> 7252.6294 | O37: =+SUM(H37:L37)+G37 -> 7986.3968
A38: =+'Pricing Turkey'!A20 -> IT.1-8 | B38: =+'Pricing Turkey'!B20 -> ARCADE CABINE 1000/900 + ARCADE CONTRE-POIDS + TIRANDS + COULISSEAUX GEARLESS | C38: =+'Pricing Turkey'!C20 -> CABINE & ARCADE | D38: =+'Pricing Turkey'!D20 -> SET | E38: =+'Pricing Turkey'!E20 -> 200 | F38: =+'Pricing Turkey'!F20 -> STEEL | G38: ='Pricing Turkey'!G20*G$7 -> 6860 | H38: =IF(F38="STEEL",MAX(G38,E38*13)*20.25%,IF(F38="GALVA",MAX(G38,E38*24)*20.25%,IF(F38="INOX",MAX(G38,E38*40)*20.25%,IF(F38="COPPER",MAX(G38,E38*60)*20.25%,G38*20.25%)))) -> 1389.15 | I38: =+((I$9*G$7+I$11+I$13+I$15+I$17)*(1+I$7)+2500)/($G$5*$H$5)*G38 -> 725.102 | J38: =(J$9+J$7*G38)/($G$5*$H$5)*G38 -> 1255.5126 | K38: =K$7*G38 -> 480.2 | L38: =+G38*L$7 -> 1715 | M38: =+G38+H38+I38+J38*50%+K38+L38*30% -> 10596.708 | N38: =+G38+H38+I38+J38*50%+K38+L38*70% -> 11282.708 | O38: =+SUM(H38:L38)+G38 -> 12424.965
A39: =+'Pricing Turkey'!A21 -> IT.1-9 | B39: =+'Pricing Turkey'!B21 -> ARCADE CABINE 1100/1000 + ARCADE CONTRE-POIDS + TIRANDS + COULISSEAUX GEARBOX | C39: =+'Pricing Turkey'!C21 -> CABINE & ARCADE | D39: =+'Pricing Turkey'!D21 -> SET | E39: =+'Pricing Turkey'!E21 -> 200 | F39: =+'Pricing Turkey'!F21 -> STEEL | G39: ='Pricing Turkey'!G21*G$7 -> 4606 | H39: =IF(F39="STEEL",MAX(G39,E39*13)*20.25%,IF(F39="GALVA",MAX(G39,E39*24)*20.25%,IF(F39="INOX",MAX(G39,E39*40)*20.25%,IF(F39="COPPER",MAX(G39,E39*60)*20.25%,G39*20.25%)))) -> 932.715 | I39: =+((I$9*G$7+I$11+I$13+I$15+I$17)*(1+I$7)+2500)/($G$5*$H$5)*G39 -> 486.8542 | J39: =(J$9+J$7*G39)/($G$5*$H$5)*G39 -> 841.94886 | K39: =K$7*G39 -> 322.42 | L39: =+G39*L$7 -> 1151.5 | M39: =+G39+H39+I39+J39*50%+K39+L39*30% -> 7114.4136 | N39: =+G39+H39+I39+J39*50%+K39+L39*70% -> 7575.0136 | O39: =+SUM(H39:L39)+G39 -> 8341.4381
A40: =+'Pricing Turkey'!A22 -> IT.1-10 | B40: =+'Pricing Turkey'!B22 -> ARCADE CABINE 1100/1000 + ARCADE CONTRE-POIDS + TIRANDS + COULISSEAUX GEARLESS | C40: =+'Pricing Turkey'!C22 -> CABINE & ARCADE | D40: =+'Pricing Turkey'!D22 -> SET | E40: =+'Pricing Turkey'!E22 -> 200 | F40: =+'Pricing Turkey'!F22 -> STEEL | G40: ='Pricing Turkey'!G22*G$7 -> 7056 | H40: =IF(F40="STEEL",MAX(G40,E40*13)*20.25%,IF(F40="GALVA",MAX(G40,E40*24)*20.25%,IF(F40="INOX",MAX(G40,E40*40)*20.25%,IF(F40="COPPER",MAX(G40,E40*60)*20.25%,G40*20.25%)))) -> 1428.84 | I40: =+((I$9*G$7+I$11+I$13+I$15+I$17)*(1+I$7)+2500)/($G$5*$H$5)*G40 -> 745.8192 | J40: =(J$9+J$7*G40)/($G$5*$H$5)*G40 -> 1291.5227 | K40: =K$7*G40 -> 493.92 | L40: =+G40*L$7 -> 1764 | M40: =+G40+H40+I40+J40*50%+K40+L40*30% -> 10899.541 | N40: =+G40+H40+I40+J40*50%+K40+L40*70% -> 11605.141 | O40: =+SUM(H40:L40)+G40 -> 12780.102
A41: =+'Pricing Turkey'!A23 -> IT.1-11 | B41: =+'Pricing Turkey'!B23 -> ARCADE CABINE 1200/1100 + ARCADE CONTRE-POIDS + TIRANDS + COULISSEAUX GEARBOX | C41: =+'Pricing Turkey'!C23 -> CABINE & ARCADE | D41: =+'Pricing Turkey'!D23 -> SET | E41: =+'Pricing Turkey'!E23 -> 200 | F41: =+'Pricing Turkey'!F23 -> STEEL | G41: ='Pricing Turkey'!G23*G$7 -> 4802 | H41: =IF(F41="STEEL",MAX(G41,E41*13)*20.25%,IF(F41="GALVA",MAX(G41,E41*24)*20.25%,IF(F41="INOX",MAX(G41,E41*40)*20.25%,IF(F41="COPPER",MAX(G41,E41*60)*20.25%,G41*20.25%)))) -> 972.405 | I41: =+((I$9*G$7+I$11+I$13+I$15+I$17)*(1+I$7)+2500)/($G$5*$H$5)*G41 -> 507.5714 | J41: =(J$9+J$7*G41)/($G$5*$H$5)*G41 -> 877.87059 | K41: =K$7*G41 -> 336.14 | L41: =+G41*L$7 -> 1200.5 | M41: =+G41+H41+I41+J41*50%+K41+L41*30% -> 7417.2017 | N41: =+G41+H41+I41+J41*50%+K41+L41*70% -> 7897.4017 | O41: =+SUM(H41:L41)+G41 -> 8696.487
A42: =+'Pricing Turkey'!A24 -> IT.1-12 | B42: =+'Pricing Turkey'!B24 -> ARCADE CABINE 1200/1100 + ARCADE CONTRE-POIDS + TIRANDS + COULISSEAUX GEARLESS | C42: =+'Pricing Turkey'!C24 -> CABINE & ARCADE | D42: =+'Pricing Turkey'!D24 -> SET | E42: =+'Pricing Turkey'!E24 -> 200 | F42: =+'Pricing Turkey'!F24 -> STEEL | G42: ='Pricing Turkey'!G24*G$7 -> 7252 | H42: =IF(F42="STEEL",MAX(G42,E42*13)*20.25%,IF(F42="GALVA",MAX(G42,E42*24)*20.25%,IF(F42="INOX",MAX(G42,E42*40)*20.25%,IF(F42="COPPER",MAX(G42,E42*60)*20.25%,G42*20.25%)))) -> 1468.53 | I42: =+((I$9*G$7+I$11+I$13+I$15+I$17)*(1+I$7)+2500)/($G$5*$H$5)*G42 -> 766.5364 | J42: =(J$9+J$7*G42)/($G$5*$H$5)*G42 -> 1327.5405 | K42: =K$7*G42 -> 507.64 | L42: =+G42*L$7 -> 1813 | M42: =+G42+H42+I42+J42*50%+K42+L42*30% -> 11202.377 | N42: =+G42+H42+I42+J42*50%+K42+L42*70% -> 11927.577 | O42: =+SUM(H42:L42)+G42 -> 13135.247
A43: =+'Pricing Turkey'!A25 -> IT.1-15 | B43: =+'Pricing Turkey'!B25 -> ARCADE CABINE 1400/1300 + ARCADE CONTRE-POIDS + TIRANDS + COULISSEAUX GEARBOX | C43: =+'Pricing Turkey'!C25 -> CABINE & ARCADE | D43: =+'Pricing Turkey'!D25 -> SET | E43: =+'Pricing Turkey'!E25 -> 201 | F43: =+'Pricing Turkey'!F25 -> STEEL | G43: ='Pricing Turkey'!G25*G$7 -> 5782 | H43: =IF(F43="STEEL",MAX(G43,E43*13)*20.25%,IF(F43="GALVA",MAX(G43,E43*24)*20.25%,IF(F43="INOX",MAX(G43,E43*40)*20.25%,IF(F43="COPPER",MAX(G43,E43*60)*20.25%,G43*20.25%)))) -> 1170.855 | I43: =+((I$9*G$7+I$11+I$13+I$15+I$17)*(1+I$7)+2500)/($G$5*$H$5)*G43 -> 611.1574 | J43: =(J$9+J$7*G43)/($G$5*$H$5)*G43 -> 1057.5945 | K43: =K$7*G43 -> 404.74 | L43: =+G43*L$7 -> 1445.5 | M43: =+G43+H43+I43+J43*50%+K43+L43*30% -> 8931.1996 | N43: =+G43+H43+I43+J43*50%+K43+L43*70% -> 9509.3996 | O43: =+SUM(H43:L43)+G43 -> 10471.847
A44: =+'Pricing Turkey'!A26 -> IT.1-16 | B44: =+'Pricing Turkey'!B26 -> ARCADE CABINE 1400/1300 + ARCADE CONTRE-POIDS + TIRANDS + COULISSEAUX GEARLESS | C44: =+'Pricing Turkey'!C26 -> CABINE & ARCADE | D44: =+'Pricing Turkey'!D26 -> SET | E44: =+'Pricing Turkey'!E26 -> 202 | F44: =+'Pricing Turkey'!F26 -> STEEL | G44: ='Pricing Turkey'!G26*G$7 -> 9212 | H44: =IF(F44="STEEL",MAX(G44,E44*13)*20.25%,IF(F44="GALVA",MAX(G44,E44*24)*20.25%,IF(F44="INOX",MAX(G44,E44*40)*20.25%,IF(F44="COPPER",MAX(G44,E44*60)*20.25%,G44*20.25%)))) -> 1865.43 | I44: =+((I$9*G$7+I$11+I$13+I$15+I$17)*(1+I$7)+2500)/($G$5*$H$5)*G44 -> 973.7084 | J44: =(J$9+J$7*G44)/($G$5*$H$5)*G44 -> 1688.1408 | K44: =K$7*G44 -> 644.84 | L44: =+G44*L$7 -> 2303 | M44: =+G44+H44+I44+J44*50%+K44+L44*30% -> 14230.949 | N44: =+G44+H44+I44+J44*50%+K44+L44*70% -> 15152.149 | O44: =+SUM(H44:L44)+G44 -> 16687.119
A45: =+'Pricing Turkey'!A27 -> IT.1-17 | B45: =+'Pricing Turkey'!B27 -> SET ARCADE TYPE L VVVF 2V | C45: =+'Pricing Turkey'!C27 -> CABINE & ARCADE | D45: =+'Pricing Turkey'!D27 -> SET | E45: =+'Pricing Turkey'!E27 -> 203 | F45: =+'Pricing Turkey'!F27 -> STEEL | G45: ='Pricing Turkey'!G27*G$7 -> 9800 | H45: =IF(F45="STEEL",MAX(G45,E45*13)*20.25%,IF(F45="GALVA",MAX(G45,E45*24)*20.25%,IF(F45="INOX",MAX(G45,E45*40)*20.25%,IF(F45="COPPER",MAX(G45,E45*60)*20.25%,G45*20.25%)))) -> 1984.5 | I45: =+((I$9*G$7+I$11+I$13+I$15+I$17)*(1+I$7)+2500)/($G$5*$H$5)*G45 -> 1035.86 | J45: =(J$9+J$7*G45)/($G$5*$H$5)*G45 -> 1796.4707 | K45: =K$7*G45 -> 686 | L45: =+G45*L$7 -> 2450 | M45: =+G45+H45+I45+J45*50%+K45+L45*30% -> 15139.595 | N45: =+G45+H45+I45+J45*50%+K45+L45*70% -> 16119.595 | O45: =+SUM(H45:L45)+G45 -> 17752.831
A46: =+'Pricing Turkey'!A28 -> IT.1-18 | B46: =+'Pricing Turkey'!B28 -> SET ARCADE TYPE L GEARLESS | C46: =+'Pricing Turkey'!C28 -> CABINE & ARCADE | D46: =+'Pricing Turkey'!D28 -> SET | E46: =+'Pricing Turkey'!E28 -> 204 | F46: =+'Pricing Turkey'!F28 -> STEEL | G46: ='Pricing Turkey'!G28*G$7 -> 11760 | H46: =IF(F46="STEEL",MAX(G46,E46*13)*20.25%,IF(F46="GALVA",MAX(G46,E46*24)*20.25%,IF(F46="INOX",MAX(G46,E46*40)*20.25%,IF(F46="COPPER",MAX(G46,E46*60)*20.25%,G46*20.25%)))) -> 2381.4 | I46: =+((I$9*G$7+I$11+I$13+I$15+I$17)*(1+I$7)+2500)/($G$5*$H$5)*G46 -> 1243.032 | J46: =(J$9+J$7*G46)/($G$5*$H$5)*G46 -> 2158.0698 | K46: =K$7*G46 -> 823.2 | L46: =+G46*L$7 -> 2940 | M46: =+G46+H46+I46+J46*50%+K46+L46*30% -> 18168.667 | N46: =+G46+H46+I46+J46*50%+K46+L46*70% -> 19344.667 | O46: =+SUM(H46:L46)+G46 -> 21305.702
A47: =+'Pricing Turkey'!A29 -> HYD1-1 | B47: =+'Pricing Turkey'!B29 -> SET SYSTÈME HYDRAULIQUE MAX4 STANDARD 0,15M/S 10M COURSE (4 NIVEAUX) | C47: =+'Pricing Turkey'!C29 -> HYDRAULIQUE | D47: =+'Pricing Turkey'!D29 -> SET | E47: =+'Pricing Turkey'!E29 -> 200 | F47: =+'Pricing Turkey'!F29 -> STEEL | G47: ='Pricing Turkey'!G29*G$7 -> 14700 | H47: =IF(F47="STEEL",MAX(G47,E47*13)*20.25%,IF(F47="GALVA",MAX(G47,E47*24)*20.25%,IF(F47="INOX",MAX(G47,E47*40)*20.25%,IF(F47="COPPER",MAX(G47,E47*60)*20.25%,G47*20.25%)))) -> 2976.75 | I47: =+((I$9*G$7+I$11+I$13+I$15+I$17)*(1+I$7)+2500)/($G$5*$H$5)*G47 -> 1553.79 | J47: =(J$9+J$7*G47)/($G$5*$H$5)*G47 -> 2701.909 | K47: =K$7*G47 -> 1029 | L47: =+G47*L$7 -> 3675 | M47: =+G47+H47+I47+J47*50%+K47+L47*30% -> 22712.995 | N47: =+G47+H47+I47+J47*50%+K47+L47*70% -> 24182.995 | O47: =+SUM(H47:L47)+G47 -> 26636.449
A48: =+'Pricing Turkey'!A30 -> HYD1-2 | B48: =+'Pricing Turkey'!B30 -> SET SYSTÈME HYDRAULIQUE MAX4 STANDARD 0,15M/S 7M COURSE (3 NIVEAUX) | C48: =+'Pricing Turkey'!C30 -> HYDRAULIQUE | D48: =+'Pricing Turkey'!D30 -> SET | E48: =+'Pricing Turkey'!E30 -> 198 | F48: =+'Pricing Turkey'!F30 -> STEEL | G48: ='Pricing Turkey'!G30*G$7 -> 0 | H48: =IF(F48="STEEL",MAX(G48,E48*13)*20.25%,IF(F48="GALVA",MAX(G48,E48*24)*20.25%,IF(F48="INOX",MAX(G48,E48*40)*20.25%,IF(F48="COPPER",MAX(G48,E48*60)*20.25%,G48*20.25%)))) -> 521.235 | I48: =+((I$9*G$7+I$11+I$13+I$15+I$17)*(1+I$7)+2500)/($G$5*$H$5)*G48 -> 0 | J48: =(J$9+J$7*G48)/($G$5*$H$5)*G48 -> 0 | K48: =K$7*G48 -> 0 | L48: =+G48*L$7 -> 0 | M48: =+G48+H48+I48+J48*50%+K48+L48*30% -> 521.235 | N48: =+G48+H48+I48+J48*50%+K48+L48*70% -> 521.235 | O48: =+SUM(H48:L48)+G48 -> 521.235
... A66: =+'Pricing Turkey'!A48 -> IT.13 | B66: =+'Pricing Turkey'!B48 -> MOTEUR AKİŞ 2V MAX8 | C66: =+'Pricing Turkey'!C48 -> MOTEUR | D66: =+'Pricing Turkey'!D48 -> Pc | E66: =+'Pricing Turkey'!E48 -> 380 | F66: =+'Pricing Turkey'!F48 -> N | G66: ='Pricing Turkey'!G48*G$7 -> 10486 | H66: =IF(F66="STEEL",MAX(G66,E66*13)*20.25%,IF(F66="GALVA",MAX(G66,E66*24)*20.25%,IF(F66="INOX",MAX(G66,E66*40)*20.25%,IF(F66="COPPER",MAX(G66,E66*60)*20.25%,G66*20.25%)))) -> 2123.415 | I66: =+((I$9*G$7+I$11+I$13+I$15+I$17)*(1+I$7)+2500)/($G$5*$H$5)*G66 -> 1108.3702 | J66: =(J$9+J$7*G66)/($G$5*$H$5)*G66 -> 1922.943 | K66: =K$7*G66 -> 734.02 | L66: =+G66*L$7 -> 2621.5 | M66: =+G66+H66+I66+J66*50%+K66+L66*30% -> 16199.727 | N66: =+G66+H66+I66+J66*50%+K66+L66*70% -> 17248.327 | O66: =+SUM(H66:L66)+G66 -> 18996.248
A67: =+'Pricing Turkey'!A49 -> IT.14 | B67: =+'Pricing Turkey'!B49 -> CLASSIC BRACKET 60X60 (PATE) | C67: =+'Pricing Turkey'!C49 -> RAILS & ACCESSOIRES | D67: =+'Pricing Turkey'!D49 -> Pc | E67: =+'Pricing Turkey'!E49 -> 0.5 | F67: =+'Pricing Turkey'!F49 -> STEEL | G67: ='Pricing Turkey'!G49*G$7 -> 5.88 | H67: =IF(F67="STEEL",MAX(G67,E67*13)*20.25%,IF(F67="GALVA",MAX(G67,E67*24)*20.25%,IF(F67="INOX",MAX(G67,E67*40)*20.25%,IF(F67="COPPER",MAX(G67,E67*60)*20.25%,G67*20.25%)))) -> 1.31625 | I67: =+((I$9*G$7+I$11+I$13+I$15+I$17)*(1+I$7)+2500)/($G$5*$H$5)*G67 -> 0.621516 | J67: =(J$9+J$7*G67)/($G$5*$H$5)*G67 -> 1.0721235 | K67: =K$7*G67 -> 0.4116 | L67: =+G67*L$7 -> 1.47 | M67: =+G67+H67+I67+J67*50%+K67+L67*30% -> 9.2064277 | N67: =+G67+H67+I67+J67*50%+K67+L67*70% -> 9.7944277 | O67: =+SUM(H67:L67)+G67 -> 10.771489 | AB67: w
A68: =+'Pricing Turkey'!A50 -> IT.15 | B68: =+'Pricing Turkey'!B50 -> CLASSIC BRACKET 60X80 (PATE) | C68: =+'Pricing Turkey'!C50 -> RAILS & ACCESSOIRES | D68: =+'Pricing Turkey'!D50 -> Pc | E68: =+'Pricing Turkey'!E50 -> 0.65 | F68: =+'Pricing Turkey'!F50 -> STEEL | G68: ='Pricing Turkey'!G50*G$7 -> 8.82 | H68: =IF(F68="STEEL",MAX(G68,E68*13)*20.25%,IF(F68="GALVA",MAX(G68,E68*24)*20.25%,IF(F68="INOX",MAX(G68,E68*40)*20.25%,IF(F68="COPPER",MAX(G68,E68*60)*20.25%,G68*20.25%)))) -> 1.78605 | I68: =+((I$9*G$7+I$11+I$13+I$15+I$17)*(1+I$7)+2500)/($G$5*$H$5)*G68 -> 0.932274 | J68: =(J$9+J$7*G68)/($G$5*$H$5)*G68 -> 1.6081878 | K68: =K$7*G68 -> 0.6174 | L68: =+G68*L$7 -> 2.205 | M68: =+G68+H68+I68+J68*50%+K68+L68*30% -> 13.621318 | N68: =+G68+H68+I68+J68*50%+K68+L68*70% -> 14.503318 | O68: =+SUM(H68:L68)+G68 -> 15.968912
A69: =+'Pricing Turkey'!A51 -> IT.16 | B69: =+'Pricing Turkey'!B51 -> CROMPO 50 | C69: =+'Pricing Turkey'!C51 -> RAILS & ACCESSOIRES | D69: =+'Pricing Turkey'!D51 -> Pc | E69: =+'Pricing Turkey'!E51 -> 0.11 | F69: =+'Pricing Turkey'!F51 -> GALVA | G69: ='Pricing Turkey'!G51*G$7 -> 2.744 | H69: =IF(F69="STEEL",MAX(G69,E69*13)*20.25%,IF(F69="GALVA",MAX(G69,E69*24)*20.25%,IF(F69="INOX",MAX(G69,E69*40)*20.25%,IF(F69="COPPER",MAX(G69,E69*60)*20.25%,G69*20.25%)))) -> 0.55566 | I69: =+((I$9*G$7+I$11+I$13+I$15+I$17)*(1+I$7)+2500)/($G$5*$H$5)*G69 -> 0.2900408 | J69: =(J$9+J$7*G69)/($G$5*$H$5)*G69 -> 0.50032342 | K69: =K$7*G69 -> 0.19208 | L69: =+G69*L$7 -> 0.686 | M69: =+G69+H69+I69+J69*50%+K69+L69*30% -> 4.2377425 | N69: =+G69+H69+I69+J69*50%+K69+L69*70% -> 4.5121425 | O69: =+SUM(H69:L69)+G69 -> 4.9681042
A70: =+'Pricing Turkey'!A52 -> IT.17 | B70: =+'Pricing Turkey'!B52 -> CROMPO 70 | C70: =+'Pricing Turkey'!C52 -> RAILS & ACCESSOIRES | D70: =+'Pricing Turkey'!D52 -> Pc | E70: =+'Pricing Turkey'!E52 -> 0.12 | F70: =+'Pricing Turkey'!F52 -> GALVA | G70: ='Pricing Turkey'!G52*G$7 -> 3.626 | H70: =IF(F70="STEEL",MAX(G70,E70*13)*20.25%,IF(F70="GALVA",MAX(G70,E70*24)*20.25%,IF(F70="INOX",MAX(G70,E70*40)*20.25%,IF(F70="COPPER",MAX(G70,E70*60)*20.25%,G70*20.25%)))) -> 0.734265 | I70: =+((I$9*G$7+I$11+I$13+I$15+I$17)*(1+I$7)+2500)/($G$5*$H$5)*G70 -> 0.3832682 | J70: =(J$9+J$7*G70)/($G$5*$H$5)*G70 -> 0.66114198 | K70: =K$7*G70 -> 0.25382 | L70: =+G70*L$7 -> 0.9065 | M70: =+G70+H70+I70+J70*50%+K70+L70*30% -> 5.5998742 | N70: =+G70+H70+I70+J70*50%+K70+L70*70% -> 5.9624742 | O70: =+SUM(H70:L70)+G70 -> 6.5649952
A71: =+'Pricing Turkey'!A53 -> IT.18 | B71: =+'Pricing Turkey'!B53 -> SET BRACKET U | C71: =+'Pricing Turkey'!C53 -> RAILS & ACCESSOIRES | D71: =+'Pricing Turkey'!D53 -> SET | E71: =+'Pricing Turkey'!E53 -> 30 | F71: =+'Pricing Turkey'!F53 -> GALVA | G71: ='Pricing Turkey'!G53*G$7 -> 343 | H71: =IF(F71="STEEL",MAX(G71,E71*13)*20.25%,IF(F71="GALVA",MAX(G71,E71*24)*20.25%,IF(F71="INOX",MAX(G71,E71*40)*20.25%,IF(F71="COPPER",MAX(G71,E71*60)*20.25%,G71*20.25%)))) -> 145.8 | I71: =+((I$9*G$7+I$11+I$13+I$15+I$17)*(1+I$7)+2500)/($G$5*$H$5)*G71 -> 36.2551 | J71: =(J$9+J$7*G71)/($G$5*$H$5)*G71 -> 62.552098 | K71: =K$7*G71 -> 24.01 | L71: =+G71*L$7 -> 85.75 | M71: =+G71+H71+I71+J71*50%+K71+L71*30% -> 606.06615 | N71: =+G71+H71+I71+J71*50%+K71+L71*70% -> 640.36615 | O71: =+SUM(H71:L71)+G71 -> 697.3672
A72: =+'Pricing Turkey'!A54 -> IT.19 | B72: =+'Pricing Turkey'!B54 -> CROMPO 90 | C72: =+'Pricing Turkey'!C54 -> RAILS & ACCESSOIRES | D72: =+'Pricing Turkey'!D54 -> Pc | E72: =+'Pricing Turkey'!E54 -> 0.17 | F72: =+'Pricing Turkey'!F54 -> GALVA | G72: ='Pricing Turkey'!G54*G$7 -> 4.606 | H72: =IF(F72="STEEL",MAX(G72,E72*13)*20.25%,IF(F72="GALVA",MAX(G72,E72*24)*20.25%,IF(F72="INOX",MAX(G72,E72*40)*20.25%,IF(F72="COPPER",MAX(G72,E72*60)*20.25%,G72*20.25%)))) -> 0.932715 | I72: =+((I$9*G$7+I$11+I$13+I$15+I$17)*(1+I$7)+2500)/($G$5*$H$5)*G72 -> 0.4868542 | J72: =(J$9+J$7*G72)/($G$5*$H$5)*G72 -> 0.83982945 | K72: =K$7*G72 -> 0.32242 | L72: =+G72*L$7 -> 1.1515 | M72: =+G72+H72+I72+J72*50%+K72+L72*30% -> 7.1133539 | N72: =+G72+H72+I72+J72*50%+K72+L72*70% -> 7.5739539 | O72: =+SUM(H72:L72)+G72 -> 8.3393187
A73: =+'Pricing Turkey'!A55 -> IT.20 | B73: =+'Pricing Turkey'!B55 -> SET BRACKET TYPE L | C73: =+'Pricing Turkey'!C55 -> RAILS & ACCESSOIRES | D73: =+'Pricing Turkey'!D55 -> SET | E73: =+'Pricing Turkey'!E55 -> 30 | F73: =+'Pricing Turkey'!F55 -> GALVA | G73: ='Pricing Turkey'!G55*G$7 -> 490 | H73: =IF(F73="STEEL",MAX(G73,E73*13)*20.25%,IF(F73="GALVA",MAX(G73,E73*24)*20.25%,IF(F73="INOX",MAX(G73,E73*40)*20.25%,IF(F73="COPPER",MAX(G73,E73*60)*20.25%,G73*20.25%)))) -> 145.8 | I73: =+((I$9*G$7+I$11+I$13+I$15+I$17)*(1+I$7)+2500)/($G$5*$H$5)*G73 -> 51.793 | J73: =(J$9+J$7*G73)/($G$5*$H$5)*G73 -> 89.367343 | K73: =K$7*G73 -> 34.3 | L73: =+G73*L$7 -> 122.5 | M73: =+G73+H73+I73+J73*50%+K73+L73*30% -> 803.32667 | N73: =+G73+H73+I73+J73*50%+K73+L73*70% -> 852.32667 | O73: =+SUM(H73:L73)+G73 -> 933.76034
A74: =+'Pricing Turkey'!A56 -> IT.21 | B74: =+'Pricing Turkey'!B56 -> BOULON 8/30 | C74: =+'Pricing Turkey'!C56 -> RAILS & ACCESSOIRES | D74: =+'Pricing Turkey'!D56 -> Pc | E74: =+'Pricing Turkey'!E56 -> 0.02 | F74: =+'Pricing Turkey'!F56 -> GALVA | G74: ='Pricing Turkey'!G56*G$7 -> 0.686 | H74: =IF(F74="STEEL",MAX(G74,E74*13)*20.25%,IF(F74="GALVA",MAX(G74,E74*24)*20.25%,IF(F74="INOX",MAX(G74,E74*40)*20.25%,IF(F74="COPPER",MAX(G74,E74*60)*20.25%,G74*20.25%)))) -> 0.138915 | I74: =+((I$9*G$7+I$11+I$13+I$15+I$17)*(1+I$7)+2500)/($G$5*$H$5)*G74 -> 0.0725102 | J74: =(J$9+J$7*G74)/($G$5*$H$5)*G74 -> 0.12508071 | K74: =K$7*G74 -> 0.04802 | L74: =+G74*L$7 -> 0.1715 | M74: =+G74+H74+I74+J74*50%+K74+L74*30% -> 1.0594356 | N74: =+G74+H74+I74+J74*50%+K74+L74*70% -> 1.1280356 | O74: =+SUM(H74:L74)+G74 -> 1.2420259
A75: =+'Pricing Turkey'!A57 -> IT.22 | B75: =+'Pricing Turkey'!B57 -> BOULON 12/25 | C75: =+'Pricing Turkey'!C57 -> RAILS & ACCESSOIRES | D75: =+'Pricing Turkey'!D57 -> Pc | E75: =+'Pricing Turkey'!E57 -> 0.04 | F75: =+'Pricing Turkey'!F57 -> GALVA | G75: ='Pricing Turkey'!G57*G$7 -> 1.764 | H75: =IF(F75="STEEL",MAX(G75,E75*13)*20.25%,IF(F75="GALVA",MAX(G75,E75*24)*20.25%,IF(F75="INOX",MAX(G75,E75*40)*20.25%,IF(F75="COPPER",MAX(G75,E75*60)*20.25%,G75*20.25%)))) -> 0.35721 | I75: =+((I$9*G$7+I$11+I$13+I$15+I$17)*(1+I$7)+2500)/($G$5*$H$5)*G75 -> 0.1864548 | J75: =(J$9+J$7*G75)/($G$5*$H$5)*G75 -> 0.32163631 | K75: =K$7*G75 -> 0.12348 | L75: =+G75*L$7 -> 0.441 | M75: =+G75+H75+I75+J75*50%+K75+L75*30% -> 2.724263 | N75: =+G75+H75+I75+J75*50%+K75+L75*70% -> 2.900663 | O75: =+SUM(H75:L75)+G75 -> 3.1937811
A76: =+'Pricing Turkey'!A58 -> IT.23 | B76: =+'Pricing Turkey'!B58 -> BOULON 12/40 | C76: =+'Pricing Turkey'!C58 -> RAILS & ACCESSOIRES | D76: =+'Pricing Turkey'!D58 -> Pc | E76: =+'Pricing Turkey'!E58 -> 0.05 | F76: =+'Pricing Turkey'!F58 -> GALVA | G76: ='Pricing Turkey'!G58*G$7 -> 1.96 | H76: =IF(F76="STEEL",MAX(G76,E76*13)*20.25%,IF(F76="GALVA",MAX(G76,E76*24)*20.25%,IF(F76="INOX",MAX(G76,E76*40)*20.25%,IF(F76="COPPER",MAX(G76,E76*60)*20.25%,G76*20.25%)))) -> 0.3969 | I76: =+((I$9*G$7+I$11+I$13+I$15+I$17)*(1+I$7)+2500)/($G$5*$H$5)*G76 -> 0.207172 | J76: =(J$9+J$7*G76)/($G$5*$H$5)*G76 -> 0.35737372 | K76: =K$7*G76 -> 0.1372 | L76: =+G76*L$7 -> 0.49 | M76: =+G76+H76+I76+J76*50%+K76+L76*30% -> 3.0269589 | N76: =+G76+H76+I76+J76*50%+K76+L76*70% -> 3.2229589 | O76: =+SUM(H76:L76)+G76 -> 3.5486457
A77: =+'Pricing Turkey'!A59 -> IT.24 | B77: =+'Pricing Turkey'!B59 -> BOULON 14/70 | C77: =+'Pricing Turkey'!C59 -> RAILS & ACCESSOIRES | D77: =+'Pricing Turkey'!D59 -> Pc | E77: =+'Pricing Turkey'!E59 -> 0 | F77: =+'Pricing Turkey'!F59 -> GALVA | G77: ='Pricing Turkey'!G59*G$7 -> 2.94 | H77: =IF(F77="STEEL",MAX(G77,E77*13)*20.25%,IF(F77="GALVA",MAX(G77,E77*24)*20.25%,IF(F77="INOX",MAX(G77,E77*40)*20.25%,IF(F77="COPPER",MAX(G77,E77*60)*20.25%,G77*20.25%)))) -> 0.59535 | I77: =+((I$9*G$7+I$11+I$13+I$15+I$17)*(1+I$7)+2500)/($G$5*$H$5)*G77 -> 0.310758 | J77: =(J$9+J$7*G77)/($G$5*$H$5)*G77 -> 0.53606086 | K77: =K$7*G77 -> 0.2058 | L77: =+G77*L$7 -> 0.735 | M77: =+G77+H77+I77+J77*50%+K77+L77*30% -> 4.5404384 | N77: =+G77+H77+I77+J77*50%+K77+L77*70% -> 4.8344384 | O77: =+SUM(H77:L77)+G77 -> 5.3229689
A78: =+'Pricing Turkey'!A60 -> IT.25 | B78: =+'Pricing Turkey'!B60 -> CHEVEILLE 12/100 | C78: =+'Pricing Turkey'!C60 -> RAILS & ACCESSOIRES | D78: =+'Pricing Turkey'!D60 -> Pc | E78: =+'Pricing Turkey'!E60 -> 0.09 | F78: =+'Pricing Turkey'!F60 -> GALVA | G78: ='Pricing Turkey'!G60*G$7 -> 2.058 | H78: =IF(F78="STEEL",MAX(G78,E78*13)*20.25%,IF(F78="GALVA",MAX(G78,E78*24)*20.25%,IF(F78="INOX",MAX(G78,E78*40)*20.25%,IF(F78="COPPER",MAX(G78,E78*60)*20.25%,G78*20.25%)))) -> 0.4374 | I78: =+((I$9*G$7+I$11+I$13+I$15+I$17)*(1+I$7)+2500)/($G$5*$H$5)*G78 -> 0.2175306 | J78: =(J$9+J$7*G78)/($G$5*$H$5)*G78 -> 0.37524242 | K78: =K$7*G78 -> 0.14406 | L78: =+G78*L$7 -> 0.5145 | M78: =+G78+H78+I78+J78*50%+K78+L78*30% -> 3.1989618 | N78: =+G78+H78+I78+J78*50%+K78+L78*70% -> 3.4047618 | O78: =+SUM(H78:L78)+G78 -> 3.746733
A79: =+'Pricing Turkey'!A61 -> IT.26 | B79: =+'Pricing Turkey'!B61 -> GUIDE RAIL 50 | C79: =+'Pricing Turkey'!C61 -> RAILS & ACCESSOIRES | D79: =+'Pricing Turkey'!D61 -> Pc | E79: =+'Pricing Turkey'!E61 -> 27 | F79: =+'Pricing Turkey'!F61 -> STEEL | G79: ='Pricing Turkey'!G61*G$7 -> 170.52 | H79: =IF(F79="STEEL",MAX(G79,E79*13)*20.25%,IF(F79="GALVA",MAX(G79,E79*24)*20.25%,IF(F79="INOX",MAX(G79,E79*40)*20.25%,IF(F79="COPPER",MAX(G79,E79*60)*20.25%,G79*20.25%)))) -> 71.0775 | I79: =+((I$9*G$7+I$11+I$13+I$15+I$17)*(1+I$7)+2500)/($G$5*$H$5)*G79 -> 18.023964 | J79: =(J$9+J$7*G79)/($G$5*$H$5)*G79 -> 31.094388 | K79: =K$7*G79 -> 11.9364 | L79: =+G79*L$7 -> 42.63 | M79: =+G79+H79+I79+J79*50%+K79+L79*30% -> 299.89406 | N79: =+G79+H79+I79+J79*50%+K79+L79*70% -> 316.94606 | O79: =+SUM(H79:L79)+G79 -> 345.28225
... A84: =+'Pricing Turkey'!A66 -> IT.31 | B84: =+'Pricing Turkey'!B66 -> CABLE TRACTION (10mm) | C84: =+'Pricing Turkey'!C66 -> CABLES & ACCESSOIRES | D84: =+'Pricing Turkey'!D66 -> M | E84: =+'Pricing Turkey'!E66 -> 0.4 | F84: =+'Pricing Turkey'!F66 -> STEEL | G84: ='Pricing Turkey'!G66*G$7 -> 9.016 | H84: =IF(F84="STEEL",MAX(G84,E84*13)*20.25%,IF(F84="GALVA",MAX(G84,E84*24)*20.25%,IF(F84="INOX",MAX(G84,E84*40)*20.25%,IF(F84="COPPER",MAX(G84,E84*60)*20.25%,G84*20.25%)))) -> 1.82574 | I84: =+((I$9*G$7+I$11+I$13+I$15+I$17)*(1+I$7)+2500)/($G$5*$H$5)*G84 -> 0.9529912 | J84: =(J$9+J$7*G84)/($G$5*$H$5)*G84 -> 1.6439255 | K84: =K$7*G84 -> 0.63112 | L84: =+G84*L$7 -> 2.254 | M84: =+G84+H84+I84+J84*50%+K84+L84*30% -> 13.924014 | N84: =+G84+H84+I84+J84*50%+K84+L84*70% -> 14.825614 | O84: =+SUM(H84:L84)+G84 -> 16.323777
A85: =+'Pricing Turkey'!A67 -> IT.32 | B85: =+'Pricing Turkey'!B67 -> CABLE GEARLESS (6,5mm) | C85: =+'Pricing Turkey'!C67 -> CABLES & ACCESSOIRES | D85: =+'Pricing Turkey'!D67 -> M | E85: =+'Pricing Turkey'!E67 -> 0 | F85: =+'Pricing Turkey'!F109 -> STEEL | G85: ='Pricing Turkey'!G67*G$7 -> 8.526 | H85: =IF(F85="STEEL",MAX(G85,E85*13)*20.25%,IF(F85="GALVA",MAX(G85,E85*24)*20.25%,IF(F85="INOX",MAX(G85,E85*40)*20.25%,IF(F85="COPPER",MAX(G85,E85*60)*20.25%,G85*20.25%)))) -> 1.726515 | I85: =+((I$9*G$7+I$11+I$13+I$15+I$17)*(1+I$7)+2500)/($G$5*$H$5)*G85 -> 0.9011982 | J85: =(J$9+J$7*G85)/($G$5*$H$5)*G85 -> 1.5545813 | K85: =K$7*G85 -> 0.59682 | L85: =+G85*L$7 -> 2.1315 | M85: =+G85+H85+I85+J85*50%+K85+L85*30% -> 13.167274 | N85: =+G85+H85+I85+J85*50%+K85+L85*70% -> 14.019874 | O85: =+SUM(H85:L85)+G85 -> 15.436614
A86: =+'Pricing Turkey'!A68 -> IT.33 | B86: =+'Pricing Turkey'!B68 -> CABLE REGULATEUR (6mm) | C86: =+'Pricing Turkey'!C68 -> CABLES & ACCESSOIRES | D86: =+'Pricing Turkey'!D68 -> 0 | E86: =+'Pricing Turkey'!E68 -> 0.22 | F86: =+'Pricing Turkey'!F68 -> STEEL | G86: ='Pricing Turkey'!G68*G$7 -> 2.744 | H86: =IF(F86="STEEL",MAX(G86,E86*13)*20.25%,IF(F86="GALVA",MAX(G86,E86*24)*20.25%,IF(F86="INOX",MAX(G86,E86*40)*20.25%,IF(F86="COPPER",MAX(G86,E86*60)*20.25%,G86*20.25%)))) -> 0.57915 | I86: =+((I$9*G$7+I$11+I$13+I$15+I$17)*(1+I$7)+2500)/($G$5*$H$5)*G86 -> 0.2900408 | J86: =(J$9+J$7*G86)/($G$5*$H$5)*G86 -> 0.50032342 | K86: =K$7*G86 -> 0.19208 | L86: =+G86*L$7 -> 0.686 | M86: =+G86+H86+I86+J86*50%+K86+L86*30% -> 4.2612325 | N86: =+G86+H86+I86+J86*50%+K86+L86*70% -> 4.5356325 | O86: =+SUM(H86:L86)+G86 -> 4.9915942
A87: =+'Pricing Turkey'!A69 -> IT.34 | B87: =+'Pricing Turkey'!B69 -> TIRANDS 10MM | C87: =+'Pricing Turkey'!C69 -> CABLES & ACCESSOIRES | D87: =+'Pricing Turkey'!D69 -> Pc | E87: =+'Pricing Turkey'!E69 -> 1.09 | F87: =+'Pricing Turkey'!F69 -> GALVA | G87: ='Pricing Turkey'!G69*G$7 -> 21.07 | H87: =IF(F87="STEEL",MAX(G87,E87*13)*20.25%,IF(F87="GALVA",MAX(G87,E87*24)*20.25%,IF(F87="INOX",MAX(G87,E87*40)*20.25%,IF(F87="COPPER",MAX(G87,E87*60)*20.25%,G87*20.25%)))) -> 5.2974 | I87: =+((I$9*G$7+I$11+I$13+I$15+I$17)*(1+I$7)+2500)/($G$5*$H$5)*G87 -> 2.227099 | J87: =(J$9+J$7*G87)/($G$5*$H$5)*G87 -> 3.8418077 | K87: =K$7*G87 -> 1.4749 | L87: =+G87*L$7 -> 5.2675 | M87: =+G87+H87+I87+J87*50%+K87+L87*30% -> 33.570553 | N87: =+G87+H87+I87+J87*50%+K87+L87*70% -> 35.677553 | O87: =+SUM(H87:L87)+G87 -> 39.178707
A88: =+'Pricing Turkey'!A70 -> IT.35 | B88: =+'Pricing Turkey'!B70 -> TIRANDS 6,5MM | C88: =+'Pricing Turkey'!C70 -> CABLES & ACCESSOIRES | D88: =+'Pricing Turkey'!D70 -> Pc | E88: =+'Pricing Turkey'!E70 -> 0 | F88: =+'Pricing Turkey'!F70 -> GALVA | G88: ='Pricing Turkey'!G70*G$7 -> 21.07 | H88: =IF(F88="STEEL",MAX(G88,E88*13)*20.25%,IF(F88="GALVA",MAX(G88,E88*24)*20.25%,IF(F88="INOX",MAX(G88,E88*40)*20.25%,IF(F88="COPPER",MAX(G88,E88*60)*20.25%,G88*20.25%)))) -> 4.266675 | I88: =+((I$9*G$7+I$11+I$13+I$15+I$17)*(1+I$7)+2500)/($G$5*$H$5)*G88 -> 2.227099 | J88: =(J$9+J$7*G88)/($G$5*$H$5)*G88 -> 3.8418077 | K88: =K$7*G88 -> 1.4749 | L88: =+G88*L$7 -> 5.2675 | M88: =+G88+H88+I88+J88*50%+K88+L88*30% -> 32.539828 | N88: =+G88+H88+I88+J88*50%+K88+L88*70% -> 34.646828 | O88: =+SUM(H88:L88)+G88 -> 38.147982
A89: =+'Pricing Turkey'!A71 -> IT.36 | B89: =+'Pricing Turkey'!B71 -> SERRE CABLE DIAM 10mm * | C89: =+'Pricing Turkey'!C71 -> CABLES & ACCESSOIRES | D89: =+'Pricing Turkey'!D71 -> Pc | E89: =+'Pricing Turkey'!E71 -> 0.07 | F89: =+'Pricing Turkey'!F71 -> GALVA | G89: ='Pricing Turkey'!G71*G$7 -> 1.96 | H89: =IF(F89="STEEL",MAX(G89,E89*13)*20.25%,IF(F89="GALVA",MAX(G89,E89*24)*20.25%,IF(F89="INOX",MAX(G89,E89*40)*20.25%,IF(F89="COPPER",MAX(G89,E89*60)*20.25%,G89*20.25%)))) -> 0.3969 | I89: =+((I$9*G$7+I$11+I$13+I$15+I$17)*(1+I$7)+2500)/($G$5*$H$5)*G89 -> 0.207172 | J89: =(J$9+J$7*G89)/($G$5*$H$5)*G89 -> 0.35737372 | K89: =K$7*G89 -> 0.1372 | L89: =+G89*L$7 -> 0.49 | M89: =+G89+H89+I89+J89*50%+K89+L89*30% -> 3.0269589 | N89: =+G89+H89+I89+J89*50%+K89+L89*70% -> 3.2229589 | O89: =+SUM(H89:L89)+G89 -> 3.5486457
A90: =+'Pricing Turkey'!A72 -> IT.37 | B90: =+'Pricing Turkey'!B72 -> SERRE CABLE DIAM 6,5mm * | C90: =+'Pricing Turkey'!C72 -> CABLES & ACCESSOIRES | D90: =+'Pricing Turkey'!D72 -> 0 | E90: =+'Pricing Turkey'!E72 -> 0 | F90: =+'Pricing Turkey'!F72 -> GALVA | G90: ='Pricing Turkey'!G72*G$7 -> 1.47 | H90: =IF(F90="STEEL",MAX(G90,E90*13)*20.25%,IF(F90="GALVA",MAX(G90,E90*24)*20.25%,IF(F90="INOX",MAX(G90,E90*40)*20.25%,IF(F90="COPPER",MAX(G90,E90*60)*20.25%,G90*20.25%)))) -> 0.297675 | I90: =+((I$9*G$7+I$11+I$13+I$15+I$17)*(1+I$7)+2500)/($G$5*$H$5)*G90 -> 0.155379 | J90: =(J$9+J$7*G90)/($G$5*$H$5)*G90 -> 0.26803022 | K90: =K$7*G90 -> 0.1029 | L90: =+G90*L$7 -> 0.3675 | M90: =+G90+H90+I90+J90*50%+K90+L90*30% -> 2.2702191 | N90: =+G90+H90+I90+J90*50%+K90+L90*70% -> 2.4172191 | O90: =+SUM(H90:L90)+G90 -> 2.6614842
A91: =+'Pricing Turkey'!A73 -> IT.38 | B91: =+'Pricing Turkey'!B73 -> SERRE CABLE DIAM 6mm * | C91: =+'Pricing Turkey'!C73 -> CABLES & ACCESSOIRES | D91: =+'Pricing Turkey'!D73 -> Pc | E91: =+'Pricing Turkey'!E73 -> 0.01 | F91: =+'Pricing Turkey'!F73 -> GALVA | G91: ='Pricing Turkey'!G73*G$7 -> 0.98 | H91: =IF(F91="STEEL",MAX(G91,E91*13)*20.25%,IF(F91="GALVA",MAX(G91,E91*24)*20.25%,IF(F91="INOX",MAX(G91,E91*40)*20.25%,IF(F91="COPPER",MAX(G91,E91*60)*20.25%,G91*20.25%)))) -> 0.19845 | I91: =+((I$9*G$7+I$11+I$13+I$15+I$17)*(1+I$7)+2500)/($G$5*$H$5)*G91 -> 0.103586 | J91: =(J$9+J$7*G91)/($G$5*$H$5)*G91 -> 0.17868676 | K91: =K$7*G91 -> 0.0686 | L91: =+G91*L$7 -> 0.245 | M91: =+G91+H91+I91+J91*50%+K91+L91*30% -> 1.5134794 | N91: =+G91+H91+I91+J91*50%+K91+L91*70% -> 1.6114794 | O91: =+SUM(H91:L91)+G91 -> 1.7743228
A92: =+'Pricing Turkey'!A74 -> IT.39 | B92: =+'Pricing Turkey'!B74 -> GOSE 96 CM (50 KG) | C92: =+'Pricing Turkey'!C74 -> GOSE | D92: =+'Pricing Turkey'!D74 -> Pc | E92: =+'Pricing Turkey'!E74 -> 50 | F92: =+'Pricing Turkey'!F74 -> CONCRETE | G92: ='Pricing Turkey'!G74*G$7 -> 58.8 | H92: =IF(F92="STEEL",MAX(G92,E92*13)*20.25%,IF(F92="GALVA",MAX(G92,E92*24)*20.25%,IF(F92="INOX",MAX(G92,E92*40)*20.25%,IF(F92="COPPER",MAX(G92,E92*60)*20.25%,G92*20.25%)))) -> 11.907 | I92: =+((I$9*G$7+I$11+I$13+I$15+I$17)*(1+I$7)+2500)/($G$5*$H$5)*G92 -> 6.21516 | J92: =(J$9+J$7*G92)/($G$5*$H$5)*G92 -> 10.721546 | K92: =K$7*G92 -> 4.116 | L92: =+G92*L$7 -> 14.7 | M92: =+G92+H92+I92+J92*50%+K92+L92*30% -> 90.808933 | N92: =+G92+H92+I92+J92*50%+K92+L92*70% -> 96.688933 | O92: =+SUM(H92:L92)+G92 -> 106.45971
A93: =+'Pricing Turkey'!A75 -> IT.40 | B93: =+'Pricing Turkey'!B75 -> COLLECTEUR D'HUILE | C93: =+'Pricing Turkey'!C75 -> AUTRES | D93: =+'Pricing Turkey'!D75 -> Pc | E93: =+'Pricing Turkey'!E75 -> 0.07 | F93: =+'Pricing Turkey'!F75 -> PVC | G93: ='Pricing Turkey'!G75*G$7 -> 2.45 | H93: =IF(F93="STEEL",MAX(G93,E93*13)*20.25%,IF(F93="GALVA",MAX(G93,E93*24)*20.25%,IF(F93="INOX",MAX(G93,E93*40)*20.25%,IF(F93="COPPER",MAX(G93,E93*60)*20.25%,G93*20.25%)))) -> 0.496125 | I93: =+((I$9*G$7+I$11+I$13+I$15+I$17)*(1+I$7)+2500)/($G$5*$H$5)*G93 -> 0.258965 | J93: =(J$9+J$7*G93)/($G$5*$H$5)*G93 -> 0.44671727 | K93: =K$7*G93 -> 0.1715 | L93: =+G93*L$7 -> 0.6125 | M93: =+G93+H93+I93+J93*50%+K93+L93*30% -> 3.7836986 | N93: =+G93+H93+I93+J93*50%+K93+L93*70% -> 4.0286986 | O93: =+SUM(H93:L93)+G93 -> 4.4358073
A94: =+'Pricing Turkey'!A76 -> IT.41 | B94: =+'Pricing Turkey'!B76 -> BOITE DE LUBRIFICATION | C94: =+'Pricing Turkey'!C76 -> AUTRES | D94: =+'Pricing Turkey'!D76 -> Pc | E94: =+'Pricing Turkey'!E76 -> 0.3 | F94: =+'Pricing Turkey'!F76 -> PVC | G94: ='Pricing Turkey'!G76*G$7 -> 9.8 | H94: =IF(F94="STEEL",MAX(G94,E94*13)*20.25%,IF(F94="GALVA",MAX(G94,E94*24)*20.25%,IF(F94="INOX",MAX(G94,E94*40)*20.25%,IF(F94="COPPER",MAX(G94,E94*60)*20.25%,G94*20.25%)))) -> 1.9845 | I94: =+((I$9*G$7+I$11+I$13+I$15+I$17)*(1+I$7)+2500)/($G$5*$H$5)*G94 -> 1.03586 | J94: =(J$9+J$7*G94)/($G$5*$H$5)*G94 -> 1.7868763 | K94: =K$7*G94 -> 0.686 | L94: =+G94*L$7 -> 2.45 | M94: =+G94+H94+I94+J94*50%+K94+L94*30% -> 15.134798 | N94: =+G94+H94+I94+J94*50%+K94+L94*70% -> 16.114798 | O94: =+SUM(H94:L94)+G94 -> 17.743236
A95: =+'Pricing Turkey'!A77 -> IT.42 | B95: =+'Pricing Turkey'!B77 -> COULISSEAUX CABIN | C95: =+'Pricing Turkey'!C77 -> AUTRES | D95: =+'Pricing Turkey'!D77 -> Pc | E95: =+'Pricing Turkey'!E77 -> 1 | F95: =+'Pricing Turkey'!F80 -> GALVA | G95: ='Pricing Turkey'!G77*G$7 -> 58.8 | H95: =IF(F95="STEEL",MAX(G95,E95*13)*20.25%,IF(F95="GALVA",MAX(G95,E95*24)*20.25%,IF(F95="INOX",MAX(G95,E95*40)*20.25%,IF(F95="COPPER",MAX(G95,E95*60)*20.25%,G95*20.25%)))) -> 11.907 | I95: =+((I$9*G$7+I$11+I$13+I$15+I$17)*(1+I$7)+2500)/($G$5*$H$5)*G95 -> 6.21516 | J95: =(J$9+J$7*G95)/($G$5*$H$5)*G95 -> 10.721546 | K95: =K$7*G95 -> 4.116 | L95: =+G95*L$7 -> 14.7 | M95: =+G95+H95+I95+J95*50%+K95+L95*30% -> 90.808933 | N95: =+G95+H95+I95+J95*50%+K95+L95*70% -> 96.688933 | O95: =+SUM(H95:L95)+G95 -> 106.45971
A96: =+'Pricing Turkey'!A78 -> IT.43 | B96: =+'Pricing Turkey'!B78 -> COULISSEAUX CONTRE-POIDS | C96: =+'Pricing Turkey'!C78 -> AUTRES | D96: =+'Pricing Turkey'!D78 -> Pc | E96: =+'Pricing Turkey'!E78 -> 0.6 | F96: =+'Pricing Turkey'!F78 -> STEEL | G96: ='Pricing Turkey'!G78*G$7 -> 34.3 | H96: =IF(F96="STEEL",MAX(G96,E96*13)*20.25%,IF(F96="GALVA",MAX(G96,E96*24)*20.25%,IF(F96="INOX",MAX(G96,E96*40)*20.25%,IF(F96="COPPER",MAX(G96,E96*60)*20.25%,G96*20.25%)))) -> 6.94575 | I96: =+((I$9*G$7+I$11+I$13+I$15+I$17)*(1+I$7)+2500)/($G$5*$H$5)*G96 -> 3.62551 | J96: =(J$9+J$7*G96)/($G$5*$H$5)*G96 -> 6.254151 | K96: =K$7*G96 -> 2.401 | L96: =+G96*L$7 -> 8.575 | M96: =+G96+H96+I96+J96*50%+K96+L96*30% -> 52.971835 | N96: =+G96+H96+I96+J96*50%+K96+L96*70% -> 56.401835 | O96: =+SUM(H96:L96)+G96 -> 62.101411
A97: =+'Pricing Turkey'!A79 -> IT.44 | B97: =+'Pricing Turkey'!B79 -> GARNITURE COULISSEAU 70 | C97: =+'Pricing Turkey'!C79 -> AUTRES | D97: =+'Pricing Turkey'!D79 -> Pc | E97: =+'Pricing Turkey'!E79 -> 0.14 | F97: =+'Pricing Turkey'!F79 -> PVC | G97: ='Pricing Turkey'!G79*G$7 -> 4.9 | H97: =IF(F97="STEEL",MAX(G97,E97*13)*20.25%,IF(F97="GALVA",MAX(G97,E97*24)*20.25%,IF(F97="INOX",MAX(G97,E97*40)*20.25%,IF(F97="COPPER",MAX(G97,E97*60)*20.25%,G97*20.25%)))) -> 0.99225 | I97: =+((I$9*G$7+I$11+I$13+I$15+I$17)*(1+I$7)+2500)/($G$5*$H$5)*G97 -> 0.51793 | J97: =(J$9+J$7*G97)/($G$5*$H$5)*G97 -> 0.89343573 | K97: =K$7*G97 -> 0.343 | L97: =+G97*L$7 -> 1.225 | M97: =+G97+H97+I97+J97*50%+K97+L97*30% -> 7.5673979 | N97: =+G97+H97+I97+J97*50%+K97+L97*70% -> 8.0573979 | O97: =+SUM(H97:L97)+G97 -> 8.8716157
A98: =+'Pricing Turkey'!A80 -> IT.45 | B98: =+'Pricing Turkey'!B80 -> POULIE RENVOI 5*10 GEARBOX | C98: =+'Pricing Turkey'!C80 -> AUTRES | D98: =+'Pricing Turkey'!D80 -> Pc | E98: =+'Pricing Turkey'!E80 -> 20 | F98: =+'Pricing Turkey'!#REF! -> #REF! | G98: ='Pricing Turkey'!G80*G$7 -> 588 | H98: =IF(F98="STEEL",MAX(G98,E98*13)*20.25%,IF(F98="GALVA",MAX(G98,E98*24)*20.25%,IF(F98="INOX",MAX(G98,E98*40)*20.25%,IF(F98="COPPER",MAX(G98,E98*60)*20.25%,G98*20.25%)))) -> #REF! | I98: =+((I$9*G$7+I$11+I$13+I$15+I$17)*(1+I$7)+2500)/($G$5*$H$5)*G98 -> 62.1516 | J98: =(J$9+J$7*G98)/($G$5*$H$5)*G98 -> 107.24657 | K98: =K$7*G98 -> 41.16 | L98: =+G98*L$7 -> 147 | M98: =+G98+H98+I98+J98*50%+K98+L98*30% -> #REF! | N98: =+G98+H98+I98+J98*50%+K98+L98*70% -> #REF! | O98: =+SUM(H98:L98)+G98 -> #REF!
A99: =+'Pricing Turkey'!A81 -> IT.46 | B99: =+'Pricing Turkey'!B81 -> BUFFER CABIN/C,P / LES BOUDINS SET COMPLET | C99: =+'Pricing Turkey'!C81 -> AUTRES | D99: =+'Pricing Turkey'!D81 -> SET | E99: =+'Pricing Turkey'!E81 -> 22 | F99: =+'Pricing Turkey'!F81 -> GALVA | G99: ='Pricing Turkey'!G81*G$7 -> 323.4 | H99: =IF(F99="STEEL",MAX(G99,E99*13)*20.25%,IF(F99="GALVA",MAX(G99,E99*24)*20.25%,IF(F99="INOX",MAX(G99,E99*40)*20.25%,IF(F99="COPPER",MAX(G99,E99*60)*20.25%,G99*20.25%)))) -> 106.92 | I99: =+((I$9*G$7+I$11+I$13+I$15+I$17)*(1+I$7)+2500)/($G$5*$H$5)*G99 -> 34.18338 | J99: =(J$9+J$7*G99)/($G$5*$H$5)*G99 -> 58.977059 | K99: =K$7*G99 -> 22.638 | L99: =+G99*L$7 -> 80.85 | M99: =+G99+H99+I99+J99*50%+K99+L99*30% -> 540.88491 | N99: =+G99+H99+I99+J99*50%+K99+L99*70% -> 573.22491 | O99: =+SUM(H99:L99)+G99 -> 626.96844
A100: =+'Pricing Turkey'!A82 -> IT.47 | B100: =+'Pricing Turkey'!B82 -> CABLE 0,75MM | C100: =+'Pricing Turkey'!C82 -> CABLES ELECTRIQUES & ACCESSOIRES | D100: =+'Pricing Turkey'!D82 -> M | E100: =+'Pricing Turkey'!E82 -> 0.02 | F100: =+'Pricing Turkey'!F82 -> COPPER | G100: ='Pricing Turkey'!G82*G$7 -> 0.2254 | H100: =IF(F100="STEEL",MAX(G100,E100*13)*20.25%,IF(F100="GALVA",MAX(G100,E100*24)*20.25%,IF(F100="INOX",MAX(G100,E100*40)*20.25%,IF(F100="COPPER",MAX(G100,E100*60)*20.25%,G100*20.25%)))) -> 0.243 | I100: =+((I$9*G$7+I$11+I$13+I$15+I$17)*(1+I$7)+2500)/($G$5*$H$5)*G100 -> 0.02382478 | J100: =(J$9+J$7*G100)/($G$5*$H$5)*G100 -> 0.041097938 | K100: =K$7*G100 -> 0.015778 | L100: =+G100*L$7 -> 0.05635 | M100: =+G100+H100+I100+J100*50%+K100+L100*30% -> 0.54545675 | N100: =+G100+H100+I100+J100*50%+K100+L100*70% -> 0.56799675 | O100: =+SUM(H100:L100)+G100 -> 0.60545072
A101: =+'Pricing Turkey'!A83 -> IT.48 | B101: =+'Pricing Turkey'!B83 -> CABLE 4MM | C101: =+'Pricing Turkey'!C83 -> CABLES ELECTRIQUES & ACCESSOIRES | D101: =+'Pricing Turkey'!D83 -> M | E101: =+'Pricing Turkey'!E83 -> 0.03 | F101: =+'Pricing Turkey'!F83 -> COPPER | G101: ='Pricing Turkey'!G83*G$7 -> 1.0486 | H101: =IF(F101="STEEL",MAX(G101,E101*13)*20.25%,IF(F101="GALVA",MAX(G101,E101*24)*20.25%,IF(F101="INOX",MAX(G101,E101*40)*20.25%,IF(F101="COPPER",MAX(G101,E101*60)*20.25%,G101*20.25%)))) -> 0.3645 | I101: =+((I$9*G$7+I$11+I$13+I$15+I$17)*(1+I$7)+2500)/($G$5*$H$5)*G101 -> 0.11083702 | J101: =(J$9+J$7*G101)/($G$5*$H$5)*G101 -> 0.19119484 | K101: =K$7*G101 -> 0.073402 | L101: =+G101*L$7 -> 0.26215 | M101: =+G101+H101+I101+J101*50%+K101+L101*30% -> 1.7715814 | N101: =+G101+H101+I101+J101*50%+K101+L101*70% -> 1.8764414 | O101: =+SUM(H101:L101)+G101 -> 2.0506839
A102: =+'Pricing Turkey'!A84 -> IT.49 | B102: =+'Pricing Turkey'!B84 -> CÂBLE NUMÉRIQUE DT/13 | C102: =+'Pricing Turkey'!C84 -> CABLES ELECTRIQUES & ACCESSOIRES | D102: =+'Pricing Turkey'!D84 -> M | E102: =+'Pricing Turkey'!E84 -> 0.04 | F102: =+'Pricing Turkey'!F84 -> COPPER | G102: ='Pricing Turkey'!G84*G$7 -> 1.1956 | H102: =IF(F102="STEEL",MAX(G102,E102*13)*20.25%,IF(F102="GALVA",MAX(G102,E102*24)*20.25%,IF(F102="INOX",MAX(G102,E102*40)*20.25%,IF(F102="COPPER",MAX(G102,E102*60)*20.25%,G102*20.25%)))) -> 0.486 | I102: =+((I$9*G$7+I$11+I$13+I$15+I$17)*(1+I$7)+2500)/($G$5*$H$5)*G102 -> 0.12637492 | J102: =(J$9+J$7*G102)/($G$5*$H$5)*G102 -> 0.21799788 | K102: =K$7*G102 -> 0.083692 | L102: =+G102*L$7 -> 0.2989 | M102: =+G102+H102+I102+J102*50%+K102+L102*30% -> 2.0903359 | N102: =+G102+H102+I102+J102*50%+K102+L102*70% -> 2.2098959 | O102: =+SUM(H102:L102)+G102 -> 2.4085648
A103: =+'Pricing Turkey'!A85 -> IT.50 | B103: =+'Pricing Turkey'!B85 -> TTR CABLE 3*0,75MM | C103: =+'Pricing Turkey'!C85 -> CABLES ELECTRIQUES & ACCESSOIRES | D103: =+'Pricing Turkey'!D85 -> M | E103: =+'Pricing Turkey'!E85 -> 0.05 | F103: =+'Pricing Turkey'!F85 -> COPPER | G103: ='Pricing Turkey'!G85*G$7 -> 1.3426 | H103: =IF(F103="STEEL",MAX(G103,E103*13)*20.25%,IF(F103="GALVA",MAX(G103,E103*24)*20.25%,IF(F103="INOX",MAX(G103,E103*40)*20.25%,IF(F103="COPPER",MAX(G103,E103*60)*20.25%,G103*20.25%)))) -> 0.6075 | I103: =+((I$9*G$7+I$11+I$13+I$15+I$17)*(1+I$7)+2500)/($G$5*$H$5)*G103 -> 0.14191282 | J103: =(J$9+J$7*G103)/($G$5*$H$5)*G103 -> 0.24480091 | K103: =K$7*G103 -> 0.093982 | L103: =+G103*L$7 -> 0.33565 | M103: =+G103+H103+I103+J103*50%+K103+L103*30% -> 2.4090903 | N103: =+G103+H103+I103+J103*50%+K103+L103*70% -> 2.5433503 | O103: =+SUM(H103:L103)+G103 -> 2.7664457
A104: =+'Pricing Turkey'!A86 -> IT.51 | B104: =+'Pricing Turkey'!B86 -> CABLE SOUPLE 24 36 -> 75 DH / 24 -> 55 À 60 DH | C104: =+'Pricing Turkey'!C86 -> CABLES ELECTRIQUES & ACCESSOIRES | D104: =+'Pricing Turkey'!D86 -> M | E104: =+'Pricing Turkey'!E86 -> 1.2 | F104: =+'Pricing Turkey'!F86 -> COPPER | G104: ='Pricing Turkey'!G86*G$7 -> 15.12434 | H104: =IF(F104="STEEL",MAX(G104,E104*13)*20.25%,IF(F104="GALVA",MAX(G104,E104*24)*20.25%,IF(F104="INOX",MAX(G104,E104*40)*20.25%,IF(F104="COPPER",MAX(G104,E104*60)*20.25%,G104*20.25%)))) -> 14.58 | I104: =+((I$9*G$7+I$11+I$13+I$15+I$17)*(1+I$7)+2500)/($G$5*$H$5)*G104 -> 1.5986427 | J104: =(J$9+J$7*G104)/($G$5*$H$5)*G104 -> 2.7576942 | K104: =K$7*G104 -> 1.0587038 | L104: =+G104*L$7 -> 3.781085 | M104: =+G104+H104+I104+J104*50%+K104+L104*30% -> 34.874859 | N104: =+G104+H104+I104+J104*50%+K104+L104*70% -> 36.387293 | O104: =+SUM(H104:L104)+G104 -> 38.900466
A105: =+'Pricing Turkey'!A87 -> IT.52 | B105: =+'Pricing Turkey'!B87 -> SUPPORT CABLE SOUPLE TYPE RECTANGLE | C105: =+'Pricing Turkey'!C87 -> CABLES ELECTRIQUES & ACCESSOIRES | D105: =+'Pricing Turkey'!D87 -> M | E105: =+'Pricing Turkey'!E87 -> 0.3 | F105: =+'Pricing Turkey'!F87 -> COPPER | G105: ='Pricing Turkey'!G87*G$7 -> 7.84 | H105: =IF(F105="STEEL",MAX(G105,E105*13)*20.25%,IF(F105="GALVA",MAX(G105,E105*24)*20.25%,IF(F105="INOX",MAX(G105,E105*40)*20.25%,IF(F105="COPPER",MAX(G105,E105*60)*20.25%,G105*20.25%)))) -> 3.645 | I105: =+((I$9*G$7+I$11+I$13+I$15+I$17)*(1+I$7)+2500)/($G$5*$H$5)*G105 -> 0.828688 | J105: =(J$9+J$7*G105)/($G$5*$H$5)*G105 -> 1.4294995 | K105: =K$7*G105 -> 0.5488 | L105: =+G105*L$7 -> 1.96 | M105: =+G105+H105+I105+J105*50%+K105+L105*30% -> 14.165238 | N105: =+G105+H105+I105+J105*50%+K105+L105*70% -> 14.949238 | O105: =+SUM(H105:L105)+G105 -> 16.251987
A106: =+'Pricing Turkey'!A88 -> IT.53 | B106: =+'Pricing Turkey'!B88 -> WIRE DUCT GOULLOTTE 40X40 | C106: =+'Pricing Turkey'!C88 -> CABLES ELECTRIQUES & ACCESSOIRES | D106: =+'Pricing Turkey'!D88 -> M | E106: =+'Pricing Turkey'!E88 -> 0.5 | F106: =+'Pricing Turkey'!F88 -> COPPER | G106: ='Pricing Turkey'!G88*G$7 -> 3.92 | H106: =IF(F106="STEEL",MAX(G106,E106*13)*20.25%,IF(F106="GALVA",MAX(G106,E106*24)*20.25%,IF(F106="INOX",MAX(G106,E106*40)*20.25%,IF(F106="COPPER",MAX(G106,E106*60)*20.25%,G106*20.25%)))) -> 6.075 | I106: =+((I$9*G$7+I$11+I$13+I$15+I$17)*(1+I$7)+2500)/($G$5*$H$5)*G106 -> 0.414344 | J106: =(J$9+J$7*G106)/($G$5*$H$5)*G106 -> 0.7147482 | K106: =K$7*G106 -> 0.2744 | L106: =+G106*L$7 -> 0.98 | M106: =+G106+H106+I106+J106*50%+K106+L106*30% -> 11.335118 | N106: =+G106+H106+I106+J106*50%+K106+L106*70% -> 11.727118 | O106: =+SUM(H106:L106)+G106 -> 12.378492
A107: =+'Pricing Turkey'!A89 -> IT.54 | B107: =+'Pricing Turkey'!B89 -> TUBE SPIRALÉ 14MM | C107: =+'Pricing Turkey'!C89 -> CABLES ELECTRIQUES & ACCESSOIRES | D107: =+'Pricing Turkey'!D89 -> M | E107: =+'Pricing Turkey'!E89 -> 1 | F107: =+'Pricing Turkey'!F89 -> COPPER | G107: ='Pricing Turkey'!G89*G$7 -> 0.882 | H107: =IF(F107="STEEL",MAX(G107,E107*13)*20.25%,IF(F107="GALVA",MAX(G107,E107*24)*20.25%,IF(F107="INOX",MAX(G107,E107*40)*20.25%,IF(F107="COPPER",MAX(G107,E107*60)*20.25%,G107*20.25%)))) -> 12.15 | I107: =+((I$9*G$7+I$11+I$13+I$15+I$17)*(1+I$7)+2500)/($G$5*$H$5)*G107 -> 0.0932274 | J107: =(J$9+J$7*G107)/($G$5*$H$5)*G107 -> 0.16081808 | K107: =K$7*G107 -> 0.06174 | L107: =+G107*L$7 -> 0.2205 | M107: =+G107+H107+I107+J107*50%+K107+L107*30% -> 13.333526 | N107: =+G107+H107+I107+J107*50%+K107+L107*70% -> 13.421726 | O107: =+SUM(H107:L107)+G107 -> 13.568285
A108: =+'Pricing Turkey'!A90 -> IT.55 | B108: =+'Pricing Turkey'!B90 -> BOUTONS DE CABINE D’ASCENSEUR 2M | C108: =+'Pricing Turkey'!C90 -> BOUTONS | D108: =+'Pricing Turkey'!D90 -> Pc | E108: =+'Pricing Turkey'!E90 -> 1.8 | F108: =+'Pricing Turkey'!F90 -> INOX | G108: ='Pricing Turkey'!G90*G$7 -> 931 | H108: =IF(F108="STEEL",MAX(G108,E108*13)*20.25%,IF(F108="GALVA",MAX(G108,E108*24)*20.25%,IF(F108="INOX",MAX(G108,E108*40)*20.25%,IF(F108="COPPER",MAX(G108,E108*60)*20.25%,G108*20.25%)))) -> 188.5275 | I108: =+((I$9*G$7+I$11+I$13+I$15+I$17)*(1+I$7)+2500)/($G$5*$H$5)*G108 -> 98.4067 | J108: =(J$9+J$7*G108)/($G$5*$H$5)*G108 -> 169.83901 | K108: =K$7*G108 -> 65.17 | L108: =+G108*L$7 -> 232.75 | M108: =+G108+H108+I108+J108*50%+K108+L108*30% -> 1437.8487 | N108: =+G108+H108+I108+J108*50%+K108+L108*70% -> 1530.9487 | O108: =+SUM(H108:L108)+G108 -> 1685.6932
A109: =+'Pricing Turkey'!A91 -> IT.56 | B109: =+'Pricing Turkey'!B91 -> BOUTONS DE CABINE D’ASCENSEUR 1M | C109: =+'Pricing Turkey'!C91 -> BOUTONS | D109: =+'Pricing Turkey'!D91 -> Pc | E109: =+'Pricing Turkey'!E91 -> 1.2 | F109: =+'Pricing Turkey'!F91 -> INOX | G109: ='Pricing Turkey'!G91*G$7 -> 784 | H109: =IF(F109="STEEL",MAX(G109,E109*13)*20.25%,IF(F109="GALVA",MAX(G109,E109*24)*20.25%,IF(F109="INOX",MAX(G109,E109*40)*20.25%,IF(F109="COPPER",MAX(G109,E109*60)*20.25%,G109*20.25%)))) -> 158.76 | I109: =+((I$9*G$7+I$11+I$13+I$15+I$17)*(1+I$7)+2500)/($G$5*$H$5)*G109 -> 82.8688 | J109: =(J$9+J$7*G109)/($G$5*$H$5)*G109 -> 143.0108 | K109: =K$7*G109 -> 54.88 | L109: =+G109*L$7 -> 196 | M109: =+G109+H109+I109+J109*50%+K109+L109*30% -> 1210.8142 | N109: =+G109+H109+I109+J109*50%+K109+L109*70% -> 1289.2142 | O109: =+SUM(H109:L109)+G109 -> 1419.5196
A110: =+'Pricing Turkey'!A92 -> IT.57 | B110: =+'Pricing Turkey'!B92 -> BOUTON PALIER AVEC AFFICHEUR | C110: =+'Pricing Turkey'!C92 -> BOUTONS | D110: =+'Pricing Turkey'!D92 -> Pc | E110: =+'Pricing Turkey'!E92 -> 1.5 | F110: =+'Pricing Turkey'!F92 -> INOX | G110: ='Pricing Turkey'!G92*G$7 -> 62.72 | H110: =IF(F110="STEEL",MAX(G110,E110*13)*20.25%,IF(F110="GALVA",MAX(G110,E110*24)*20.25%,IF(F110="INOX",MAX(G110,E110*40)*20.25%,IF(F110="COPPER",MAX(G110,E110*60)*20.25%,G110*20.25%)))) -> 12.7008 | I110: =+((I$9*G$7+I$11+I$13+I$15+I$17)*(1+I$7)+2500)/($G$5*$H$5)*G110 -> 6.629504 | J110: =(J$9+J$7*G110)/($G$5*$H$5)*G110 -> 11.43634 | K110: =K$7*G110 -> 4.3904 | L110: =+G110*L$7 -> 15.68 | M110: =+G110+H110+I110+J110*50%+K110+L110*30% -> 96.862874 | N110: =+G110+H110+I110+J110*50%+K110+L110*70% -> 103.13487 | O110: =+SUM(H110:L110)+G110 -> 113.55704
... A126: =+'Pricing Turkey'!A108 -> IT.73 | B126: =+'Pricing Turkey'!B108 -> UPS | C126: =+'Pricing Turkey'!C108 -> AUTRES | D126: =+'Pricing Turkey'!D108 -> Pc | E126: =+'Pricing Turkey'!E108 -> 25 | F126: =+'Pricing Turkey'!F108 -> - | G126: ='Pricing Turkey'!G108*G$7 -> 735 | H126: =IF(F126="STEEL",MAX(G126,E126*13)*20.25%,IF(F126="GALVA",MAX(G126,E126*24)*20.25%,IF(F126="INOX",MAX(G126,E126*40)*20.25%,IF(F126="COPPER",MAX(G126,E126*60)*20.25%,G126*20.25%)))) -> 148.8375 | I126: =+((I$9*G$7+I$11+I$13+I$15+I$17)*(1+I$7)+2500)/($G$5*$H$5)*G126 -> 77.6895 | J126: =(J$9+J$7*G126)/($G$5*$H$5)*G126 -> 134.06902 | K126: =K$7*G126 -> 51.45 | L126: =+G126*L$7 -> 183.75 | M126: =+G126+H126+I126+J126*50%+K126+L126*30% -> 1135.1365 | N126: =+G126+H126+I126+J126*50%+K126+L126*70% -> 1208.6365 | O126: =+SUM(H126:L126)+G126 -> 1330.796
A127: =+'Pricing Turkey'!A109 -> IT.74 | B127: =+'Pricing Turkey'!B109 -> CHASSIS MOTEUR STANDARD VVVF 2V AVEC CYLINBLOC | C127: =+'Pricing Turkey'!C109 -> MOTEUR | D127: =+'Pricing Turkey'!D109 -> SET | E127: =+'Pricing Turkey'!E109 -> 75 | F127: =+'Pricing Turkey'!#REF! -> #REF! | G127: ='Pricing Turkey'!G109*G$7 -> 539 | H127: =IF(F127="STEEL",MAX(G127,E127*13)*20.25%,IF(F127="GALVA",MAX(G127,E127*24)*20.25%,IF(F127="INOX",MAX(G127,E127*40)*20.25%,IF(F127="COPPER",MAX(G127,E127*60)*20.25%,G127*20.25%)))) -> #REF! | I127: =+((I$9*G$7+I$11+I$13+I$15+I$17)*(1+I$7)+2500)/($G$5*$H$5)*G127 -> 56.9723 | J127: =(J$9+J$7*G127)/($G$5*$H$5)*G127 -> 98.306719 | K127: =K$7*G127 -> 37.73 | L127: =+G127*L$7 -> 134.75 | M127: =+G127+H127+I127+J127*50%+K127+L127*30% -> #REF! | N127: =+G127+H127+I127+J127*50%+K127+L127*70% -> #REF! | O127: =+SUM(H127:L127)+G127 -> #REF!
A128: =+'Pricing Turkey'!A110 -> IT.75 | B128: =+'Pricing Turkey'!B110 -> CHASSIS MOTEUR GEARLESS | C128: =+'Pricing Turkey'!C110 -> MOTEUR | D128: =+'Pricing Turkey'!D110 -> SET | E128: =+'Pricing Turkey'!E110 -> 260 | F128: =+'Pricing Turkey'!F110 -> STEEL | G128: ='Pricing Turkey'!G110*G$7 -> 2450 | H128: =IF(F128="STEEL",MAX(G128,E128*13)*20.25%,IF(F128="GALVA",MAX(G128,E128*24)*20.25%,IF(F128="INOX",MAX(G128,E128*40)*20.25%,IF(F128="COPPER",MAX(G128,E128*60)*20.25%,G128*20.25%)))) -> 684.45 | I128: =+((I$9*G$7+I$11+I$13+I$15+I$17)*(1+I$7)+2500)/($G$5*$H$5)*G128 -> 258.965 | J128: =(J$9+J$7*G128)/($G$5*$H$5)*G128 -> 447.31692 | K128: =K$7*G128 -> 171.5 | L128: =+G128*L$7 -> 612.5 | M128: =+G128+H128+I128+J128*50%+K128+L128*30% -> 3972.3235 | N128: =+G128+H128+I128+J128*50%+K128+L128*70% -> 4217.3235 | O128: =+SUM(H128:L128)+G128 -> 4624.7319
A129: =+'Pricing Turkey'!A111 -> IT.76 | B129: =+'Pricing Turkey'!B111 -> ARMOIRE GEARLESS EEM + BOITE INSPECTION + ALARM MAX4 MAX6 MAX8 | C129: =+'Pricing Turkey'!C111 -> ARMOIRE | D129: =+'Pricing Turkey'!D111 -> SET | E129: =+'Pricing Turkey'!E111 -> 32 | F129: =+'Pricing Turkey'!F111 -> - | G129: ='Pricing Turkey'!G111*G$7 -> 7154 | H129: =IF(F129="STEEL",MAX(G129,E129*13)*20.25%,IF(F129="GALVA",MAX(G129,E129*24)*20.25%,IF(F129="INOX",MAX(G129,E129*40)*20.25%,IF(F129="COPPER",MAX(G129,E129*60)*20.25%,G129*20.25%)))) -> 1448.685 | I129: =+((I$9*G$7+I$11+I$13+I$15+I$17)*(1+I$7)+2500)/($G$5*$H$5)*G129 -> 756.1778 | J129: =(J$9+J$7*G129)/($G$5*$H$5)*G129 -> 1309.5306 | K129: =K$7*G129 -> 500.78 | L129: =+G129*L$7 -> 1788.5 | M129: =+G129+H129+I129+J129*50%+K129+L129*30% -> 11050.958 | N129: =+G129+H129+I129+J129*50%+K129+L129*70% -> 11766.358 | O129: =+SUM(H129:L129)+G129 -> 12957.673
A130: =+'Pricing Turkey'!A112 -> IT.77 | B130: =+'Pricing Turkey'!B112 -> ARMOIRE GEARLESS EEM + BOITE INSPECTION + ALARM MAX10 | C130: =+'Pricing Turkey'!C112 -> ARMOIRE | D130: =+'Pricing Turkey'!D112 -> SET | E130: =+'Pricing Turkey'!E112 -> 260 | F130: =+'Pricing Turkey'!F112 -> - | G130: ='Pricing Turkey'!G112*G$7 -> 7154 | H130: =IF(F130="STEEL",MAX(G130,E130*13)*20.25%,IF(F130="GALVA",MAX(G130,E130*24)*20.25%,IF(F130="INOX",MAX(G130,E130*40)*20.25%,IF(F130="COPPER",MAX(G130,E130*60)*20.25%,G130*20.25%)))) -> 1448.685 | I130: =+((I$9*G$7+I$11+I$13+I$15+I$17)*(1+I$7)+2500)/($G$5*$H$5)*G130 -> 756.1778 | J130: =(J$9+J$7*G130)/($G$5*$H$5)*G130 -> 1309.5306 | K130: =K$7*G130 -> 500.78 | L130: =+G130*L$7 -> 1788.5 | M130: =+G130+H130+I130+J130*50%+K130+L130*30% -> 11050.958 | N130: =+G130+H130+I130+J130*50%+K130+L130*70% -> 11766.358 | O130: =+SUM(H130:L130)+G130 -> 12957.673
A131: =+'Pricing Turkey'!A113 -> IT.78 | B131: =+'Pricing Turkey'!B113 -> OPERATEUR 60CM ATERYA | C131: =+'Pricing Turkey'!C113 -> OPÉRATEUR | D131: =+'Pricing Turkey'!D113 -> Pc | E131: =+'Pricing Turkey'!E113 -> 1.5 | F131: =+'Pricing Turkey'!F113 -> INOX | G131: ='Pricing Turkey'!G113*G$7 -> 3920 | H131: =IF(F131="STEEL",MAX(G131,E131*13)*20.25%,IF(F131="GALVA",MAX(G131,E131*24)*20.25%,IF(F131="INOX",MAX(G131,E131*40)*20.25%,IF(F131="COPPER",MAX(G131,E131*60)*20.25%,G131*20.25%)))) -> 793.8 | I131: =+((I$9*G$7+I$11+I$13+I$15+I$17)*(1+I$7)+2500)/($G$5*$H$5)*G131 -> 414.344 | J131: =(J$9+J$7*G131)/($G$5*$H$5)*G131 -> 716.28331 | K131: =K$7*G131 -> 274.4 | L131: =+G131*L$7 -> 980 | M131: =+G131+H131+I131+J131*50%+K131+L131*30% -> 6054.6857 | N131: =+G131+H131+I131+J131*50%+K131+L131*70% -> 6446.6857 | O131: =+SUM(H131:L131)+G131 -> 7098.8273
A132: =+'Pricing Turkey'!A114 -> IT.79 | B132: =+'Pricing Turkey'!B114 -> CABINE 90*62CM | C132: =+'Pricing Turkey'!C114 -> CABINE & ARCADE | D132: =+'Pricing Turkey'!D114 -> Pc | E132: =+'Pricing Turkey'!E114 -> 420 | F132: =+'Pricing Turkey'!F114 -> INOX | G132: ='Pricing Turkey'!G114*G$7 -> 8820 | H132: =IF(F132="STEEL",MAX(G132,E132*13)*20.25%,IF(F132="GALVA",MAX(G132,E132*24)*20.25%,IF(F132="INOX",MAX(G132,E132*40)*20.25%,IF(F132="COPPER",MAX(G132,E132*60)*20.25%,G132*20.25%)))) -> 3402 | I132: =+((I$9*G$7+I$11+I$13+I$15+I$17)*(1+I$7)+2500)/($G$5*$H$5)*G132 -> 932.274 | J132: =(J$9+J$7*G132)/($G$5*$H$5)*G132 -> 1615.9592 | K132: =K$7*G132 -> 617.4 | L132: =+G132*L$7 -> 2205 | M132: =+G132+H132+I132+J132*50%+K132+L132*30% -> 15241.154 | N132: =+G132+H132+I132+J132*50%+K132+L132*70% -> 16123.154 | O132: =+SUM(H132:L132)+G132 -> 17592.633
A133: =+'Pricing Turkey'!A115 -> IT.80 | B133: =+'Pricing Turkey'!B115 -> CALIBTEURS FIN DE COURSE | C133: =+'Pricing Turkey'!C115 -> AUTRES | D133: =+'Pricing Turkey'!D115 -> Pc | E133: =+'Pricing Turkey'!E115 -> 1 | F133: =+'Pricing Turkey'!F115 -> GALVA | G133: ='Pricing Turkey'!G115*G$7 -> 39.2 | H133: =IF(F133="STEEL",MAX(G133,E133*13)*20.25%,IF(F133="GALVA",MAX(G133,E133*24)*20.25%,IF(F133="INOX",MAX(G133,E133*40)*20.25%,IF(F133="COPPER",MAX(G133,E133*60)*20.25%,G133*20.25%)))) -> 7.938 | I133: =+((I$9*G$7+I$11+I$13+I$15+I$17)*(1+I$7)+2500)/($G$5*$H$5)*G133 -> 4.14344 | J133: =(J$9+J$7*G133)/($G$5*$H$5)*G133 -> 7.1476203 | K133: =K$7*G133 -> 2.744 | L133: =+G133*L$7 -> 9.8 | M133: =+G133+H133+I133+J133*50%+K133+L133*30% -> 60.53925 | N133: =+G133+H133+I133+J133*50%+K133+L133*70% -> 64.45925 | O133: =+SUM(H133:L133)+G133 -> 70.97306
A134: =+'Pricing Turkey'!A116 -> IT.81 | B134: =+'Pricing Turkey'!B116 -> GOSE 76CM - 31KG | C134: =+'Pricing Turkey'!C116 -> GOSE | D134: =+'Pricing Turkey'!D116 -> Pc | E134: =+'Pricing Turkey'!E116 -> 31 | F134: =+'Pricing Turkey'!F116 -> CONCRETE | G134: ='Pricing Turkey'!G116*G$7 -> 42.532 | H134: =IF(F134="STEEL",MAX(G134,E134*13)*20.25%,IF(F134="GALVA",MAX(G134,E134*24)*20.25%,IF(F134="INOX",MAX(G134,E134*40)*20.25%,IF(F134="COPPER",MAX(G134,E134*60)*20.25%,G134*20.25%)))) -> 8.61273 | I134: =+((I$9*G$7+I$11+I$13+I$15+I$17)*(1+I$7)+2500)/($G$5*$H$5)*G134 -> 4.4956324 | J134: =(J$9+J$7*G134)/($G$5*$H$5)*G134 -> 7.7551822 | K134: =K$7*G134 -> 2.97724 | L134: =+G134*L$7 -> 10.633 | M134: =+G134+H134+I134+J134*50%+K134+L134*60% -> 68.874994 | N134: =+G134+H134+I134+J134*50%+K134+L134*75% -> 70.469944 | O134: =+SUM(H134:L134)+G134 -> 77.005785
A135: =+'Pricing Turkey'!A117 -> IT.82 | B135: =+'Pricing Turkey'!B117 -> MOTEUR PRIMO 2V MAX4 + CHASSIS | C135: =+'Pricing Turkey'!C117 -> MOTEUR | D135: =+'Pricing Turkey'!D117 -> Pc | E135: =+'Pricing Turkey'!E117 -> 560 | F135: =+'Pricing Turkey'!F117 -> 0 | G135: ='Pricing Turkey'!G117*G$7 -> #VALUE! | H135: =IF(F135="STEEL",MAX(G135,E135*13)*20.25%,IF(F135="GALVA",MAX(G135,E135*24)*20.25%,IF(F135="INOX",MAX(G135,E135*40)*20.25%,IF(F135="COPPER",MAX(G135,E135*60)*20.25%,G135*20.25%)))) -> #VALUE! | I135: =+((I$9*G$7+I$11+I$13+I$15+I$17)*(1+I$7)+2500)/($G$5*$H$5)*G135 -> #VALUE! | J135: =(J$9+J$7*G135)/($G$5*$H$5)*G135 -> #VALUE! | K135: =K$7*G135 -> #VALUE! | L135: =+G135*L$7 -> #VALUE! | M135: =+G135+H135+I135+J135*50%+K135+L135*60% -> #VALUE! | N135: =+G135+H135+I135+J135*50%+K135+L135*75% -> #VALUE! | O135: =+SUM(H135:L135)+G135 -> #VALUE!
A136: =+'Pricing Turkey'!A118 -> IT.83 | B136: =+'Pricing Turkey'!B118 -> MOTEUR PRIMO 2V MAX6 + CHASSIS | C136: =+'Pricing Turkey'!C118 -> MOTEUR | D136: =+'Pricing Turkey'!D118 -> Pc | E136: =+'Pricing Turkey'!E118 -> 140 | F136: =+'Pricing Turkey'!F118 -> 0 | G136: ='Pricing Turkey'!G118*G$7 -> #VALUE! | H136: =IF(F136="STEEL",MAX(G136,E136*13)*20.25%,IF(F136="GALVA",MAX(G136,E136*24)*20.25%,IF(F136="INOX",MAX(G136,E136*40)*20.25%,IF(F136="COPPER",MAX(G136,E136*60)*20.25%,G136*20.25%)))) -> #VALUE! | I136: =+((I$9*G$7+I$11+I$13+I$15+I$17)*(1+I$7)+2500)/($G$5*$H$5)*G136 -> #VALUE! | J136: =(J$9+J$7*G136)/($G$5*$H$5)*G136 -> #VALUE! | K136: =K$7*G136 -> #VALUE! | L136: =+G136*L$7 -> #VALUE! | M136: =+G136+H136+I136+J136*50%+K136+L136*30% -> #VALUE! | N136: =+G136+H136+I136+J136*50%+K136+L136*70% -> #VALUE! | O136: =+SUM(H136:L136)+G136 -> #VALUE!
A137: =+'Pricing Turkey'!A119 -> IT.84 | B137: =+'Pricing Turkey'!B119 -> MOTEUR PRIMO 2V MAX8 + CHASSIS | C137: =+'Pricing Turkey'!C119 -> MOTEUR | D137: =+'Pricing Turkey'!D119 -> Pc | E137: =+'Pricing Turkey'!E119 -> 135 | F137: =+'Pricing Turkey'!F119 -> 0 | G137: ='Pricing Turkey'!G119*G$7 -> #VALUE! | H137: =IF(F137="STEEL",MAX(G137,E137*13)*20.25%,IF(F137="GALVA",MAX(G137,E137*24)*20.25%,IF(F137="INOX",MAX(G137,E137*40)*20.25%,IF(F137="COPPER",MAX(G137,E137*60)*20.25%,G137*20.25%)))) -> #VALUE! | I137: =+((I$9*G$7+I$11+I$13+I$15+I$17)*(1+I$7)+2500)/($G$5*$H$5)*G137 -> #VALUE! | J137: =(J$9+J$7*G137)/($G$5*$H$5)*G137 -> #VALUE! | K137: =K$7*G137 -> #VALUE! | L137: =+G137*L$7 -> #VALUE! | M137: =+G137+H137+I137+J137*50%+K137+L137*30% -> #VALUE! | N137: =+G137+H137+I137+J137*50%+K137+L137*70% -> #VALUE! | O137: =+SUM(H137:L137)+G137 -> #VALUE!
A138: =+'Pricing Turkey'!A120 -> IT.85 | B138: =+'Pricing Turkey'!B120 -> MOTEUR PRIMO 2V MAX10 + CHASSIS | C138: =+'Pricing Turkey'!C120 -> MOTEUR | D138: =+'Pricing Turkey'!D120 -> Pc | E138: =+'Pricing Turkey'!E120 -> 35 | F138: =+'Pricing Turkey'!F120 -> 0 | G138: ='Pricing Turkey'!G120*G$7 -> #VALUE! | H138: =IF(F138="STEEL",MAX(G138,E138*13)*20.25%,IF(F138="GALVA",MAX(G138,E138*24)*20.25%,IF(F138="INOX",MAX(G138,E138*40)*20.25%,IF(F138="COPPER",MAX(G138,E138*60)*20.25%,G138*20.25%)))) -> #VALUE! | I138: =+((I$9*G$7+I$11+I$13+I$15+I$17)*(1+I$7)+2500)/($G$5*$H$5)*G138 -> #VALUE! | J138: =(J$9+J$7*G138)/($G$5*$H$5)*G138 -> #VALUE! | K138: =K$7*G138 -> #VALUE! | L138: =+G138*L$7 -> #VALUE! | M138: =+G138+H138+I138+J138*50%+K138+L138*30% -> #VALUE! | N138: =+G138+H138+I138+J138*50%+K138+L138*70% -> #VALUE! | O138: =+SUM(H138:L138)+G138 -> #VALUE!
A139: =+'Pricing Turkey'!A121 -> IT.86 | B139: =+'Pricing Turkey'!B121 -> PORTES CABINE / OPERATEUR *DEAS* INOX 70/80 | C139: =+'Pricing Turkey'!C121 -> OPÉRATEUR | D139: =+'Pricing Turkey'!D121 -> Pc | E139: =+'Pricing Turkey'!E121 -> 110 | F139: =+'Pricing Turkey'!F121 -> INOX | G139: ='Pricing Turkey'!G121*G$7 -> 3234 | H139: =IF(F139="STEEL",MAX(G139,E139*13)*20.25%,IF(F139="GALVA",MAX(G139,E139*24)*20.25%,IF(F139="INOX",MAX(G139,E139*40)*20.25%,IF(F139="COPPER",MAX(G139,E139*60)*20.25%,G139*20.25%)))) -> 891 | I139: =+((I$9*G$7+I$11+I$13+I$15+I$17)*(1+I$7)+2500)/($G$5*$H$5)*G139 -> 341.8338 | J139: =(J$9+J$7*G139)/($G$5*$H$5)*G139 -> 590.71188 | K139: =K$7*G139 -> 226.38 | L139: =+G139*L$7 -> 808.5 | M139: =+G139+H139+I139+J139*50%+K139+L139*30% -> 5231.1197 | N139: =+G139+H139+I139+J139*50%+K139+L139*70% -> 5554.5197 | O139: =+SUM(H139:L139)+G139 -> 6092.4257
A140: =+'Pricing Turkey'!A122 -> IT.87 | B140: =+'Pricing Turkey'!B122 -> PORTES PALIERE AUTOMATIQUE INOX *DEAS* 70/80 | C140: =+'Pricing Turkey'!C122 -> PORTE | D140: =+'Pricing Turkey'!D122 -> Pc | E140: =+'Pricing Turkey'!E122 -> 135 | F140: =+'Pricing Turkey'!F122 -> INOX | G140: ='Pricing Turkey'!G122*G$7 -> 2205 | H140: =IF(F140="STEEL",MAX(G140,E140*13)*20.25%,IF(F140="GALVA",MAX(G140,E140*24)*20.25%,IF(F140="INOX",MAX(G140,E140*40)*20.25%,IF(F140="COPPER",MAX(G140,E140*60)*20.25%,G140*20.25%)))) -> 1093.5 | I140: =+((I$9*G$7+I$11+I$13+I$15+I$17)*(1+I$7)+2500)/($G$5*$H$5)*G140 -> 233.0685 | J140: =(J$9+J$7*G140)/($G$5*$H$5)*G140 -> 402.5312 | K140: =K$7*G140 -> 154.35 | L140: =+G140*L$7 -> 551.25 | M140: =+G140+H140+I140+J140*50%+K140+L140*30% -> 4052.5591 | N140: =+G140+H140+I140+J140*50%+K140+L140*70% -> 4273.0591 | O140: =+SUM(H140:L140)+G140 -> 4639.6997
A141: =+'Pricing Turkey'!A123 -> IT.88 | B141: =+'Pricing Turkey'!B123 -> PORTES PALIERE AUTOMATIQUE PEINTURE EPOXY *DEAS* 70/80 | C141: =+'Pricing Turkey'!C123 -> PORTE | D141: =+'Pricing Turkey'!D123 -> Pc | E141: =+'Pricing Turkey'!E123 -> 135 | F141: =+'Pricing Turkey'!F123 -> STEEL | G141: ='Pricing Turkey'!G123*G$7 -> 1813 | H141: =IF(F141="STEEL",MAX(G141,E141*13)*20.25%,IF(F141="GALVA",MAX(G141,E141*24)*20.25%,IF(F141="INOX",MAX(G141,E141*40)*20.25%,IF(F141="COPPER",MAX(G141,E141*60)*20.25%,G141*20.25%)))) -> 367.1325 | I141: =+((I$9*G$7+I$11+I$13+I$15+I$17)*(1+I$7)+2500)/($G$5*$H$5)*G141 -> 191.6341 | J141: =(J$9+J$7*G141)/($G$5*$H$5)*G141 -> 330.89903 | K141: =K$7*G141 -> 126.91 | L141: =+G141*L$7 -> 453.25 | M141: =+G141+H141+I141+J141*50%+K141+L141*30% -> 2800.1011 | N141: =+G141+H141+I141+J141*50%+K141+L141*70% -> 2981.4011 | O141: =+SUM(H141:L141)+G141 -> 3282.8256
A142: =+'Pricing Turkey'!A124 -> IT.89 | B142: =+'Pricing Turkey'!B124 -> PORTE PALIERE AUTOMATIQUE INOX FERMATOR 70 | C142: =+'Pricing Turkey'!C124 -> PORTE | D142: =+'Pricing Turkey'!D124 -> Pc | E142: =+'Pricing Turkey'!E124 -> 135 | F142: =+'Pricing Turkey'!F124 -> INOX | G142: ='Pricing Turkey'!G124*G$7 -> 3675 | H142: =IF(F142="STEEL",MAX(G142,E142*13)*20.25%,IF(F142="GALVA",MAX(G142,E142*24)*20.25%,IF(F142="INOX",MAX(G142,E142*40)*20.25%,IF(F142="COPPER",MAX(G142,E142*60)*20.25%,G142*20.25%)))) -> 1093.5 | I142: =+((I$9*G$7+I$11+I$13+I$15+I$17)*(1+I$7)+2500)/($G$5*$H$5)*G142 -> 388.4475 | J142: =(J$9+J$7*G142)/($G$5*$H$5)*G142 -> 671.42556 | K142: =K$7*G142 -> 257.25 | L142: =+G142*L$7 -> 918.75 | M142: =+G142+H142+I142+J142*50%+K142+L142*30% -> 6025.5353 | N142: =+G142+H142+I142+J142*50%+K142+L142*70% -> 6393.0353 | O142: =+SUM(H142:L142)+G142 -> 7004.3731
...

Sheet Pricing sheet clean
E1: Pricing | F1: Type | G1: Nombre de personne | H1: Nombre de niveau | I1: Moteur marque | J1: Porte marque | K1: Porte matériau | L1: Porte type | M1: Porte dimension | N1: Moteur capacité
B2: Items Pricing Order Lift Morocco | D2: Ascenseur complet | F2: GEARLESS | G2: 8 | H2: 5 | I2: AKİŞ | J2: ATERYA | K2: INOX | L2: AUTOMATIQUE | M2: 70 | N2: =+IF(G2<5,"MAX4",IF(G2<7,"MAX6",IF(G2<9,"MAX8","MAX10"))) -> MAX8 | P2: Version 11/12/2025
D3: Générer devis
D4: Générer facture
G5: Porte 70 prs inf 4 & 80 pour >= 5 prs | I5: Standard, Gaine > 130 x 130. >11 étages
A10: Ref | B10: Description | C10: Composante | D10: Unité | E10: Poids | F10: Prix à proposer ss stock (min) | G10: Prix à proposer (normal) | H10: Prix à proposer avec stock | I10: Quantité | S10: ARMOIRE | T10: MOTEUR | U10: PORTE | V10: OPÉRATEUR | W10: CABINE & ARCADE | X10: RAILS & ACCESSOIRES | Y10: CABLES & ACCESSOIRES | Z10: CABLES ELECTRIQUES & ACCESSOIRES | AA10: BOUTONS | AB10: GOSE | AC10: AUTRES
A11: =+'Pricing sheet'!A21 -> IT.1 | B11: =+'Pricing sheet'!B21 -> SET CABINE STANDARD INOX 1200/1100 + ARCADES & ACCESSOIRES GEARBOX | C11: =+'Pricing sheet'!C21 -> CABINE & ARCADE | D11: =+'Pricing sheet'!D21 -> SET | E11: =+'Pricing sheet'!E21 -> 650 | F11: =+'Pricing sheet'!M21 -> 25001.245 | G11: =+'Pricing sheet'!N21 -> 25736.245 | H11: =+'Pricing sheet'!O21 -> 28924.699 | S11: =IF($C11=S$10,IF(AND(ISNUMBER(SEARCH($F$2,$B11)),ISNUMBER(SEARCH($N$2,$B11)),ISNUMBER(SEARCH($N$2,$B11))),1,""),"") | T11: =IF($C11=T$10,IF(AND(ISNUMBER(SEARCH($F$2,$B11)),ISNUMBER(SEARCH($N$2,$B11)),ISNUMBER(SEARCH($I$2,$B11))),1,""),"") | U11: =IF($C11=U$10,IF(AND(ISNUMBER(SEARCH($M$2,$B11)),ISNUMBER(SEARCH($L$2,$B11)),ISNUMBER(SEARCH($J$2,$B11)),ISNUMBER(SEARCH($K$2,$B11))),$H$2,""),"") | V11: =IF($C11=V$10,IF(AND(ISNUMBER(SEARCH($M$2,$B11)),ISNUMBER(SEARCH($J$2,$B11))),1,""),"")
A12: =+'Pricing sheet'!A22 -> IT.1-1 | B12: =+'Pricing sheet'!B22 -> CABINE INOX 1000/900 STANDARD | C12: =+'Pricing sheet'!C22 -> CABINE & ARCADE | D12: =+'Pricing sheet'!D22 -> Pc | E12: =+'Pricing sheet'!E22 -> 350 | F12: =+'Pricing sheet'!M22 -> 15332.112 | G12: =+'Pricing sheet'!N22 -> 15797.612 | H12: =+'Pricing sheet'!O22 -> 17814.458 | S12: =IF($C12=S$10,IF(AND(ISNUMBER(SEARCH($F$2,$B12)),ISNUMBER(SEARCH($N$2,$B12)),ISNUMBER(SEARCH($N$2,$B12))),1,""),"") | T12: =IF($C12=T$10,IF(AND(ISNUMBER(SEARCH($F$2,$B12)),ISNUMBER(SEARCH($N$2,$B12)),ISNUMBER(SEARCH($I$2,$B12))),1,""),"") | U12: =IF($C12=U$10,IF(AND(ISNUMBER(SEARCH($M$2,$B12)),ISNUMBER(SEARCH($L$2,$B12)),ISNUMBER(SEARCH($J$2,$B12)),ISNUMBER(SEARCH($K$2,$B12))),$H$2,""),"") | V12: =IF($C12=V$10,IF(AND(ISNUMBER(SEARCH($M$2,$B12)),ISNUMBER(SEARCH($J$2,$B12))),1,""),"")
A13: =+'Pricing sheet'!A23 -> IT.1-2 | B13: =+'Pricing sheet'!B23 -> CABINE INOX 1000/900 PERSONALISÉE | C13: =+'Pricing sheet'!C23 -> CABINE & ARCADE | D13: =+'Pricing sheet'!D23 -> Pc | E13: =+'Pricing sheet'!E23 -> 350 | F13: =+'Pricing sheet'!M23 -> 18622.267 | G13: =+'Pricing sheet'!N23 -> 19210.267 | H13: =+'Pricing sheet'!O23 -> 21759.302 | S13: =IF($C13=S$10,IF(AND(ISNUMBER(SEARCH($F$2,$B13)),ISNUMBER(SEARCH($N$2,$B13)),ISNUMBER(SEARCH($N$2,$B13))),1,""),"") | T13: =IF($C13=T$10,IF(AND(ISNUMBER(SEARCH($F$2,$B13)),ISNUMBER(SEARCH($N$2,$B13)),ISNUMBER(SEARCH($I$2,$B13))),1,""),"") | U13: =IF($C13=U$10,IF(AND(ISNUMBER(SEARCH($M$2,$B13)),ISNUMBER(SEARCH($L$2,$B13)),ISNUMBER(SEARCH($J$2,$B13)),ISNUMBER(SEARCH($K$2,$B13))),$H$2,""),"") | V13: =IF($C13=V$10,IF(AND(ISNUMBER(SEARCH($M$2,$B13)),ISNUMBER(SEARCH($J$2,$B13))),1,""),"")
A14: =+'Pricing sheet'!A24 -> IT.1-3 | B14: =+'Pricing sheet'!B24 -> CABINE INOX 1100/1000 STANDARD | C14: =+'Pricing sheet'!C24 -> CABINE & ARCADE | D14: =+'Pricing sheet'!D24 -> Pc | E14: =+'Pricing sheet'!E24 -> 350 | F14: =+'Pricing sheet'!M24 -> 16253.295 | G14: =+'Pricing sheet'!N24 -> 16753.095 | H14: =+'Pricing sheet'!O24 -> 18918.893 | S14: =IF($C14=S$10,IF(AND(ISNUMBER(SEARCH($F$2,$B14)),ISNUMBER(SEARCH($N$2,$B14)),ISNUMBER(SEARCH($N$2,$B14))),1,""),"") | T14: =IF($C14=T$10,IF(AND(ISNUMBER(SEARCH($F$2,$B14)),ISNUMBER(SEARCH($N$2,$B14)),ISNUMBER(SEARCH($I$2,$B14))),1,""),"") | U14: =IF($C14=U$10,IF(AND(ISNUMBER(SEARCH($M$2,$B14)),ISNUMBER(SEARCH($L$2,$B14)),ISNUMBER(SEARCH($J$2,$B14)),ISNUMBER(SEARCH($K$2,$B14))),$H$2,""),"") | V14: =IF($C14=V$10,IF(AND(ISNUMBER(SEARCH($M$2,$B14)),ISNUMBER(SEARCH($J$2,$B14))),1,""),"")
A15: =+'Pricing sheet'!A25 -> IT.1-4 | B15: =+'Pricing sheet'!B25 -> CABINE INOX 1100/1000 PERSONALISÉE | C15: =+'Pricing sheet'!C25 -> CABINE & ARCADE | D15: =+'Pricing sheet'!D25 -> Pc | E15: =+'Pricing sheet'!E25 -> 350 | F15: =+'Pricing sheet'!M25 -> 20201.754 | G15: =+'Pricing sheet'!N25 -> 20848.554 | H15: =+'Pricing sheet'!O25 -> 23653.253 | S15: =IF($C15=S$10,IF(AND(ISNUMBER(SEARCH($F$2,$B15)),ISNUMBER(SEARCH($N$2,$B15)),ISNUMBER(SEARCH($N$2,$B15))),1,""),"") | T15: =IF($C15=T$10,IF(AND(ISNUMBER(SEARCH($F$2,$B15)),ISNUMBER(SEARCH($N$2,$B15)),ISNUMBER(SEARCH($I$2,$B15))),1,""),"") | U15: =IF($C15=U$10,IF(AND(ISNUMBER(SEARCH($M$2,$B15)),ISNUMBER(SEARCH($L$2,$B15)),ISNUMBER(SEARCH($J$2,$B15)),ISNUMBER(SEARCH($K$2,$B15))),$H$2,""),"") | V15: =IF($C15=V$10,IF(AND(ISNUMBER(SEARCH($M$2,$B15)),ISNUMBER(SEARCH($J$2,$B15))),1,""),"")
A16: =+'Pricing sheet'!A26 -> IT.1-5 | B16: =+'Pricing sheet'!B26 -> CABINE INOX 1200/1100 STANDARD | C16: =+'Pricing sheet'!C26 -> CABINE & ARCADE | D16: =+'Pricing sheet'!D26 -> Pc | E16: =+'Pricing sheet'!E26 -> 350 | F16: =+'Pricing sheet'!M26 -> 17174.525 | G16: =+'Pricing sheet'!N26 -> 17708.625 | H16: =+'Pricing sheet'!O26 -> 20023.423 | S16: =IF($C16=S$10,IF(AND(ISNUMBER(SEARCH($F$2,$B16)),ISNUMBER(SEARCH($N$2,$B16)),ISNUMBER(SEARCH($N$2,$B16))),1,""),"") | T16: =IF($C16=T$10,IF(AND(ISNUMBER(SEARCH($F$2,$B16)),ISNUMBER(SEARCH($N$2,$B16)),ISNUMBER(SEARCH($I$2,$B16))),1,""),"") | U16: =IF($C16=U$10,IF(AND(ISNUMBER(SEARCH($M$2,$B16)),ISNUMBER(SEARCH($L$2,$B16)),ISNUMBER(SEARCH($J$2,$B16)),ISNUMBER(SEARCH($K$2,$B16))),$H$2,""),"") | V16: =IF($C16=V$10,IF(AND(ISNUMBER(SEARCH($M$2,$B16)),ISNUMBER(SEARCH($J$2,$B16))),1,""),"")
A17: =+'Pricing sheet'!A27 -> IT.1-6 | B17: =+'Pricing sheet'!B27 -> CABINE INOX 1200/1100 PERSONALISÉE | C17: =+'Pricing sheet'!C27 -> CABINE & ARCADE | D17: =+'Pricing sheet'!D27 -> Pc | E17: =+'Pricing sheet'!E27 -> 350 | F17: =+'Pricing sheet'!M27 -> 21123.186 | G17: =+'Pricing sheet'!N27 -> 21804.286 | H17: =+'Pricing sheet'!O27 -> 24758.186 | S17: =IF($C17=S$10,IF(AND(ISNUMBER(SEARCH($F$2,$B17)),ISNUMBER(SEARCH($N$2,$B17)),ISNUMBER(SEARCH($N$2,$B17))),1,""),"") | T17: =IF($C17=T$10,IF(AND(ISNUMBER(SEARCH($F$2,$B17)),ISNUMBER(SEARCH($N$2,$B17)),ISNUMBER(SEARCH($I$2,$B17))),1,""),"") | U17: =IF($C17=U$10,IF(AND(ISNUMBER(SEARCH($M$2,$B17)),ISNUMBER(SEARCH($L$2,$B17)),ISNUMBER(SEARCH($J$2,$B17)),ISNUMBER(SEARCH($K$2,$B17))),$H$2,""),"") | V17: =IF($C17=V$10,IF(AND(ISNUMBER(SEARCH($M$2,$B17)),ISNUMBER(SEARCH($J$2,$B17))),1,""),"")
A18: =+'Pricing sheet'!A28 -> IT.1-13 | B18: =+'Pricing sheet'!B28 -> CABINE INOX 1400/1300 STANDARD | C18: =+'Pricing sheet'!C28 -> CABINE & ARCADE | D18: =+'Pricing sheet'!D28 -> SET | E18: =+'Pricing sheet'!E28 -> 350 | F18: =+'Pricing sheet'!M28 -> 20289.246 | G18: =+'Pricing sheet'!N28 -> 20945.846 | H18: =+'Pricing sheet'!O28 -> 23793.169 | S18: =IF($C18=S$10,IF(AND(ISNUMBER(SEARCH($F$2,$B18)),ISNUMBER(SEARCH($N$2,$B18)),ISNUMBER(SEARCH($N$2,$B18))),1,""),"") | T18: =IF($C18=T$10,IF(AND(ISNUMBER(SEARCH($F$2,$B18)),ISNUMBER(SEARCH($N$2,$B18)),ISNUMBER(SEARCH($I$2,$B18))),1,""),"") | U18: =IF($C18=U$10,IF(AND(ISNUMBER(SEARCH($M$2,$B18)),ISNUMBER(SEARCH($L$2,$B18)),ISNUMBER(SEARCH($J$2,$B18)),ISNUMBER(SEARCH($K$2,$B18))),$H$2,""),"") | V18: =IF($C18=V$10,IF(AND(ISNUMBER(SEARCH($M$2,$B18)),ISNUMBER(SEARCH($J$2,$B18))),1,""),"")
A19: =+'Pricing sheet'!A29 -> IT.1-14 | B19: =+'Pricing sheet'!B29 -> CABINE INOX 1400/1300 PERSONALISÉE | C19: =+'Pricing sheet'!C29 -> CABINE & ARCADE | D19: =+'Pricing sheet'!D29 -> SET | E19: =+'Pricing sheet'!E29 -> 350 | F19: =+'Pricing sheet'!M29 -> 26349.079 | G19: =+'Pricing sheet'!N29 -> 27201.679 | H19: =+'Pricing sheet'!O29 -> 30902.291 | S19: =IF($C19=S$10,IF(AND(ISNUMBER(SEARCH($F$2,$B19)),ISNUMBER(SEARCH($N$2,$B19)),ISNUMBER(SEARCH($N$2,$B19))),1,""),"") | T19: =IF($C19=T$10,IF(AND(ISNUMBER(SEARCH($F$2,$B19)),ISNUMBER(SEARCH($N$2,$B19)),ISNUMBER(SEARCH($I$2,$B19))),1,""),"") | U19: =IF($C19=U$10,IF(AND(ISNUMBER(SEARCH($M$2,$B19)),ISNUMBER(SEARCH($L$2,$B19)),ISNUMBER(SEARCH($J$2,$B19)),ISNUMBER(SEARCH($K$2,$B19))),$H$2,""),"") | V19: =IF($C19=V$10,IF(AND(ISNUMBER(SEARCH($M$2,$B19)),ISNUMBER(SEARCH($J$2,$B19))),1,""),"")
A20: =+'Pricing sheet'!A30 -> IT.1-17 | B20: =+'Pricing sheet'!B30 -> CABINE 1000/900 PANORAMIQUE | C20: =+'Pricing sheet'!C30 -> CABINE & ARCADE | D20: =+'Pricing sheet'!D30 -> Pc | E20: =+'Pricing sheet'!E30 -> 350 | F20: =+'Pricing sheet'!M30 -> 24227.962 | G20: =+'Pricing sheet'!N30 -> 25011.962 | H20: =+'Pricing sheet'!O30 -> 28413.749 | S20: =IF($C20=S$10,IF(AND(ISNUMBER(SEARCH($F$2,$B20)),ISNUMBER(SEARCH($N$2,$B20)),ISNUMBER(SEARCH($N$2,$B20))),1,""),"") | T20: =IF($C20=T$10,IF(AND(ISNUMBER(SEARCH($F$2,$B20)),ISNUMBER(SEARCH($N$2,$B20)),ISNUMBER(SEARCH($I$2,$B20))),1,""),"") | U20: =IF($C20=U$10,IF(AND(ISNUMBER(SEARCH($M$2,$B20)),ISNUMBER(SEARCH($L$2,$B20)),ISNUMBER(SEARCH($J$2,$B20)),ISNUMBER(SEARCH($K$2,$B20))),$H$2,""),"") | V20: =IF($C20=V$10,IF(AND(ISNUMBER(SEARCH($M$2,$B20)),ISNUMBER(SEARCH($J$2,$B20))),1,""),"")
A21: =+'Pricing sheet'!A31 -> IT.1-18 | B21: =+'Pricing sheet'!B31 -> CABINE 1100/1000 PANORAMIQUE | C21: =+'Pricing sheet'!C31 -> CABINE & ARCADE | D21: =+'Pricing sheet'!D31 -> Pc | E21: =+'Pricing sheet'!E31 -> 350 | F21: =+'Pricing sheet'!M31 -> 25743.026 | G21: =+'Pricing sheet'!N31 -> 26576.026 | H21: =+'Pricing sheet'!O31 -> 30191.241 | S21: =IF($C21=S$10,IF(AND(ISNUMBER(SEARCH($F$2,$B21)),ISNUMBER(SEARCH($N$2,$B21)),ISNUMBER(SEARCH($N$2,$B21))),1,""),"") | T21: =IF($C21=T$10,IF(AND(ISNUMBER(SEARCH($F$2,$B21)),ISNUMBER(SEARCH($N$2,$B21)),ISNUMBER(SEARCH($I$2,$B21))),1,""),"") | U21: =IF($C21=U$10,IF(AND(ISNUMBER(SEARCH($M$2,$B21)),ISNUMBER(SEARCH($L$2,$B21)),ISNUMBER(SEARCH($J$2,$B21)),ISNUMBER(SEARCH($K$2,$B21))),$H$2,""),"") | V21: =IF($C21=V$10,IF(AND(ISNUMBER(SEARCH($M$2,$B21)),ISNUMBER(SEARCH($J$2,$B21))),1,""),"")
A22: =+'Pricing sheet'!A32 -> IT.1-19 | B22: =+'Pricing sheet'!B32 -> CABINE 1200/1100 PANORAMIQUE | C22: =+'Pricing sheet'!C32 -> CABINE & ARCADE | D22: =+'Pricing sheet'!D32 -> Pc | E22: =+'Pricing sheet'!E32 -> 350 | F22: =+'Pricing sheet'!M32 -> 28015.803 | G22: =+'Pricing sheet'!N32 -> 28922.303 | H22: =+'Pricing sheet'!O32 -> 32857.839 | S22: =IF($C22=S$10,IF(AND(ISNUMBER(SEARCH($F$2,$B22)),ISNUMBER(SEARCH($N$2,$B22)),ISNUMBER(SEARCH($N$2,$B22))),1,""),"") | T22: =IF($C22=T$10,IF(AND(ISNUMBER(SEARCH($F$2,$B22)),ISNUMBER(SEARCH($N$2,$B22)),ISNUMBER(SEARCH($I$2,$B22))),1,""),"") | U22: =IF($C22=U$10,IF(AND(ISNUMBER(SEARCH($M$2,$B22)),ISNUMBER(SEARCH($L$2,$B22)),ISNUMBER(SEARCH($J$2,$B22)),ISNUMBER(SEARCH($K$2,$B22))),$H$2,""),"") | V22: =IF($C22=V$10,IF(AND(ISNUMBER(SEARCH($M$2,$B22)),ISNUMBER(SEARCH($J$2,$B22))),1,""),"")
A23: =+'Pricing sheet'!A33 -> IT.1-20 | B23: =+'Pricing sheet'!B33 -> CABINE INOX 1300/1200 STANDARD | C23: =+'Pricing sheet'!C33 -> CABINE & ARCADE | D23: =+'Pricing sheet'!D33 -> Pc | E23: =+'Pricing sheet'!E33 -> 350 | F23: =+'Pricing sheet'!M33 -> 18095.802 | G23: =+'Pricing sheet'!N33 -> 18664.202 | H23: =+'Pricing sheet'!O33 -> 21128.046 | S23: =IF($C23=S$10,IF(AND(ISNUMBER(SEARCH($F$2,$B23)),ISNUMBER(SEARCH($N$2,$B23)),ISNUMBER(SEARCH($N$2,$B23))),1,""),"") | T23: =IF($C23=T$10,IF(AND(ISNUMBER(SEARCH($F$2,$B23)),ISNUMBER(SEARCH($N$2,$B23)),ISNUMBER(SEARCH($I$2,$B23))),1,""),"") | U23: =IF($C23=U$10,IF(AND(ISNUMBER(SEARCH($M$2,$B23)),ISNUMBER(SEARCH($L$2,$B23)),ISNUMBER(SEARCH($J$2,$B23)),ISNUMBER(SEARCH($K$2,$B23))),$H$2,""),"") | V23: =IF($C23=V$10,IF(AND(ISNUMBER(SEARCH($M$2,$B23)),ISNUMBER(SEARCH($J$2,$B23))),1,""),"")
A24: =+'Pricing sheet'!A34 -> IT.1-21 | B24: =+'Pricing sheet'!B34 -> CABINE INOX 1300/1200 PERSONALISÉE | C24: =+'Pricing sheet'!C34 -> CABINE & ARCADE | D24: =+'Pricing sheet'!D34 -> Pc | E24: =+'Pricing sheet'!E34 -> 350 | F24: =+'Pricing sheet'!M34 -> 22107.034 | G24: =+'Pricing sheet'!N34 -> 22822.434 | H24: =+'Pricing sheet'!O34 -> 25925.583 | I24: =IF(SUM(S24:AC24)<>0,SUM(S24:AC24),"") | S24: =IF($C24=S$10,IF(AND(ISNUMBER(SEARCH($F$2,$B24)),ISNUMBER(SEARCH($N$2,$B24)),ISNUMBER(SEARCH($N$2,$B24))),1,""),"") | T24: =IF($C24=T$10,IF(AND(ISNUMBER(SEARCH($F$2,$B24)),ISNUMBER(SEARCH($N$2,$B24)),ISNUMBER(SEARCH($I$2,$B24))),1,""),"") | U24: =IF($C24=U$10,IF(AND(ISNUMBER(SEARCH($M$2,$B24)),ISNUMBER(SEARCH($L$2,$B24)),ISNUMBER(SEARCH($J$2,$B24)),ISNUMBER(SEARCH($K$2,$B24))),$H$2,""),"") | V24: =IF($C24=V$10,IF(AND(ISNUMBER(SEARCH($M$2,$B24)),ISNUMBER(SEARCH($J$2,$B24))),1,""),"")
A25: =+'Pricing sheet'!A35 -> IT.1-22 | B25: =+'Pricing sheet'!B35 -> CABINE 1300/1200 PANORAMIQUE | C25: =+'Pricing sheet'!C35 -> CABINE & ARCADE | D25: =+'Pricing sheet'!D35 -> Pc | E25: =+'Pricing sheet'!E35 -> 350 | F25: =+'Pricing sheet'!M35 -> 31046.507 | G25: =+'Pricing sheet'!N35 -> 32051.007 | H25: =+'Pricing sheet'!O35 -> 36413.975 | I25: =IF(SUM(S25:AC25)<>0,SUM(S25:AC25),"") | S25: =IF($C25=S$10,IF(AND(ISNUMBER(SEARCH($F$2,$B25)),ISNUMBER(SEARCH($N$2,$B25)),ISNUMBER(SEARCH($N$2,$B25))),1,""),"") | T25: =IF($C25=T$10,IF(AND(ISNUMBER(SEARCH($F$2,$B25)),ISNUMBER(SEARCH($N$2,$B25)),ISNUMBER(SEARCH($I$2,$B25))),1,""),"") | U25: =IF($C25=U$10,IF(AND(ISNUMBER(SEARCH($M$2,$B25)),ISNUMBER(SEARCH($L$2,$B25)),ISNUMBER(SEARCH($J$2,$B25)),ISNUMBER(SEARCH($K$2,$B25))),$H$2,""),"") | V25: =IF($C25=V$10,IF(AND(ISNUMBER(SEARCH($M$2,$B25)),ISNUMBER(SEARCH($J$2,$B25))),1,""),"")
A26: =+'Pricing sheet'!A36 -> IT.1-23 | B26: =+'Pricing sheet'!B36 -> CABINE 1400/1300 PANORAMIQUE | C26: =+'Pricing sheet'!C36 -> CABINE & ARCADE | D26: =+'Pricing sheet'!D36 -> Pc | E26: =+'Pricing sheet'!E36 -> 350 | F26: =+'Pricing sheet'!M36 -> 34835.427 | G26: =+'Pricing sheet'!N36 -> 35962.427 | H26: =+'Pricing sheet'!O36 -> 40860.226 | I26: =IF(SUM(S26:AC26)<>0,SUM(S26:AC26),"") | S26: =IF($C26=S$10,IF(AND(ISNUMBER(SEARCH($F$2,$B26)),ISNUMBER(SEARCH($N$2,$B26)),ISNUMBER(SEARCH($N$2,$B26))),1,""),"") | T26: =IF($C26=T$10,IF(AND(ISNUMBER(SEARCH($F$2,$B26)),ISNUMBER(SEARCH($N$2,$B26)),ISNUMBER(SEARCH($I$2,$B26))),1,""),"") | U26: =IF($C26=U$10,IF(AND(ISNUMBER(SEARCH($M$2,$B26)),ISNUMBER(SEARCH($L$2,$B26)),ISNUMBER(SEARCH($J$2,$B26)),ISNUMBER(SEARCH($K$2,$B26))),$H$2,""),"") | V26: =IF($C26=V$10,IF(AND(ISNUMBER(SEARCH($M$2,$B26)),ISNUMBER(SEARCH($J$2,$B26))),1,""),"")
A27: =+'Pricing sheet'!A37 -> IT.1-7 | B27: =+'Pricing sheet'!B37 -> ARCADE CABINE 1000/900 + ARCADE CONTRE-POIDS + TIRANDS + COULISSEAUX GEARBOX | C27: =+'Pricing sheet'!C37 -> CABINE & ARCADE | D27: =+'Pricing sheet'!D37 -> SET | E27: =+'Pricing sheet'!E37 -> 200 | F27: =+'Pricing sheet'!M37 -> 6811.6294 | G27: =+'Pricing sheet'!N37 -> 7252.6294 | H27: =+'Pricing sheet'!O37 -> 7986.3968 | I27: =IF(SUM(S27:AC27)<>0,SUM(S27:AC27),"") | S27: =IF($C27=S$10,IF(AND(ISNUMBER(SEARCH($F$2,$B27)),ISNUMBER(SEARCH($N$2,$B27)),ISNUMBER(SEARCH($N$2,$B27))),1,""),"") | T27: =IF($C27=T$10,IF(AND(ISNUMBER(SEARCH($F$2,$B27)),ISNUMBER(SEARCH($N$2,$B27)),ISNUMBER(SEARCH($I$2,$B27))),1,""),"") | U27: =IF($C27=U$10,IF(AND(ISNUMBER(SEARCH($M$2,$B27)),ISNUMBER(SEARCH($L$2,$B27)),ISNUMBER(SEARCH($J$2,$B27)),ISNUMBER(SEARCH($K$2,$B27))),$H$2,""),"") | V27: =IF($C27=V$10,IF(AND(ISNUMBER(SEARCH($M$2,$B27)),ISNUMBER(SEARCH($J$2,$B27))),1,""),"")
A28: =+'Pricing sheet'!A38 -> IT.1-8 | B28: =+'Pricing sheet'!B38 -> ARCADE CABINE 1000/900 + ARCADE CONTRE-POIDS + TIRANDS + COULISSEAUX GEARLESS | C28: =+'Pricing sheet'!C38 -> CABINE & ARCADE | D28: =+'Pricing sheet'!D38 -> SET | E28: =+'Pricing sheet'!E38 -> 200 | F28: =+'Pricing sheet'!M38 -> 10596.708 | G28: =+'Pricing sheet'!N38 -> 11282.708 | H28: =+'Pricing sheet'!O38 -> 12424.965 | I28: =IF(SUM(S28:AC28)<>0,SUM(S28:AC28),"") | S28: =IF($C28=S$10,IF(AND(ISNUMBER(SEARCH($F$2,$B28)),ISNUMBER(SEARCH($N$2,$B28)),ISNUMBER(SEARCH($N$2,$B28))),1,""),"") | T28: =IF($C28=T$10,IF(AND(ISNUMBER(SEARCH($F$2,$B28)),ISNUMBER(SEARCH($N$2,$B28)),ISNUMBER(SEARCH($I$2,$B28))),1,""),"") | U28: =IF($C28=U$10,IF(AND(ISNUMBER(SEARCH($M$2,$B28)),ISNUMBER(SEARCH($L$2,$B28)),ISNUMBER(SEARCH($J$2,$B28)),ISNUMBER(SEARCH($K$2,$B28))),$H$2,""),"") | V28: =IF($C28=V$10,IF(AND(ISNUMBER(SEARCH($M$2,$B28)),ISNUMBER(SEARCH($J$2,$B28))),1,""),"")
A29: =+'Pricing sheet'!A39 -> IT.1-9 | B29: =+'Pricing sheet'!B39 -> ARCADE CABINE 1100/1000 + ARCADE CONTRE-POIDS + TIRANDS + COULISSEAUX GEARBOX | C29: =+'Pricing sheet'!C39 -> CABINE & ARCADE | D29: =+'Pricing sheet'!D39 -> SET | E29: =+'Pricing sheet'!E39 -> 200 | F29: =+'Pricing sheet'!M39 -> 7114.4136 | G29: =+'Pricing sheet'!N39 -> 7575.0136 | H29: =+'Pricing sheet'!O39 -> 8341.4381 | I29: =IF(SUM(S29:AC29)<>0,SUM(S29:AC29),"") | S29: =IF($C29=S$10,IF(AND(ISNUMBER(SEARCH($F$2,$B29)),ISNUMBER(SEARCH($N$2,$B29)),ISNUMBER(SEARCH($N$2,$B29))),1,""),"") | T29: =IF($C29=T$10,IF(AND(ISNUMBER(SEARCH($F$2,$B29)),ISNUMBER(SEARCH($N$2,$B29)),ISNUMBER(SEARCH($I$2,$B29))),1,""),"") | U29: =IF($C29=U$10,IF(AND(ISNUMBER(SEARCH($M$2,$B29)),ISNUMBER(SEARCH($L$2,$B29)),ISNUMBER(SEARCH($J$2,$B29)),ISNUMBER(SEARCH($K$2,$B29))),$H$2,""),"") | V29: =IF($C29=V$10,IF(AND(ISNUMBER(SEARCH($M$2,$B29)),ISNUMBER(SEARCH($J$2,$B29))),1,""),"") | AC29: =IF(L2="SEMI",1,"")
A30: =+'Pricing sheet'!A40 -> IT.1-10 | B30: =+'Pricing sheet'!B40 -> ARCADE CABINE 1100/1000 + ARCADE CONTRE-POIDS + TIRANDS + COULISSEAUX GEARLESS | C30: =+'Pricing sheet'!C40 -> CABINE & ARCADE | D30: =+'Pricing sheet'!D40 -> SET | E30: =+'Pricing sheet'!E40 -> 200 | F30: =+'Pricing sheet'!M40 -> 10899.541 | G30: =+'Pricing sheet'!N40 -> 11605.141 | H30: =+'Pricing sheet'!O40 -> 12780.102 | I30: =IF(SUM(S30:AC30)<>0,SUM(S30:AC30),"") | S30: =IF($C30=S$10,IF(AND(ISNUMBER(SEARCH($F$2,$B30)),ISNUMBER(SEARCH($N$2,$B30)),ISNUMBER(SEARCH($N$2,$B30))),1,""),"") | T30: =IF($C30=T$10,IF(AND(ISNUMBER(SEARCH($F$2,$B30)),ISNUMBER(SEARCH($N$2,$B30)),ISNUMBER(SEARCH($I$2,$B30))),1,""),"") | U30: =IF($C30=U$10,IF(AND(ISNUMBER(SEARCH($M$2,$B30)),ISNUMBER(SEARCH($L$2,$B30)),ISNUMBER(SEARCH($J$2,$B30)),ISNUMBER(SEARCH($K$2,$B30))),$H$2,""),"") | V30: =IF($C30=V$10,IF(AND(ISNUMBER(SEARCH($M$2,$B30)),ISNUMBER(SEARCH($J$2,$B30))),1,""),"") | AC30: =IF(L3="SEMI",1,"")
A31: =+'Pricing sheet'!A41 -> IT.1-11 | B31: =+'Pricing sheet'!B41 -> ARCADE CABINE 1200/1100 + ARCADE CONTRE-POIDS + TIRANDS + COULISSEAUX GEARBOX | C31: =+'Pricing sheet'!C41 -> CABINE & ARCADE | D31: =+'Pricing sheet'!D41 -> SET | E31: =+'Pricing sheet'!E41 -> 200 | F31: =+'Pricing sheet'!M41 -> 7417.2017 | G31: =+'Pricing sheet'!N41 -> 7897.4017 | H31: =+'Pricing sheet'!O41 -> 8696.487 | I31: =IF(SUM(S31:AC31)<>0,SUM(S31:AC31),"") | S31: =IF($C31=S$10,IF(AND(ISNUMBER(SEARCH($F$2,$B31)),ISNUMBER(SEARCH($N$2,$B31)),ISNUMBER(SEARCH($N$2,$B31))),1,""),"") | T31: =IF($C31=T$10,IF(AND(ISNUMBER(SEARCH($F$2,$B31)),ISNUMBER(SEARCH($N$2,$B31)),ISNUMBER(SEARCH($I$2,$B31))),1,""),"") | U31: =IF($C31=U$10,IF(AND(ISNUMBER(SEARCH($M$2,$B31)),ISNUMBER(SEARCH($L$2,$B31)),ISNUMBER(SEARCH($J$2,$B31)),ISNUMBER(SEARCH($K$2,$B31))),$H$2,""),"") | V31: =IF($C31=V$10,IF(AND(ISNUMBER(SEARCH($M$2,$B31)),ISNUMBER(SEARCH($J$2,$B31))),1,""),"") | AC31: =IF(L4="SEMI",1,"")
A32: =+'Pricing sheet'!A42 -> IT.1-12 | B32: =+'Pricing sheet'!B42 -> ARCADE CABINE 1200/1100 + ARCADE CONTRE-POIDS + TIRANDS + COULISSEAUX GEARLESS | C32: =+'Pricing sheet'!C42 -> CABINE & ARCADE | D32: =+'Pricing sheet'!D42 -> SET | E32: =+'Pricing sheet'!E42 -> 200 | F32: =+'Pricing sheet'!M42 -> 11202.377 | G32: =+'Pricing sheet'!N42 -> 11927.577 | H32: =+'Pricing sheet'!O42 -> 13135.247 | I32: =IF(SUM(S32:AC32)<>0,SUM(S32:AC32),"") | S32: =IF($C32=S$10,IF(AND(ISNUMBER(SEARCH($F$2,$B32)),ISNUMBER(SEARCH($N$2,$B32)),ISNUMBER(SEARCH($N$2,$B32))),1,""),"") | T32: =IF($C32=T$10,IF(AND(ISNUMBER(SEARCH($F$2,$B32)),ISNUMBER(SEARCH($N$2,$B32)),ISNUMBER(SEARCH($I$2,$B32))),1,""),"") | U32: =IF($C32=U$10,IF(AND(ISNUMBER(SEARCH($M$2,$B32)),ISNUMBER(SEARCH($L$2,$B32)),ISNUMBER(SEARCH($J$2,$B32)),ISNUMBER(SEARCH($K$2,$B32))),$H$2,""),"") | V32: =IF($C32=V$10,IF(AND(ISNUMBER(SEARCH($M$2,$B32)),ISNUMBER(SEARCH($J$2,$B32))),1,""),"")
A33: =+'Pricing sheet'!A43 -> IT.1-15 | B33: =+'Pricing sheet'!B43 -> ARCADE CABINE 1400/1300 + ARCADE CONTRE-POIDS + TIRANDS + COULISSEAUX GEARBOX | C33: =+'Pricing sheet'!C43 -> CABINE & ARCADE | D33: =+'Pricing sheet'!D43 -> SET | E33: =+'Pricing sheet'!E43 -> 201 | F33: =+'Pricing sheet'!M43 -> 8931.1996 | G33: =+'Pricing sheet'!N43 -> 9509.3996 | H33: =+'Pricing sheet'!O43 -> 10471.847 | I33: =IF(SUM(S33:AC33)<>0,SUM(S33:AC33),"") | S33: =IF($C33=S$10,IF(AND(ISNUMBER(SEARCH($F$2,$B33)),ISNUMBER(SEARCH($N$2,$B33)),ISNUMBER(SEARCH($N$2,$B33))),1,""),"") | T33: =IF($C33=T$10,IF(AND(ISNUMBER(SEARCH($F$2,$B33)),ISNUMBER(SEARCH($N$2,$B33)),ISNUMBER(SEARCH($I$2,$B33))),1,""),"") | U33: =IF($C33=U$10,IF(AND(ISNUMBER(SEARCH($M$2,$B33)),ISNUMBER(SEARCH($L$2,$B33)),ISNUMBER(SEARCH($J$2,$B33)),ISNUMBER(SEARCH($K$2,$B33))),$H$2,""),"") | V33: =IF($C33=V$10,IF(AND(ISNUMBER(SEARCH($M$2,$B33)),ISNUMBER(SEARCH($J$2,$B33))),1,""),"")
A34: =+'Pricing sheet'!A44 -> IT.1-16 | B34: =+'Pricing sheet'!B44 -> ARCADE CABINE 1400/1300 + ARCADE CONTRE-POIDS + TIRANDS + COULISSEAUX GEARLESS | C34: =+'Pricing sheet'!C44 -> CABINE & ARCADE | D34: =+'Pricing sheet'!D44 -> SET | E34: =+'Pricing sheet'!E44 -> 202 | F34: =+'Pricing sheet'!M44 -> 14230.949 | G34: =+'Pricing sheet'!N44 -> 15152.149 | H34: =+'Pricing sheet'!O44 -> 16687.119 | I34: =IF(SUM(S34:AC34)<>0,SUM(S34:AC34),"") | S34: =IF($C34=S$10,IF(AND(ISNUMBER(SEARCH($F$2,$B34)),ISNUMBER(SEARCH($N$2,$B34)),ISNUMBER(SEARCH($N$2,$B34))),1,""),"") | T34: =IF($C34=T$10,IF(AND(ISNUMBER(SEARCH($F$2,$B34)),ISNUMBER(SEARCH($N$2,$B34)),ISNUMBER(SEARCH($I$2,$B34))),1,""),"") | U34: =IF($C34=U$10,IF(AND(ISNUMBER(SEARCH($M$2,$B34)),ISNUMBER(SEARCH($L$2,$B34)),ISNUMBER(SEARCH($J$2,$B34)),ISNUMBER(SEARCH($K$2,$B34))),$H$2,""),"") | V34: =IF($C34=V$10,IF(AND(ISNUMBER(SEARCH($M$2,$B34)),ISNUMBER(SEARCH($J$2,$B34))),1,""),"")
A35: =+'Pricing sheet'!A45 -> IT.1-17 | B35: =+'Pricing sheet'!B45 -> SET ARCADE TYPE L VVVF 2V | C35: =+'Pricing sheet'!C45 -> CABINE & ARCADE | D35: =+'Pricing sheet'!D45 -> SET | E35: =+'Pricing sheet'!E45 -> 203 | F35: =+'Pricing sheet'!M45 -> 15139.595 | G35: =+'Pricing sheet'!N45 -> 16119.595 | H35: =+'Pricing sheet'!O45 -> 17752.831 | I35: =IF(SUM(S35:AC35)<>0,SUM(S35:AC35),"") | S35: =IF($C35=S$10,IF(AND(ISNUMBER(SEARCH($F$2,$B35)),ISNUMBER(SEARCH($N$2,$B35)),ISNUMBER(SEARCH($N$2,$B35))),1,""),"") | T35: =IF($C35=T$10,IF(AND(ISNUMBER(SEARCH($F$2,$B35)),ISNUMBER(SEARCH($N$2,$B35)),ISNUMBER(SEARCH($I$2,$B35))),1,""),"") | U35: =IF($C35=U$10,IF(AND(ISNUMBER(SEARCH($M$2,$B35)),ISNUMBER(SEARCH($L$2,$B35)),ISNUMBER(SEARCH($J$2,$B35)),ISNUMBER(SEARCH($K$2,$B35))),$H$2,""),"") | V35: =IF($C35=V$10,IF(AND(ISNUMBER(SEARCH($M$2,$B35)),ISNUMBER(SEARCH($J$2,$B35))),1,""),"")
A36: =+'Pricing sheet'!A46 -> IT.1-18 | B36: =+'Pricing sheet'!B46 -> SET ARCADE TYPE L GEARLESS | C36: =+'Pricing sheet'!C46 -> CABINE & ARCADE | D36: =+'Pricing sheet'!D46 -> SET | E36: =+'Pricing sheet'!E46 -> 204 | F36: =+'Pricing sheet'!M46 -> 18168.667 | G36: =+'Pricing sheet'!N46 -> 19344.667 | H36: =+'Pricing sheet'!O46 -> 21305.702 | I36: =IF(SUM(S36:AC36)<>0,SUM(S36:AC36),"") -> 36 | S36: =IF($C36=S$10,IF(AND(ISNUMBER(SEARCH($F$2,$B36)),ISNUMBER(SEARCH($N$2,$B36)),ISNUMBER(SEARCH($N$2,$B36))),1,""),"") | T36: =IF($C36=T$10,IF(AND(ISNUMBER(SEARCH($F$2,$B36)),ISNUMBER(SEARCH($N$2,$B36)),ISNUMBER(SEARCH($I$2,$B36))),1,""),"") | U36: =IF($C36=U$10,IF(AND(ISNUMBER(SEARCH($M$2,$B36)),ISNUMBER(SEARCH($L$2,$B36)),ISNUMBER(SEARCH($J$2,$B36)),ISNUMBER(SEARCH($K$2,$B36))),$H$2,""),"") | V36: =IF($C36=V$10,IF(AND(ISNUMBER(SEARCH($M$2,$B36)),ISNUMBER(SEARCH($J$2,$B36))),1,""),"") | X36: =(INT((H2+1)*3/2))*4 -> 36
A37: =+'Pricing sheet'!A47 -> HYD1-1 | B37: =+'Pricing sheet'!B47 -> SET SYSTÈME HYDRAULIQUE MAX4 STANDARD 0,15M/S 10M COURSE (4 NIVEAUX) | C37: =+'Pricing sheet'!C47 -> HYDRAULIQUE | D37: =+'Pricing sheet'!D47 -> SET | E37: =+'Pricing sheet'!E47 -> 200 | F37: =+'Pricing sheet'!M47 -> 22712.995 | G37: =+'Pricing sheet'!N47 -> 24182.995 | H37: =+'Pricing sheet'!O47 -> 26636.449 | I37: =IF(SUM(S37:AC37)<>0,SUM(S37:AC37),"") -> 36 | S37: =IF($C37=S$10,IF(AND(ISNUMBER(SEARCH($F$2,$B37)),ISNUMBER(SEARCH($N$2,$B37)),ISNUMBER(SEARCH($N$2,$B37))),1,""),"") | T37: =IF($C37=T$10,IF(AND(ISNUMBER(SEARCH($F$2,$B37)),ISNUMBER(SEARCH($N$2,$B37)),ISNUMBER(SEARCH($I$2,$B37))),1,""),"") | U37: =IF($C37=U$10,IF(AND(ISNUMBER(SEARCH($M$2,$B37)),ISNUMBER(SEARCH($L$2,$B37)),ISNUMBER(SEARCH($J$2,$B37)),ISNUMBER(SEARCH($K$2,$B37))),$H$2,""),"") | V37: =IF($C37=V$10,IF(AND(ISNUMBER(SEARCH($M$2,$B37)),ISNUMBER(SEARCH($J$2,$B37))),1,""),"") | X37: =(INT((H2+1)*3/2))*4 -> 36
A38: =+'Pricing sheet'!A48 -> HYD1-2 | B38: =+'Pricing sheet'!B48 -> SET SYSTÈME HYDRAULIQUE MAX4 STANDARD 0,15M/S 7M COURSE (3 NIVEAUX) | C38: =+'Pricing sheet'!C48 -> HYDRAULIQUE | D38: =+'Pricing sheet'!D48 -> SET | E38: =+'Pricing sheet'!E48 -> 198 | F38: =+'Pricing sheet'!M48 -> 521.235 | G38: =+'Pricing sheet'!N48 -> 521.235 | H38: =+'Pricing sheet'!O48 -> 521.235 | I38: =IF(SUM(S38:AC38)<>0,SUM(S38:AC38),"") -> 36 | S38: =IF($C38=S$10,IF(AND(ISNUMBER(SEARCH($F$2,$B38)),ISNUMBER(SEARCH($N$2,$B38)),ISNUMBER(SEARCH($N$2,$B38))),1,""),"") | T38: =IF($C38=T$10,IF(AND(ISNUMBER(SEARCH($F$2,$B38)),ISNUMBER(SEARCH($N$2,$B38)),ISNUMBER(SEARCH($I$2,$B38))),1,""),"") | U38: =IF($C38=U$10,IF(AND(ISNUMBER(SEARCH($M$2,$B38)),ISNUMBER(SEARCH($L$2,$B38)),ISNUMBER(SEARCH($J$2,$B38)),ISNUMBER(SEARCH($K$2,$B38))),$H$2,""),"") | V38: =IF($C38=V$10,IF(AND(ISNUMBER(SEARCH($M$2,$B38)),ISNUMBER(SEARCH($J$2,$B38))),1,""),"") | X38: =+X36 -> 36
A39: =+'Pricing sheet'!A49 -> HYD1-3 | B39: =+'Pricing sheet'!B49 -> SET SYSTÈME HYDRAULIQUE MAX4 STANDARD 0,15M/S 4M COURSE (2 NIVEAUX) | C39: =+'Pricing sheet'!C49 -> HYDRAULIQUE | D39: =+'Pricing sheet'!D49 -> SET | E39: =+'Pricing sheet'!E49 -> 199 | F39: =+'Pricing sheet'!M49 -> 523.8675 | G39: =+'Pricing sheet'!N49 -> 523.8675 | H39: =+'Pricing sheet'!O49 -> 523.8675 | I39: =IF(SUM(S39:AC39)<>0,SUM(S39:AC39),"") -> 36 | S39: =IF($C39=S$10,IF(AND(ISNUMBER(SEARCH($F$2,$B39)),ISNUMBER(SEARCH($N$2,$B39)),ISNUMBER(SEARCH($N$2,$B39))),1,""),"") | T39: =IF($C39=T$10,IF(AND(ISNUMBER(SEARCH($F$2,$B39)),ISNUMBER(SEARCH($N$2,$B39)),ISNUMBER(SEARCH($I$2,$B39))),1,""),"") | U39: =IF($C39=U$10,IF(AND(ISNUMBER(SEARCH($M$2,$B39)),ISNUMBER(SEARCH($L$2,$B39)),ISNUMBER(SEARCH($J$2,$B39)),ISNUMBER(SEARCH($K$2,$B39))),$H$2,""),"") | V39: =IF($C39=V$10,IF(AND(ISNUMBER(SEARCH($M$2,$B39)),ISNUMBER(SEARCH($J$2,$B39))),1,""),"") | X39: =+IF(G2>8,"",X38) -> 36
A40: =+'Pricing sheet'!A50 -> HYD2-1 | B40: =+'Pricing sheet'!B50 -> SET SYSTÈME HYDRAULIQUE MAX4 GMV 0,62M/S 10M COURSE (4 NIVEAUX) | C40: =+'Pricing sheet'!C50 -> HYDRAULIQUE | D40: =+'Pricing sheet'!D50 -> SET | E40: =+'Pricing sheet'!E50 -> 200 | F40: =+'Pricing sheet'!M50 -> 49997.112 | G40: =+'Pricing sheet'!N50 -> 53231.112 | H40: =+'Pricing sheet'!O50 -> 58657.236 | I40: =IF(SUM(S40:AC40)<>0,SUM(S40:AC40),"") | S40: =IF($C40=S$10,IF(AND(ISNUMBER(SEARCH($F$2,$B40)),ISNUMBER(SEARCH($N$2,$B40)),ISNUMBER(SEARCH($N$2,$B40))),1,""),"") | T40: =IF($C40=T$10,IF(AND(ISNUMBER(SEARCH($F$2,$B40)),ISNUMBER(SEARCH($N$2,$B40)),ISNUMBER(SEARCH($I$2,$B40))),1,""),"") | U40: =IF($C40=U$10,IF(AND(ISNUMBER(SEARCH($M$2,$B40)),ISNUMBER(SEARCH($L$2,$B40)),ISNUMBER(SEARCH($J$2,$B40)),ISNUMBER(SEARCH($K$2,$B40))),$H$2,""),"") | V40: =IF($C40=V$10,IF(AND(ISNUMBER(SEARCH($M$2,$B40)),ISNUMBER(SEARCH($J$2,$B40))),1,""),"")
A41: =+'Pricing sheet'!A51 -> HYD2-2 | B41: =+'Pricing sheet'!B51 -> SET SYSTÈME HYDRAULIQUE MAX4 GMV 0,62M/S 7M COURSE (3 NIVEAUX) | C41: =+'Pricing sheet'!C51 -> HYDRAULIQUE | D41: =+'Pricing sheet'!D51 -> SET | E41: =+'Pricing sheet'!E51 -> 200 | F41: =+'Pricing sheet'!M51 -> 45447.598 | G41: =+'Pricing sheet'!N51 -> 48387.598 | H41: =+'Pricing sheet'!O51 -> 53316.116 | I41: =IF(SUM(S41:AC41)<>0,SUM(S41:AC41),"") | S41: =IF($C41=S$10,IF(AND(ISNUMBER(SEARCH($F$2,$B41)),ISNUMBER(SEARCH($N$2,$B41)),ISNUMBER(SEARCH($N$2,$B41))),1,""),"") | T41: =IF($C41=T$10,IF(AND(ISNUMBER(SEARCH($F$2,$B41)),ISNUMBER(SEARCH($N$2,$B41)),ISNUMBER(SEARCH($I$2,$B41))),1,""),"") | U41: =IF($C41=U$10,IF(AND(ISNUMBER(SEARCH($M$2,$B41)),ISNUMBER(SEARCH($L$2,$B41)),ISNUMBER(SEARCH($J$2,$B41)),ISNUMBER(SEARCH($K$2,$B41))),$H$2,""),"") | V41: =IF($C41=V$10,IF(AND(ISNUMBER(SEARCH($M$2,$B41)),ISNUMBER(SEARCH($J$2,$B41))),1,""),"") | X41: =+IF(G2>8,X38,"")
A42: =+'Pricing sheet'!A52 -> HYD2-3 | B42: =+'Pricing sheet'!B52 -> SET SYSTÈME HYDRAULIQUE MAX4 GMV 0,62M/S 4M COURSE (2 NIVEAUX) | C42: =+'Pricing sheet'!C52 -> HYDRAULIQUE | D42: =+'Pricing sheet'!D52 -> SET | E42: =+'Pricing sheet'!E52 -> 200 | F42: =+'Pricing sheet'!M52 -> 40898.949 | G42: =+'Pricing sheet'!N52 -> 43544.949 | H42: =+'Pricing sheet'!O52 -> 47976.725 | I42: =IF(SUM(S42:AC42)<>0,SUM(S42:AC42),"") | S42: =IF($C42=S$10,IF(AND(ISNUMBER(SEARCH($F$2,$B42)),ISNUMBER(SEARCH($N$2,$B42)),ISNUMBER(SEARCH($N$2,$B42))),1,""),"") | T42: =IF($C42=T$10,IF(AND(ISNUMBER(SEARCH($F$2,$B42)),ISNUMBER(SEARCH($N$2,$B42)),ISNUMBER(SEARCH($I$2,$B42))),1,""),"") | U42: =IF($C42=U$10,IF(AND(ISNUMBER(SEARCH($M$2,$B42)),ISNUMBER(SEARCH($L$2,$B42)),ISNUMBER(SEARCH($J$2,$B42)),ISNUMBER(SEARCH($K$2,$B42))),$H$2,""),"") | V42: =IF($C42=V$10,IF(AND(ISNUMBER(SEARCH($M$2,$B42)),ISNUMBER(SEARCH($J$2,$B42))),1,""),"")
A43: =+'Pricing sheet'!A53 -> HYD3 | B43: =+'Pricing sheet'!B53 -> SET COMPOSANTES ELECTRIQUES POUR SYSTEME HYDRAULIQUE | C43: =+'Pricing sheet'!C53 -> HYDRAULIQUE | D43: =+'Pricing sheet'!D53 -> SET | E43: =+'Pricing sheet'!E53 -> 200 | F43: =+'Pricing sheet'!M53 -> 12110.908 | G43: =+'Pricing sheet'!N53 -> 12894.908 | H43: =+'Pricing sheet'!O53 -> 14200.728 | I43: =IF(SUM(S43:AC43)<>0,SUM(S43:AC43),"") -> 64 | S43: =IF($C43=S$10,IF(AND(ISNUMBER(SEARCH($F$2,$B43)),ISNUMBER(SEARCH($N$2,$B43)),ISNUMBER(SEARCH($N$2,$B43))),1,""),"") | T43: =IF($C43=T$10,IF(AND(ISNUMBER(SEARCH($F$2,$B43)),ISNUMBER(SEARCH($N$2,$B43)),ISNUMBER(SEARCH($I$2,$B43))),1,""),"") | U43: =IF($C43=U$10,IF(AND(ISNUMBER(SEARCH($M$2,$B43)),ISNUMBER(SEARCH($L$2,$B43)),ISNUMBER(SEARCH($J$2,$B43)),ISNUMBER(SEARCH($K$2,$B43))),$H$2,""),"") | V43: =IF($C43=V$10,IF(AND(ISNUMBER(SEARCH($M$2,$B43)),ISNUMBER(SEARCH($J$2,$B43))),1,""),"") | X43: =+X48*8 -> 64
A44: =+'Pricing sheet'!A54 -> HYD4 | B44: =+'Pricing sheet'!B54 -> HUILE HYDRAULIQUE | C44: =+'Pricing sheet'!C54 -> HYDRAULIQUE | D44: =+'Pricing sheet'!D54 -> L | E44: =+'Pricing sheet'!E54 -> 1 | F44: =+'Pricing sheet'!M54 -> 60.53925 | G44: =+'Pricing sheet'!N54 -> 64.45925 | H44: =+'Pricing sheet'!O54 -> 70.97306 | I44: =IF(SUM(S44:AC44)<>0,SUM(S44:AC44),"") -> 72 | S44: =IF($C44=S$10,IF(AND(ISNUMBER(SEARCH($F$2,$B44)),ISNUMBER(SEARCH($N$2,$B44)),ISNUMBER(SEARCH($N$2,$B44))),1,""),"") | T44: =IF($C44=T$10,IF(AND(ISNUMBER(SEARCH($F$2,$B44)),ISNUMBER(SEARCH($N$2,$B44)),ISNUMBER(SEARCH($I$2,$B44))),1,""),"") | U44: =IF($C44=U$10,IF(AND(ISNUMBER(SEARCH($M$2,$B44)),ISNUMBER(SEARCH($L$2,$B44)),ISNUMBER(SEARCH($J$2,$B44)),ISNUMBER(SEARCH($K$2,$B44))),$H$2,""),"") | V44: =IF($C44=V$10,IF(AND(ISNUMBER(SEARCH($M$2,$B44)),ISNUMBER(SEARCH($J$2,$B44))),1,""),"") | X44: =+X36*2 -> 72
A45: =+'Pricing sheet'!A55 -> IT.2 | B45: =+'Pricing sheet'!B55 -> PORTE PALIERE AUTOMATIQUE INOX ATERYA 70/80 | C45: =+'Pricing sheet'!C55 -> PORTE | D45: =+'Pricing sheet'!D55 -> Pc | E45: =+'Pricing sheet'!E55 -> 145 | F45: =+'Pricing sheet'!M55 -> 4498.4592 | G45: =+'Pricing sheet'!N55 -> 4746.1479 | H45: =+'Pricing sheet'!O55 -> 5158.0308 | I45: =IF(SUM(S45:AC45)<>0,SUM(S45:AC45),"") -> 69 | S45: =IF($C45=S$10,IF(AND(ISNUMBER(SEARCH($F$2,$B45)),ISNUMBER(SEARCH($N$2,$B45)),ISNUMBER(SEARCH($N$2,$B45))),1,""),"") | T45: =IF($C45=T$10,IF(AND(ISNUMBER(SEARCH($F$2,$B45)),ISNUMBER(SEARCH($N$2,$B45)),ISNUMBER(SEARCH($I$2,$B45))),1,""),"") | U45: =IF($C45=U$10,IF(AND(ISNUMBER(SEARCH($M$2,$B45)),ISNUMBER(SEARCH($L$2,$B45)),ISNUMBER(SEARCH($J$2,$B45)),ISNUMBER(SEARCH($K$2,$B45))),$H$2,""),"") -> 5 | V45: =IF($C45=V$10,IF(AND(ISNUMBER(SEARCH($M$2,$B45)),ISNUMBER(SEARCH($J$2,$B45))),1,""),"") | X45: =+X43 -> 64
A46: =+'Pricing sheet'!A56 -> IT.3 | B46: =+'Pricing sheet'!B56 -> PORTE PALIERE AUTOMATIQUE EPOXY ATERYA 70/80 | C46: =+'Pricing sheet'!C56 -> PORTE | D46: =+'Pricing sheet'!D56 -> Pc | E46: =+'Pricing sheet'!E56 -> 140 | F46: =+'Pricing sheet'!M56 -> 2818.7513 | G46: =+'Pricing sheet'!N56 -> 3001.2588 | H46: =+'Pricing sheet'!O56 -> 3304.6919 | I46: =IF(SUM(S46:AC46)<>0,SUM(S46:AC46),"") -> 6 | S46: =IF($C46=S$10,IF(AND(ISNUMBER(SEARCH($F$2,$B46)),ISNUMBER(SEARCH($N$2,$B46)),ISNUMBER(SEARCH($N$2,$B46))),1,""),"") | T46: =IF($C46=T$10,IF(AND(ISNUMBER(SEARCH($F$2,$B46)),ISNUMBER(SEARCH($N$2,$B46)),ISNUMBER(SEARCH($I$2,$B46))),1,""),"") | U46: =IF($C46=U$10,IF(AND(ISNUMBER(SEARCH($M$2,$B46)),ISNUMBER(SEARCH($L$2,$B46)),ISNUMBER(SEARCH($J$2,$B46)),ISNUMBER(SEARCH($K$2,$B46))),$H$2,""),"") | V46: =IF($C46=V$10,IF(AND(ISNUMBER(SEARCH($M$2,$B46)),ISNUMBER(SEARCH($J$2,$B46))),1,""),"") | X46: 6
A47: =+'Pricing sheet'!A57 -> IT.4 | B47: =+'Pricing sheet'!B57 -> OPERATEUR INOX ATERYA 70/80 | C47: =+'Pricing sheet'!C57 -> OPÉRATEUR | D47: =+'Pricing sheet'!D57 -> Pc | E47: =+'Pricing sheet'!E57 -> 38 | F47: =+'Pricing sheet'!M57 -> 6342.6588 | G47: =+'Pricing sheet'!N57 -> 6753.3006 | H47: =+'Pricing sheet'!O57 -> 7436.4936 | I47: =IF(SUM(S47:AC47)<>0,SUM(S47:AC47),"") -> 118 | S47: =IF($C47=S$10,IF(AND(ISNUMBER(SEARCH($F$2,$B47)),ISNUMBER(SEARCH($N$2,$B47)),ISNUMBER(SEARCH($N$2,$B47))),1,""),"") | T47: =IF($C47=T$10,IF(AND(ISNUMBER(SEARCH($F$2,$B47)),ISNUMBER(SEARCH($N$2,$B47)),ISNUMBER(SEARCH($I$2,$B47))),1,""),"") | U47: =IF($C47=U$10,IF(AND(ISNUMBER(SEARCH($M$2,$B47)),ISNUMBER(SEARCH($L$2,$B47)),ISNUMBER(SEARCH($J$2,$B47)),ISNUMBER(SEARCH($K$2,$B47))),$H$2,""),"") | V47: =IF($C47=V$10,IF(AND(ISNUMBER(SEARCH($M$2,$B47)),ISNUMBER(SEARCH($J$2,$B47))),1,""),"") -> 1 | X47: =IF(F2="GEARLESS",2*X36+(H2*5)+20,2*X36+(H2*5)+8) -> 117
A48: =+'Pricing sheet'!A58 -> IT.5 | B48: =+'Pricing sheet'!B58 -> SEMI AUTOMATIC PORTE EPOXY 70/80 | C48: =+'Pricing sheet'!C58 -> PORTE | D48: =+'Pricing sheet'!D58 -> Pc | E48: =+'Pricing sheet'!E58 -> 90 | F48: =+'Pricing sheet'!M58 -> 1683.5154 | G48: =+'Pricing sheet'!N58 -> 1791.3154 | H48: =+'Pricing sheet'!O58 -> 1970.5011 | I48: =IF(SUM(S48:AC48)<>0,SUM(S48:AC48),"") -> 8 | S48: =IF($C48=S$10,IF(AND(ISNUMBER(SEARCH($F$2,$B48)),ISNUMBER(SEARCH($N$2,$B48)),ISNUMBER(SEARCH($N$2,$B48))),1,""),"") | T48: =IF($C48=T$10,IF(AND(ISNUMBER(SEARCH($F$2,$B48)),ISNUMBER(SEARCH($N$2,$B48)),ISNUMBER(SEARCH($I$2,$B48))),1,""),"") | U48: =IF($C48=U$10,IF(AND(ISNUMBER(SEARCH($M$2,$B48)),ISNUMBER(SEARCH($L$2,$B48)),ISNUMBER(SEARCH($J$2,$B48)),ISNUMBER(SEARCH($K$2,$B48))),$H$2,""),"") | V48: =IF($C48=V$10,IF(AND(ISNUMBER(SEARCH($M$2,$B48)),ISNUMBER(SEARCH($J$2,$B48))),1,""),"") | X48: =+(INT((H2+1)*3*2/5)+1) -> 8
A49: =+'Pricing sheet'!A59 -> IT.6 | B49: =+'Pricing sheet'!B59 -> SEMI AUTOMATIC PORTE INOX 70/80 | C49: =+'Pricing sheet'!C59 -> PORTE | D49: =+'Pricing sheet'!D59 -> Pc | E49: =+'Pricing sheet'!E59 -> 90 | F49: =+'Pricing sheet'!M59 -> 2175.5904 | G49: =+'Pricing sheet'!N59 -> 2283.3904 | H49: =+'Pricing sheet'!O59 -> 2462.5761 | I49: =IF(SUM(S49:AC49)<>0,SUM(S49:AC49),"") -> 8 | S49: =IF($C49=S$10,IF(AND(ISNUMBER(SEARCH($F$2,$B49)),ISNUMBER(SEARCH($N$2,$B49)),ISNUMBER(SEARCH($N$2,$B49))),1,""),"") | T49: =IF($C49=T$10,IF(AND(ISNUMBER(SEARCH($F$2,$B49)),ISNUMBER(SEARCH($N$2,$B49)),ISNUMBER(SEARCH($I$2,$B49))),1,""),"") | U49: =IF($C49=U$10,IF(AND(ISNUMBER(SEARCH($M$2,$B49)),ISNUMBER(SEARCH($L$2,$B49)),ISNUMBER(SEARCH($J$2,$B49)),ISNUMBER(SEARCH($K$2,$B49))),$H$2,""),"") | V49: =IF($C49=V$10,IF(AND(ISNUMBER(SEARCH($M$2,$B49)),ISNUMBER(SEARCH($J$2,$B49))),1,""),"") | X49: =+IF(G2>8,"",X48) -> 8
A50: =+'Pricing sheet'!A60 -> IT.7 | B50: =+'Pricing sheet'!B60 -> SERRURE (DOOR LOCK) | C50: =+'Pricing sheet'!C60 -> AUTRES | D50: =+'Pricing sheet'!D60 -> Pc | E50: =+'Pricing sheet'!E60 -> 3 | F50: =+'Pricing sheet'!M60 -> 272.42784 | G50: =+'Pricing sheet'!N60 -> 290.06784 | H50: =+'Pricing sheet'!O60 -> 319.38119 | I50: =IF(SUM(S50:AC50)<>0,SUM(S50:AC50),"") | S50: =IF($C50=S$10,IF(AND(ISNUMBER(SEARCH($F$2,$B50)),ISNUMBER(SEARCH($N$2,$B50)),ISNUMBER(SEARCH($N$2,$B50))),1,""),"") | T50: =IF($C50=T$10,IF(AND(ISNUMBER(SEARCH($F$2,$B50)),ISNUMBER(SEARCH($N$2,$B50)),ISNUMBER(SEARCH($I$2,$B50))),1,""),"") | U50: =IF($C50=U$10,IF(AND(ISNUMBER(SEARCH($M$2,$B50)),ISNUMBER(SEARCH($L$2,$B50)),ISNUMBER(SEARCH($J$2,$B50)),ISNUMBER(SEARCH($K$2,$B50))),$H$2,""),"") | V50: =IF($C50=V$10,IF(AND(ISNUMBER(SEARCH($M$2,$B50)),ISNUMBER(SEARCH($J$2,$B50))),1,""),"")
A51: =+'Pricing sheet'!A61 -> IT.8 | B51: =+'Pricing sheet'!B61 -> CAME DC 220V / 60V | C51: =+'Pricing sheet'!C61 -> AUTRES | D51: =+'Pricing sheet'!D61 -> Pc | E51: =+'Pricing sheet'!E61 -> 4 | F51: =+'Pricing sheet'!M61 -> 665.9402 | G51: =+'Pricing sheet'!N61 -> 709.0602 | H51: =+'Pricing sheet'!O61 -> 780.72057 | I51: =IF(SUM(S51:AC51)<>0,SUM(S51:AC51),"") | S51: =IF($C51=S$10,IF(AND(ISNUMBER(SEARCH($F$2,$B51)),ISNUMBER(SEARCH($N$2,$B51)),ISNUMBER(SEARCH($N$2,$B51))),1,""),"") | T51: =IF($C51=T$10,IF(AND(ISNUMBER(SEARCH($F$2,$B51)),ISNUMBER(SEARCH($N$2,$B51)),ISNUMBER(SEARCH($I$2,$B51))),1,""),"") | U51: =IF($C51=U$10,IF(AND(ISNUMBER(SEARCH($M$2,$B51)),ISNUMBER(SEARCH($L$2,$B51)),ISNUMBER(SEARCH($J$2,$B51)),ISNUMBER(SEARCH($K$2,$B51))),$H$2,""),"") | V51: =IF($C51=V$10,IF(AND(ISNUMBER(SEARCH($M$2,$B51)),ISNUMBER(SEARCH($J$2,$B51))),1,""),"") | X51: =+IF(G2<=8,"",X48)
A52: =+'Pricing sheet'!A62 -> IT.9 | B52: =+'Pricing sheet'!B62 -> DICTATOR | C52: =+'Pricing sheet'!C62 -> AUTRES | D52: =+'Pricing sheet'!D62 -> Pc | E52: =+'Pricing sheet'!E62 -> 2 | F52: =+'Pricing sheet'!M62 -> 102.91682 | G52: =+'Pricing sheet'!N62 -> 109.58082 | H52: =+'Pricing sheet'!O62 -> 120.65439 | I52: =IF(SUM(S52:AC52)<>0,SUM(S52:AC52),"") | S52: =IF($C52=S$10,IF(AND(ISNUMBER(SEARCH($F$2,$B52)),ISNUMBER(SEARCH($N$2,$B52)),ISNUMBER(SEARCH($N$2,$B52))),1,""),"") | T52: =IF($C52=T$10,IF(AND(ISNUMBER(SEARCH($F$2,$B52)),ISNUMBER(SEARCH($N$2,$B52)),ISNUMBER(SEARCH($I$2,$B52))),1,""),"") | U52: =IF($C52=U$10,IF(AND(ISNUMBER(SEARCH($M$2,$B52)),ISNUMBER(SEARCH($L$2,$B52)),ISNUMBER(SEARCH($J$2,$B52)),ISNUMBER(SEARCH($K$2,$B52))),$H$2,""),"") | V52: =IF($C52=V$10,IF(AND(ISNUMBER(SEARCH($M$2,$B52)),ISNUMBER(SEARCH($J$2,$B52))),1,""),"")
A53: =+'Pricing sheet'!A63 -> IT.10 | B53: =+'Pricing sheet'!B63 -> MOTEUR AKİŞ VOLPİ GEARLESS 3,9KW MAX4 MAX6 240*5*6,5MM 1,0M/S VVVF +ENCODEUR | C53: =+'Pricing sheet'!C63 -> MOTEUR | D53: =+'Pricing sheet'!D63 -> Pc | E53: =+'Pricing sheet'!E63 -> 180 | F53: =+'Pricing sheet'!M63 -> 15442.485 | G53: =+'Pricing sheet'!N63 -> 16442.085 | H53: =+'Pricing sheet'!O63 -> 18108.083 | I53: =IF(SUM(S53:AC53)<>0,SUM(S53:AC53),"") | S53: =IF($C53=S$10,IF(AND(ISNUMBER(SEARCH($F$2,$B53)),ISNUMBER(SEARCH($N$2,$B53)),ISNUMBER(SEARCH($N$2,$B53))),1,""),"") | T53: =IF($C53=T$10,IF(AND(ISNUMBER(SEARCH($F$2,$B53)),ISNUMBER(SEARCH($N$2,$B53)),ISNUMBER(SEARCH($I$2,$B53))),1,""),"") | U53: =IF($C53=U$10,IF(AND(ISNUMBER(SEARCH($M$2,$B53)),ISNUMBER(SEARCH($L$2,$B53)),ISNUMBER(SEARCH($J$2,$B53)),ISNUMBER(SEARCH($K$2,$B53))),$H$2,""),"") | V53: =IF($C53=V$10,IF(AND(ISNUMBER(SEARCH($M$2,$B53)),ISNUMBER(SEARCH($J$2,$B53))),1,""),"") | Y53: =+IF(F2="GEARLESS","",IF(G2<=4,4*(H2*3+3+5),5*(H2*3+3+5)))
A54: =+'Pricing sheet'!A64 -> IT.11 | B54: =+'Pricing sheet'!B64 -> MOTEUR AKİŞ VOLPİ GEARLESS 4,9KW MAX8 MAX10 240*7*6,5MM 1,0M/S VVVF +ENCODEUR | C54: =+'Pricing sheet'!C64 -> MOTEUR | D54: =+'Pricing sheet'!D64 -> Pc | E54: =+'Pricing sheet'!E64 -> 240 | F54: =+'Pricing sheet'!M64 -> 16336.033 | G54: =+'Pricing sheet'!N64 -> 17393.453 | H54: =+'Pricing sheet'!O64 -> 19156.123 | I54: =IF(SUM(S54:AC54)<>0,SUM(S54:AC54),"") -> 247 | S54: =IF($C54=S$10,IF(AND(ISNUMBER(SEARCH($F$2,$B54)),ISNUMBER(SEARCH($N$2,$B54)),ISNUMBER(SEARCH($N$2,$B54))),1,""),"") | T54: =IF($C54=T$10,IF(AND(ISNUMBER(SEARCH($F$2,$B54)),ISNUMBER(SEARCH($N$2,$B54)),ISNUMBER(SEARCH($I$2,$B54))),1,""),"") -> 1 | U54: =IF($C54=U$10,IF(AND(ISNUMBER(SEARCH($M$2,$B54)),ISNUMBER(SEARCH($L$2,$B54)),ISNUMBER(SEARCH($J$2,$B54)),ISNUMBER(SEARCH($K$2,$B54))),$H$2,""),"") | V54: =IF($C54=V$10,IF(AND(ISNUMBER(SEARCH($M$2,$B54)),ISNUMBER(SEARCH($J$2,$B54))),1,""),"") | Y54: =+IF(F2="GEARLESS",IF(G2<=5,G2*(2*(H2*3+3)+5),(G2-1*INT((G2-4)/2))*(2*(H2*3+3)+5)),"") -> 246
A55: =+'Pricing sheet'!A65 -> IT.12 | B55: =+'Pricing sheet'!B65 -> MOTEUR AKİŞ 2V MAX4 MAX6 | C55: =+'Pricing sheet'!C65 -> MOTEUR | D55: =+'Pricing sheet'!D65 -> Pc | E55: =+'Pricing sheet'!E65 -> 320 | F55: =+'Pricing sheet'!M65 -> 15139.595 | G55: =+'Pricing sheet'!N65 -> 16119.595 | H55: =+'Pricing sheet'!O65 -> 17752.831 | I55: =IF(SUM(S55:AC55)<>0,SUM(S55:AC55),"") -> 33 | S55: =IF($C55=S$10,IF(AND(ISNUMBER(SEARCH($F$2,$B55)),ISNUMBER(SEARCH($N$2,$B55)),ISNUMBER(SEARCH($N$2,$B55))),1,""),"") | T55: =IF($C55=T$10,IF(AND(ISNUMBER(SEARCH($F$2,$B55)),ISNUMBER(SEARCH($N$2,$B55)),ISNUMBER(SEARCH($I$2,$B55))),1,""),"") | U55: =IF($C55=U$10,IF(AND(ISNUMBER(SEARCH($M$2,$B55)),ISNUMBER(SEARCH($L$2,$B55)),ISNUMBER(SEARCH($J$2,$B55)),ISNUMBER(SEARCH($K$2,$B55))),$H$2,""),"") | V55: =IF($C55=V$10,IF(AND(ISNUMBER(SEARCH($M$2,$B55)),ISNUMBER(SEARCH($J$2,$B55))),1,""),"") | Y55: =+(H2*3*2+3) -> 33
A56: =+'Pricing sheet'!A66 -> IT.13 | B56: =+'Pricing sheet'!B66 -> MOTEUR AKİŞ 2V MAX8 | C56: =+'Pricing sheet'!C66 -> MOTEUR | D56: =+'Pricing sheet'!D66 -> Pc | E56: =+'Pricing sheet'!E66 -> 380 | F56: =+'Pricing sheet'!M66 -> 16199.727 | G56: =+'Pricing sheet'!N66 -> 17248.327 | H56: =+'Pricing sheet'!O66 -> 18996.248 | I56: =IF(SUM(S56:AC56)<>0,SUM(S56:AC56),"") | S56: =IF($C56=S$10,IF(AND(ISNUMBER(SEARCH($F$2,$B56)),ISNUMBER(SEARCH($N$2,$B56)),ISNUMBER(SEARCH($N$2,$B56))),1,""),"") | T56: =IF($C56=T$10,IF(AND(ISNUMBER(SEARCH($F$2,$B56)),ISNUMBER(SEARCH($N$2,$B56)),ISNUMBER(SEARCH($I$2,$B56))),1,""),"") | U56: =IF($C56=U$10,IF(AND(ISNUMBER(SEARCH($M$2,$B56)),ISNUMBER(SEARCH($L$2,$B56)),ISNUMBER(SEARCH($J$2,$B56)),ISNUMBER(SEARCH($K$2,$B56))),$H$2,""),"") | V56: =IF($C56=V$10,IF(AND(ISNUMBER(SEARCH($M$2,$B56)),ISNUMBER(SEARCH($J$2,$B56))),1,""),"") | Y56: =+IF(F2="GEARLESS","",IF(G2<=4,4*2,5*2))
A57: =+'Pricing sheet'!A67 -> IT.14 | B57: =+'Pricing sheet'!B67 -> CLASSIC BRACKET 60X60 (PATE) | C57: =+'Pricing sheet'!C67 -> RAILS & ACCESSOIRES | D57: =+'Pricing sheet'!D67 -> Pc | E57: =+'Pricing sheet'!E67 -> 0.5 | F57: =+'Pricing sheet'!M67 -> 9.2064277 | G57: =+'Pricing sheet'!N67 -> 9.7944277 | H57: =+'Pricing sheet'!O67 -> 10.771489 | I57: =IF(SUM(S57:AC57)<>0,SUM(S57:AC57),"") -> 12 | S57: =IF($C57=S$10,IF(AND(ISNUMBER(SEARCH($F$2,$B57)),ISNUMBER(SEARCH($N$2,$B57)),ISNUMBER(SEARCH($N$2,$B57))),1,""),"") | T57: =IF($C57=T$10,IF(AND(ISNUMBER(SEARCH($F$2,$B57)),ISNUMBER(SEARCH($N$2,$B57)),ISNUMBER(SEARCH($I$2,$B57))),1,""),"") | U57: =IF($C57=U$10,IF(AND(ISNUMBER(SEARCH($M$2,$B57)),ISNUMBER(SEARCH($L$2,$B57)),ISNUMBER(SEARCH($J$2,$B57)),ISNUMBER(SEARCH($K$2,$B57))),$H$2,""),"") | V57: =IF($C57=V$10,IF(AND(ISNUMBER(SEARCH($M$2,$B57)),ISNUMBER(SEARCH($J$2,$B57))),1,""),"") | Y57: =+IF(F2="GEARLESS",IF(G2<=5,G2*2,(G2-1*INT((G2-4)/2))*2),"") -> 12
A58: =+'Pricing sheet'!A68 -> IT.15 | B58: =+'Pricing sheet'!B68 -> CLASSIC BRACKET 60X80 (PATE) | C58: =+'Pricing sheet'!C68 -> RAILS & ACCESSOIRES | D58: =+'Pricing sheet'!D68 -> Pc | E58: =+'Pricing sheet'!E68 -> 0.65 | F58: =+'Pricing sheet'!M68 -> 13.621318 | G58: =+'Pricing sheet'!N68 -> 14.503318 | H58: =+'Pricing sheet'!O68 -> 15.968912 | I58: =IF(SUM(S58:AC58)<>0,SUM(S58:AC58),"") | S58: =IF($C58=S$10,IF(AND(ISNUMBER(SEARCH($F$2,$B58)),ISNUMBER(SEARCH($N$2,$B58)),ISNUMBER(SEARCH($N$2,$B58))),1,""),"") | T58: =IF($C58=T$10,IF(AND(ISNUMBER(SEARCH($F$2,$B58)),ISNUMBER(SEARCH($N$2,$B58)),ISNUMBER(SEARCH($I$2,$B58))),1,""),"") | U58: =IF($C58=U$10,IF(AND(ISNUMBER(SEARCH($M$2,$B58)),ISNUMBER(SEARCH($L$2,$B58)),ISNUMBER(SEARCH($J$2,$B58)),ISNUMBER(SEARCH($K$2,$B58))),$H$2,""),"") | V58: =IF($C58=V$10,IF(AND(ISNUMBER(SEARCH($M$2,$B58)),ISNUMBER(SEARCH($J$2,$B58))),1,""),"") | Y58: =+IF(F2="GEARLESS","",Y56*3)
A59: =+'Pricing sheet'!A69 -> IT.16 | B59: =+'Pricing sheet'!B69 -> CROMPO 50 | C59: =+'Pricing sheet'!C69 -> RAILS & ACCESSOIRES | D59: =+'Pricing sheet'!D69 -> Pc | E59: =+'Pricing sheet'!E69 -> 0.11 | F59: =+'Pricing sheet'!M69 -> 4.2377425 | G59: =+'Pricing sheet'!N69 -> 4.5121425 | H59: =+'Pricing sheet'!O69 -> 4.9681042 | I59: =IF(SUM(S59:AC59)<>0,SUM(S59:AC59),"") -> 36 | S59: =IF($C59=S$10,IF(AND(ISNUMBER(SEARCH($F$2,$B59)),ISNUMBER(SEARCH($N$2,$B59)),ISNUMBER(SEARCH($N$2,$B59))),1,""),"") | T59: =IF($C59=T$10,IF(AND(ISNUMBER(SEARCH($F$2,$B59)),ISNUMBER(SEARCH($N$2,$B59)),ISNUMBER(SEARCH($I$2,$B59))),1,""),"") | U59: =IF($C59=U$10,IF(AND(ISNUMBER(SEARCH($M$2,$B59)),ISNUMBER(SEARCH($L$2,$B59)),ISNUMBER(SEARCH($J$2,$B59)),ISNUMBER(SEARCH($K$2,$B59))),$H$2,""),"") | V59: =IF($C59=V$10,IF(AND(ISNUMBER(SEARCH($M$2,$B59)),ISNUMBER(SEARCH($J$2,$B59))),1,""),"") | Y59: =+IF(F2="GEARLESS",Y57*3,"") -> 36
A60: =+'Pricing sheet'!A70 -> IT.17 | B60: =+'Pricing sheet'!B70 -> CROMPO 70 | C60: =+'Pricing sheet'!C70 -> RAILS & ACCESSOIRES | D60: =+'Pricing sheet'!D70 -> Pc | E60: =+'Pricing sheet'!E70 -> 0.12 | F60: =+'Pricing sheet'!M70 -> 5.5998742 | G60: =+'Pricing sheet'!N70 -> 5.9624742 | H60: =+'Pricing sheet'!O70 -> 6.5649952 | I60: =IF(SUM(S60:AC60)<>0,SUM(S60:AC60),"") -> 6 | S60: =IF($C60=S$10,IF(AND(ISNUMBER(SEARCH($F$2,$B60)),ISNUMBER(SEARCH($N$2,$B60)),ISNUMBER(SEARCH($N$2,$B60))),1,""),"") | T60: =IF($C60=T$10,IF(AND(ISNUMBER(SEARCH($F$2,$B60)),ISNUMBER(SEARCH($N$2,$B60)),ISNUMBER(SEARCH($I$2,$B60))),1,""),"") | U60: =IF($C60=U$10,IF(AND(ISNUMBER(SEARCH($M$2,$B60)),ISNUMBER(SEARCH($L$2,$B60)),ISNUMBER(SEARCH($J$2,$B60)),ISNUMBER(SEARCH($K$2,$B60))),$H$2,""),"") | V60: =IF($C60=V$10,IF(AND(ISNUMBER(SEARCH($M$2,$B60)),ISNUMBER(SEARCH($J$2,$B60))),1,""),"") | Y60: 6
A61: =+'Pricing sheet'!A71 -> IT.18 | B61: =+'Pricing sheet'!B71 -> SET BRACKET U | C61: =+'Pricing sheet'!C71 -> RAILS & ACCESSOIRES | D61: =+'Pricing sheet'!D71 -> SET | E61: =+'Pricing sheet'!E71 -> 30 | F61: =+'Pricing sheet'!M71 -> 606.06615 | G61: =+'Pricing sheet'!N71 -> 640.36615 | H61: =+'Pricing sheet'!O71 -> 697.3672 | I61: =IF(SUM(S61:AC61)<>0,SUM(S61:AC61),"") | S61: =IF($C61=S$10,IF(AND(ISNUMBER(SEARCH($F$2,$B61)),ISNUMBER(SEARCH($N$2,$B61)),ISNUMBER(SEARCH($N$2,$B61))),1,""),"") | T61: =IF($C61=T$10,IF(AND(ISNUMBER(SEARCH($F$2,$B61)),ISNUMBER(SEARCH($N$2,$B61)),ISNUMBER(SEARCH($I$2,$B61))),1,""),"") | U61: =IF($C61=U$10,IF(AND(ISNUMBER(SEARCH($M$2,$B61)),ISNUMBER(SEARCH($L$2,$B61)),ISNUMBER(SEARCH($J$2,$B61)),ISNUMBER(SEARCH($K$2,$B61))),$H$2,""),"") | V61: =IF($C61=V$10,IF(AND(ISNUMBER(SEARCH($M$2,$B61)),ISNUMBER(SEARCH($J$2,$B61))),1,""),"")
A62: =+'Pricing sheet'!A72 -> IT.19 | B62: =+'Pricing sheet'!B72 -> CROMPO 90 | C62: =+'Pricing sheet'!C72 -> RAILS & ACCESSOIRES | D62: =+'Pricing sheet'!D72 -> Pc | E62: =+'Pricing sheet'!E72 -> 0.17 | F62: =+'Pricing sheet'!M72 -> 7.1133539 | G62: =+'Pricing sheet'!N72 -> 7.5739539 | H62: =+'Pricing sheet'!O72 -> 8.3393187 | I62: =IF(SUM(S62:AC62)<>0,SUM(S62:AC62),"") -> 4 | S62: =IF($C62=S$10,IF(AND(ISNUMBER(SEARCH($F$2,$B62)),ISNUMBER(SEARCH($N$2,$B62)),ISNUMBER(SEARCH($N$2,$B62))),1,""),"") | T62: =IF($C62=T$10,IF(AND(ISNUMBER(SEARCH($F$2,$B62)),ISNUMBER(SEARCH($N$2,$B62)),ISNUMBER(SEARCH($I$2,$B62))),1,""),"") | U62: =IF($C62=U$10,IF(AND(ISNUMBER(SEARCH($M$2,$B62)),ISNUMBER(SEARCH($L$2,$B62)),ISNUMBER(SEARCH($J$2,$B62)),ISNUMBER(SEARCH($K$2,$B62))),$H$2,""),"") | V62: =IF($C62=V$10,IF(AND(ISNUMBER(SEARCH($M$2,$B62)),ISNUMBER(SEARCH($J$2,$B62))),1,""),"") | AC62: 4
A63: =+'Pricing sheet'!A73 -> IT.20 | B63: =+'Pricing sheet'!B73 -> SET BRACKET TYPE L | C63: =+'Pricing sheet'!C73 -> RAILS & ACCESSOIRES | D63: =+'Pricing sheet'!D73 -> SET | E63: =+'Pricing sheet'!E73 -> 30 | F63: =+'Pricing sheet'!M73 -> 803.32667 | G63: =+'Pricing sheet'!N73 -> 852.32667 | H63: =+'Pricing sheet'!O73 -> 933.76034 | I63: =IF(SUM(S63:AC63)<>0,SUM(S63:AC63),"") -> 2 | S63: =IF($C63=S$10,IF(AND(ISNUMBER(SEARCH($F$2,$B63)),ISNUMBER(SEARCH($N$2,$B63)),ISNUMBER(SEARCH($N$2,$B63))),1,""),"") | T63: =IF($C63=T$10,IF(AND(ISNUMBER(SEARCH($F$2,$B63)),ISNUMBER(SEARCH($N$2,$B63)),ISNUMBER(SEARCH($I$2,$B63))),1,""),"") | U63: =IF($C63=U$10,IF(AND(ISNUMBER(SEARCH($M$2,$B63)),ISNUMBER(SEARCH($L$2,$B63)),ISNUMBER(SEARCH($J$2,$B63)),ISNUMBER(SEARCH($K$2,$B63))),$H$2,""),"") | V63: =IF($C63=V$10,IF(AND(ISNUMBER(SEARCH($M$2,$B63)),ISNUMBER(SEARCH($J$2,$B63))),1,""),"") | AC63: 2
A64: =+'Pricing sheet'!A74 -> IT.21 | B64: =+'Pricing sheet'!B74 -> BOULON 8/30 | C64: =+'Pricing sheet'!C74 -> RAILS & ACCESSOIRES | D64: =+'Pricing sheet'!D74 -> Pc | E64: =+'Pricing sheet'!E74 -> 0.02 | F64: =+'Pricing sheet'!M74 -> 1.0594356 | G64: =+'Pricing sheet'!N74 -> 1.1280356 | H64: =+'Pricing sheet'!O74 -> 1.2420259 | I64: =IF(SUM(S64:AC64)<>0,SUM(S64:AC64),"") | S64: =IF($C64=S$10,IF(AND(ISNUMBER(SEARCH($F$2,$B64)),ISNUMBER(SEARCH($N$2,$B64)),ISNUMBER(SEARCH($N$2,$B64))),1,""),"") | T64: =IF($C64=T$10,IF(AND(ISNUMBER(SEARCH($F$2,$B64)),ISNUMBER(SEARCH($N$2,$B64)),ISNUMBER(SEARCH($I$2,$B64))),1,""),"") | U64: =IF($C64=U$10,IF(AND(ISNUMBER(SEARCH($M$2,$B64)),ISNUMBER(SEARCH($L$2,$B64)),ISNUMBER(SEARCH($J$2,$B64)),ISNUMBER(SEARCH($K$2,$B64))),$H$2,""),"") | V64: =IF($C64=V$10,IF(AND(ISNUMBER(SEARCH($M$2,$B64)),ISNUMBER(SEARCH($J$2,$B64))),1,""),"")
A65: =+'Pricing sheet'!A75 -> IT.22 | B65: =+'Pricing sheet'!B75 -> BOULON 12/25 | C65: =+'Pricing sheet'!C75 -> RAILS & ACCESSOIRES | D65: =+'Pricing sheet'!D75 -> Pc | E65: =+'Pricing sheet'!E75 -> 0.04 | F65: =+'Pricing sheet'!M75 -> 2.724263 | G65: =+'Pricing sheet'!N75 -> 2.900663 | H65: =+'Pricing sheet'!O75 -> 3.1937811 | I65: =IF(SUM(S65:AC65)<>0,SUM(S65:AC65),"") | S65: =IF($C65=S$10,IF(AND(ISNUMBER(SEARCH($F$2,$B65)),ISNUMBER(SEARCH($N$2,$B65)),ISNUMBER(SEARCH($N$2,$B65))),1,""),"") | T65: =IF($C65=T$10,IF(AND(ISNUMBER(SEARCH($F$2,$B65)),ISNUMBER(SEARCH($N$2,$B65)),ISNUMBER(SEARCH($I$2,$B65))),1,""),"") | U65: =IF($C65=U$10,IF(AND(ISNUMBER(SEARCH($M$2,$B65)),ISNUMBER(SEARCH($L$2,$B65)),ISNUMBER(SEARCH($J$2,$B65)),ISNUMBER(SEARCH($K$2,$B65))),$H$2,""),"") | V65: =IF($C65=V$10,IF(AND(ISNUMBER(SEARCH($M$2,$B65)),ISNUMBER(SEARCH($J$2,$B65))),1,""),"")
A66: =+'Pricing sheet'!A76 -> IT.23 | B66: =+'Pricing sheet'!B76 -> BOULON 12/40 | C66: =+'Pricing sheet'!C76 -> RAILS & ACCESSOIRES | D66: =+'Pricing sheet'!D76 -> Pc | E66: =+'Pricing sheet'!E76 -> 0.05 | F66: =+'Pricing sheet'!M76 -> 3.0269589 | G66: =+'Pricing sheet'!N76 -> 3.2229589 | H66: =+'Pricing sheet'!O76 -> 3.5486457 | I66: =IF(SUM(S66:AC66)<>0,SUM(S66:AC66),"") | S66: =IF($C66=S$10,IF(AND(ISNUMBER(SEARCH($F$2,$B66)),ISNUMBER(SEARCH($N$2,$B66)),ISNUMBER(SEARCH($N$2,$B66))),1,""),"") | T66: =IF($C66=T$10,IF(AND(ISNUMBER(SEARCH($F$2,$B66)),ISNUMBER(SEARCH($N$2,$B66)),ISNUMBER(SEARCH($I$2,$B66))),1,""),"") | U66: =IF($C66=U$10,IF(AND(ISNUMBER(SEARCH($M$2,$B66)),ISNUMBER(SEARCH($L$2,$B66)),ISNUMBER(SEARCH($J$2,$B66)),ISNUMBER(SEARCH($K$2,$B66))),$H$2,""),"") | V66: =IF($C66=V$10,IF(AND(ISNUMBER(SEARCH($M$2,$B66)),ISNUMBER(SEARCH($J$2,$B66))),1,""),"")
A67: =+'Pricing sheet'!A77 -> IT.24 | B67: =+'Pricing sheet'!B77 -> BOULON 14/70 | C67: =+'Pricing sheet'!C77 -> RAILS & ACCESSOIRES | D67: =+'Pricing sheet'!D77 -> Pc | E67: =+'Pricing sheet'!E77 -> 0 | F67: =+'Pricing sheet'!M77 -> 4.5404384 | G67: =+'Pricing sheet'!N77 -> 4.8344384 | H67: =+'Pricing sheet'!O77 -> 5.3229689 | I67: =IF(SUM(S67:AC67)<>0,SUM(S67:AC67),"") | S67: =IF($C67=S$10,IF(AND(ISNUMBER(SEARCH($F$2,$B67)),ISNUMBER(SEARCH($N$2,$B67)),ISNUMBER(SEARCH($N$2,$B67))),1,""),"") | T67: =IF($C67=T$10,IF(AND(ISNUMBER(SEARCH($F$2,$B67)),ISNUMBER(SEARCH($N$2,$B67)),ISNUMBER(SEARCH($I$2,$B67))),1,""),"") | U67: =IF($C67=U$10,IF(AND(ISNUMBER(SEARCH($M$2,$B67)),ISNUMBER(SEARCH($L$2,$B67)),ISNUMBER(SEARCH($J$2,$B67)),ISNUMBER(SEARCH($K$2,$B67))),$H$2,""),"") | V67: =IF($C67=V$10,IF(AND(ISNUMBER(SEARCH($M$2,$B67)),ISNUMBER(SEARCH($J$2,$B67))),1,""),"") | AC67: =+IF(AND(I2<>"AKİŞ",F2<>"GEARLESS"),1,"")
A68: =+'Pricing sheet'!A78 -> IT.25 | B68: =+'Pricing sheet'!B78 -> CHEVEILLE 12/100 | C68: =+'Pricing sheet'!C78 -> RAILS & ACCESSOIRES | D68: =+'Pricing sheet'!D78 -> Pc | E68: =+'Pricing sheet'!E78 -> 0.09 | F68: =+'Pricing sheet'!M78 -> 3.1989618 | G68: =+'Pricing sheet'!N78 -> 3.4047618 | H68: =+'Pricing sheet'!O78 -> 3.746733 | I68: =IF(SUM(S68:AC68)<>0,SUM(S68:AC68),"") | S68: =IF($C68=S$10,IF(AND(ISNUMBER(SEARCH($F$2,$B68)),ISNUMBER(SEARCH($N$2,$B68)),ISNUMBER(SEARCH($N$2,$B68))),1,""),"") | T68: =IF($C68=T$10,IF(AND(ISNUMBER(SEARCH($F$2,$B68)),ISNUMBER(SEARCH($N$2,$B68)),ISNUMBER(SEARCH($I$2,$B68))),1,""),"") | U68: =IF($C68=U$10,IF(AND(ISNUMBER(SEARCH($M$2,$B68)),ISNUMBER(SEARCH($L$2,$B68)),ISNUMBER(SEARCH($J$2,$B68)),ISNUMBER(SEARCH($K$2,$B68))),$H$2,""),"") | V68: =IF($C68=V$10,IF(AND(ISNUMBER(SEARCH($M$2,$B68)),ISNUMBER(SEARCH($J$2,$B68))),1,""),"")
A69: =+'Pricing sheet'!A79 -> IT.26 | B69: =+'Pricing sheet'!B79 -> GUIDE RAIL 50 | C69: =+'Pricing sheet'!C79 -> RAILS & ACCESSOIRES | D69: =+'Pricing sheet'!D79 -> Pc | E69: =+'Pricing sheet'!E79 -> 27 | F69: =+'Pricing sheet'!M79 -> 299.89406 | G69: =+'Pricing sheet'!N79 -> 316.94606 | H69: =+'Pricing sheet'!O79 -> 345.28225 | I69: =IF(SUM(S69:AC69)<>0,SUM(S69:AC69),"") | S69: =IF($C69=S$10,IF(AND(ISNUMBER(SEARCH($F$2,$B69)),ISNUMBER(SEARCH($N$2,$B69)),ISNUMBER(SEARCH($N$2,$B69))),1,""),"") | T69: =IF($C69=T$10,IF(AND(ISNUMBER(SEARCH($F$2,$B69)),ISNUMBER(SEARCH($N$2,$B69)),ISNUMBER(SEARCH($I$2,$B69))),1,""),"") | U69: =IF($C69=U$10,IF(AND(ISNUMBER(SEARCH($M$2,$B69)),ISNUMBER(SEARCH($L$2,$B69)),ISNUMBER(SEARCH($J$2,$B69)),ISNUMBER(SEARCH($K$2,$B69))),$H$2,""),"") | V69: =IF($C69=V$10,IF(AND(ISNUMBER(SEARCH($M$2,$B69)),ISNUMBER(SEARCH($J$2,$B69))),1,""),"")
A70: =+'Pricing sheet'!A80 -> IT.27 | B70: =+'Pricing sheet'!B80 -> GUIDE RAIL 70 | C70: =+'Pricing sheet'!C80 -> RAILS & ACCESSOIRES | D70: =+'Pricing sheet'!D80 -> Pc | E70: =+'Pricing sheet'!E80 -> 51 | F70: =+'Pricing sheet'!M80 -> 589.2634 | G70: =+'Pricing sheet'!N80 -> 623.1714 | H70: =+'Pricing sheet'!O80 -> 679.52094 | I70: =IF(SUM(S70:AC70)<>0,SUM(S70:AC70),"") -> 400 | S70: =IF($C70=S$10,IF(AND(ISNUMBER(SEARCH($F$2,$B70)),ISNUMBER(SEARCH($N$2,$B70)),ISNUMBER(SEARCH($N$2,$B70))),1,""),"") | T70: =IF($C70=T$10,IF(AND(ISNUMBER(SEARCH($F$2,$B70)),ISNUMBER(SEARCH($N$2,$B70)),ISNUMBER(SEARCH($I$2,$B70))),1,""),"") | U70: =IF($C70=U$10,IF(AND(ISNUMBER(SEARCH($M$2,$B70)),ISNUMBER(SEARCH($L$2,$B70)),ISNUMBER(SEARCH($J$2,$B70)),ISNUMBER(SEARCH($K$2,$B70))),$H$2,""),"") | V70: =IF($C70=V$10,IF(AND(ISNUMBER(SEARCH($M$2,$B70)),ISNUMBER(SEARCH($J$2,$B70))),1,""),"") | Z70: =+IF(H2>7,700,400) -> 400
A71: =+'Pricing sheet'!A81 -> IT.28 | B71: =+'Pricing sheet'!B81 -> SET RAIL : 50 + 70 | C71: =+'Pricing sheet'!C81 -> RAILS & ACCESSOIRES | D71: =+'Pricing sheet'!D81 -> SET | E71: =+'Pricing sheet'!E81 -> 0.36 | F71: =+'Pricing sheet'!M81 -> 787.02224 | G71: =+'Pricing sheet'!N81 -> 837.98224 | H71: =+'Pricing sheet'!O81 -> 922.67376 | I71: =IF(SUM(S71:AC71)<>0,SUM(S71:AC71),"") -> 200 | S71: =IF($C71=S$10,IF(AND(ISNUMBER(SEARCH($F$2,$B71)),ISNUMBER(SEARCH($N$2,$B71)),ISNUMBER(SEARCH($N$2,$B71))),1,""),"") | T71: =IF($C71=T$10,IF(AND(ISNUMBER(SEARCH($F$2,$B71)),ISNUMBER(SEARCH($N$2,$B71)),ISNUMBER(SEARCH($I$2,$B71))),1,""),"") | U71: =IF($C71=U$10,IF(AND(ISNUMBER(SEARCH($M$2,$B71)),ISNUMBER(SEARCH($L$2,$B71)),ISNUMBER(SEARCH($J$2,$B71)),ISNUMBER(SEARCH($K$2,$B71))),$H$2,""),"") | V71: =IF($C71=V$10,IF(AND(ISNUMBER(SEARCH($M$2,$B71)),ISNUMBER(SEARCH($J$2,$B71))),1,""),"") | Z71: 200
A72: =+'Pricing sheet'!A82 -> IT.29 | B72: =+'Pricing sheet'!B82 -> GUIDE RAIL 90 | C72: =+'Pricing sheet'!C82 -> RAILS & ACCESSOIRES | D72: =+'Pricing sheet'!D82 -> Pc | E72: =+'Pricing sheet'!E82 -> 0 | F72: =+'Pricing sheet'!M82 -> 983.78186 | G72: =+'Pricing sheet'!N82 -> 1047.4819 | H72: =+'Pricing sheet'!O82 -> 1153.3503 | I72: =IF(SUM(S72:AC72)<>0,SUM(S72:AC72),"") -> 100 | S72: =IF($C72=S$10,IF(AND(ISNUMBER(SEARCH($F$2,$B72)),ISNUMBER(SEARCH($N$2,$B72)),ISNUMBER(SEARCH($N$2,$B72))),1,""),"") | T72: =IF($C72=T$10,IF(AND(ISNUMBER(SEARCH($F$2,$B72)),ISNUMBER(SEARCH($N$2,$B72)),ISNUMBER(SEARCH($I$2,$B72))),1,""),"") | U72: =IF($C72=U$10,IF(AND(ISNUMBER(SEARCH($M$2,$B72)),ISNUMBER(SEARCH($L$2,$B72)),ISNUMBER(SEARCH($J$2,$B72)),ISNUMBER(SEARCH($K$2,$B72))),$H$2,""),"") | V72: =IF($C72=V$10,IF(AND(ISNUMBER(SEARCH($M$2,$B72)),ISNUMBER(SEARCH($J$2,$B72))),1,""),"") | Z72: 100
A73: =+'Pricing sheet'!A83 -> IT.30 | B73: =+'Pricing sheet'!B83 -> GARNITURE COULISSEAU 50 | C73: =+'Pricing sheet'!C83 -> RAILS & ACCESSOIRES | D73: =+'Pricing sheet'!D83 -> SET | E73: =+'Pricing sheet'!E83 -> 0.14 | F73: =+'Pricing sheet'!M83 -> 7.5673979 | G73: =+'Pricing sheet'!N83 -> 8.0573979 | H73: =+'Pricing sheet'!O83 -> 8.8716157 | I73: =IF(SUM(S73:AC73)<>0,SUM(S73:AC73),"") -> 30 | S73: =IF($C73=S$10,IF(AND(ISNUMBER(SEARCH($F$2,$B73)),ISNUMBER(SEARCH($N$2,$B73)),ISNUMBER(SEARCH($N$2,$B73))),1,""),"") | T73: =IF($C73=T$10,IF(AND(ISNUMBER(SEARCH($F$2,$B73)),ISNUMBER(SEARCH($N$2,$B73)),ISNUMBER(SEARCH($I$2,$B73))),1,""),"") | U73: =IF($C73=U$10,IF(AND(ISNUMBER(SEARCH($M$2,$B73)),ISNUMBER(SEARCH($L$2,$B73)),ISNUMBER(SEARCH($J$2,$B73)),ISNUMBER(SEARCH($K$2,$B73))),$H$2,""),"") | V73: =IF($C73=V$10,IF(AND(ISNUMBER(SEARCH($M$2,$B73)),ISNUMBER(SEARCH($J$2,$B73))),1,""),"") | Z73: =24+(H2-3)*3 -> 30
A74: =+'Pricing sheet'!A84 -> IT.31 | B74: =+'Pricing sheet'!B84 -> CABLE TRACTION (10mm) | C74: =+'Pricing sheet'!C84 -> CABLES & ACCESSOIRES | D74: =+'Pricing sheet'!D84 -> M | E74: =+'Pricing sheet'!E84 -> 0.4 | F74: =+'Pricing sheet'!M84 -> 13.924014 | G74: =+'Pricing sheet'!N84 -> 14.825614 | H74: =+'Pricing sheet'!O84 -> 16.323777 | I74: =IF(SUM(S74:AC74)<>0,SUM(S74:AC74),"") -> 3 | S74: =IF($C74=S$10,IF(AND(ISNUMBER(SEARCH($F$2,$B74)),ISNUMBER(SEARCH($N$2,$B74)),ISNUMBER(SEARCH($N$2,$B74))),1,""),"") | T74: =IF($C74=T$10,IF(AND(ISNUMBER(SEARCH($F$2,$B74)),ISNUMBER(SEARCH($N$2,$B74)),ISNUMBER(SEARCH($I$2,$B74))),1,""),"") | U74: =IF($C74=U$10,IF(AND(ISNUMBER(SEARCH($M$2,$B74)),ISNUMBER(SEARCH($L$2,$B74)),ISNUMBER(SEARCH($J$2,$B74)),ISNUMBER(SEARCH($K$2,$B74))),$H$2,""),"") | V74: =IF($C74=V$10,IF(AND(ISNUMBER(SEARCH($M$2,$B74)),ISNUMBER(SEARCH($J$2,$B74))),1,""),"") | Z74: =+IF(H2<8,3,4) -> 3
A75: =+'Pricing sheet'!A85 -> IT.32 | B75: =+'Pricing sheet'!B85 -> CABLE GEARLESS (6,5mm) | C75: =+'Pricing sheet'!C85 -> CABLES & ACCESSOIRES | D75: =+'Pricing sheet'!D85 -> M | E75: =+'Pricing sheet'!E85 -> 0 | F75: =+'Pricing sheet'!M85 -> 13.167274 | G75: =+'Pricing sheet'!N85 -> 14.019874 | H75: =+'Pricing sheet'!O85 -> 15.436614 | I75: =IF(SUM(S75:AC75)<>0,SUM(S75:AC75),"") -> 30 | S75: =IF($C75=S$10,IF(AND(ISNUMBER(SEARCH($F$2,$B75)),ISNUMBER(SEARCH($N$2,$B75)),ISNUMBER(SEARCH($N$2,$B75))),1,""),"") | T75: =IF($C75=T$10,IF(AND(ISNUMBER(SEARCH($F$2,$B75)),ISNUMBER(SEARCH($N$2,$B75)),ISNUMBER(SEARCH($I$2,$B75))),1,""),"") | U75: =IF($C75=U$10,IF(AND(ISNUMBER(SEARCH($M$2,$B75)),ISNUMBER(SEARCH($L$2,$B75)),ISNUMBER(SEARCH($J$2,$B75)),ISNUMBER(SEARCH($K$2,$B75))),$H$2,""),"") | V75: =IF($C75=V$10,IF(AND(ISNUMBER(SEARCH($M$2,$B75)),ISNUMBER(SEARCH($J$2,$B75))),1,""),"") | Z75: =+Z73 -> 30
A76: =+'Pricing sheet'!A86 -> IT.33 | B76: =+'Pricing sheet'!B86 -> CABLE REGULATEUR (6mm) | C76: =+'Pricing sheet'!C86 -> CABLES & ACCESSOIRES | D76: =+'Pricing sheet'!D86 -> 0 | E76: =+'Pricing sheet'!E86 -> 0.22 | F76: =+'Pricing sheet'!M86 -> 4.2612325 | G76: =+'Pricing sheet'!N86 -> 4.5356325 | H76: =+'Pricing sheet'!O86 -> 4.9915942 | I76: =IF(SUM(S76:AC76)<>0,SUM(S76:AC76),"") -> 50 | S76: =IF($C76=S$10,IF(AND(ISNUMBER(SEARCH($F$2,$B76)),ISNUMBER(SEARCH($N$2,$B76)),ISNUMBER(SEARCH($N$2,$B76))),1,""),"") | T76: =IF($C76=T$10,IF(AND(ISNUMBER(SEARCH($F$2,$B76)),ISNUMBER(SEARCH($N$2,$B76)),ISNUMBER(SEARCH($I$2,$B76))),1,""),"") | U76: =IF($C76=U$10,IF(AND(ISNUMBER(SEARCH($M$2,$B76)),ISNUMBER(SEARCH($L$2,$B76)),ISNUMBER(SEARCH($J$2,$B76)),ISNUMBER(SEARCH($K$2,$B76))),$H$2,""),"") | V76: =IF($C76=V$10,IF(AND(ISNUMBER(SEARCH($M$2,$B76)),ISNUMBER(SEARCH($J$2,$B76))),1,""),"") | Z76: 50
A77: =+'Pricing sheet'!A87 -> IT.34 | B77: =+'Pricing sheet'!B87 -> TIRANDS 10MM | C77: =+'Pricing sheet'!C87 -> CABLES & ACCESSOIRES | D77: =+'Pricing sheet'!D87 -> Pc | E77: =+'Pricing sheet'!E87 -> 1.09 | F77: =+'Pricing sheet'!M87 -> 33.570553 | G77: =+'Pricing sheet'!N87 -> 35.677553 | H77: =+'Pricing sheet'!O87 -> 39.178707 | I77: =IF(SUM(S77:AC77)<>0,SUM(S77:AC77),"") -> 1 | S77: =IF($C77=S$10,IF(AND(ISNUMBER(SEARCH($F$2,$B77)),ISNUMBER(SEARCH($N$2,$B77)),ISNUMBER(SEARCH($N$2,$B77))),1,""),"") | T77: =IF($C77=T$10,IF(AND(ISNUMBER(SEARCH($F$2,$B77)),ISNUMBER(SEARCH($N$2,$B77)),ISNUMBER(SEARCH($I$2,$B77))),1,""),"") | U77: =IF($C77=U$10,IF(AND(ISNUMBER(SEARCH($M$2,$B77)),ISNUMBER(SEARCH($L$2,$B77)),ISNUMBER(SEARCH($J$2,$B77)),ISNUMBER(SEARCH($K$2,$B77))),$H$2,""),"") | V77: =IF($C77=V$10,IF(AND(ISNUMBER(SEARCH($M$2,$B77)),ISNUMBER(SEARCH($J$2,$B77))),1,""),"") | AA77: 1
A78: =+'Pricing sheet'!A88 -> IT.35 | B78: =+'Pricing sheet'!B88 -> TIRANDS 6,5MM | C78: =+'Pricing sheet'!C88 -> CABLES & ACCESSOIRES | D78: =+'Pricing sheet'!D88 -> Pc | E78: =+'Pricing sheet'!E88 -> 0 | F78: =+'Pricing sheet'!M88 -> 32.539828 | G78: =+'Pricing sheet'!N88 -> 34.646828 | H78: =+'Pricing sheet'!O88 -> 38.147982 | I78: =IF(SUM(S78:AC78)<>0,SUM(S78:AC78),"") | S78: =IF($C78=S$10,IF(AND(ISNUMBER(SEARCH($F$2,$B78)),ISNUMBER(SEARCH($N$2,$B78)),ISNUMBER(SEARCH($N$2,$B78))),1,""),"") | T78: =IF($C78=T$10,IF(AND(ISNUMBER(SEARCH($F$2,$B78)),ISNUMBER(SEARCH($N$2,$B78)),ISNUMBER(SEARCH($I$2,$B78))),1,""),"") | U78: =IF($C78=U$10,IF(AND(ISNUMBER(SEARCH($M$2,$B78)),ISNUMBER(SEARCH($L$2,$B78)),ISNUMBER(SEARCH($J$2,$B78)),ISNUMBER(SEARCH($K$2,$B78))),$H$2,""),"") | V78: =IF($C78=V$10,IF(AND(ISNUMBER(SEARCH($M$2,$B78)),ISNUMBER(SEARCH($J$2,$B78))),1,""),"")
A79: =+'Pricing sheet'!A89 -> IT.36 | B79: =+'Pricing sheet'!B89 -> SERRE CABLE DIAM 10mm * | C79: =+'Pricing sheet'!C89 -> CABLES & ACCESSOIRES | D79: =+'Pricing sheet'!D89 -> Pc | E79: =+'Pricing sheet'!E89 -> 0.07 | F79: =+'Pricing sheet'!M89 -> 3.0269589 | G79: =+'Pricing sheet'!N89 -> 3.2229589 | H79: =+'Pricing sheet'!O89 -> 3.5486457 | I79: =IF(SUM(S79:AC79)<>0,SUM(S79:AC79),"") -> 5 | S79: =IF($C79=S$10,IF(AND(ISNUMBER(SEARCH($F$2,$B79)),ISNUMBER(SEARCH($N$2,$B79)),ISNUMBER(SEARCH($N$2,$B79))),1,""),"") | T79: =IF($C79=T$10,IF(AND(ISNUMBER(SEARCH($F$2,$B79)),ISNUMBER(SEARCH($N$2,$B79)),ISNUMBER(SEARCH($I$2,$B79))),1,""),"") | U79: =IF($C79=U$10,IF(AND(ISNUMBER(SEARCH($M$2,$B79)),ISNUMBER(SEARCH($L$2,$B79)),ISNUMBER(SEARCH($J$2,$B79)),ISNUMBER(SEARCH($K$2,$B79))),$H$2,""),"") | V79: =IF($C79=V$10,IF(AND(ISNUMBER(SEARCH($M$2,$B79)),ISNUMBER(SEARCH($J$2,$B79))),1,""),"") | AA79: =+H2 -> 5
A80: =+'Pricing sheet'!A90 -> IT.37 | B80: =+'Pricing sheet'!B90 -> SERRE CABLE DIAM 6,5mm * | C80: =+'Pricing sheet'!C90 -> CABLES & ACCESSOIRES | D80: =+'Pricing sheet'!D90 -> 0 | E80: =+'Pricing sheet'!E90 -> 0 | F80: =+'Pricing sheet'!M90 -> 2.2702191 | G80: =+'Pricing sheet'!N90 -> 2.4172191 | H80: =+'Pricing sheet'!O90 -> 2.6614842 | I80: =IF(SUM(S80:AC80)<>0,SUM(S80:AC80),"") | S80: =IF($C80=S$10,IF(AND(ISNUMBER(SEARCH($F$2,$B80)),ISNUMBER(SEARCH($N$2,$B80)),ISNUMBER(SEARCH($N$2,$B80))),1,""),"") | T80: =IF($C80=T$10,IF(AND(ISNUMBER(SEARCH($F$2,$B80)),ISNUMBER(SEARCH($N$2,$B80)),ISNUMBER(SEARCH($I$2,$B80))),1,""),"") | U80: =IF($C80=U$10,IF(AND(ISNUMBER(SEARCH($M$2,$B80)),ISNUMBER(SEARCH($L$2,$B80)),ISNUMBER(SEARCH($J$2,$B80)),ISNUMBER(SEARCH($K$2,$B80))),$H$2,""),"") | V80: =IF($C80=V$10,IF(AND(ISNUMBER(SEARCH($M$2,$B80)),ISNUMBER(SEARCH($J$2,$B80))),1,""),"")
A81: =+'Pricing sheet'!A91 -> IT.38 | B81: =+'Pricing sheet'!B91 -> SERRE CABLE DIAM 6mm * | C81: =+'Pricing sheet'!C91 -> CABLES & ACCESSOIRES | D81: =+'Pricing sheet'!D91 -> Pc | E81: =+'Pricing sheet'!E91 -> 0.01 | F81: =+'Pricing sheet'!M91 -> 1.5134794 | G81: =+'Pricing sheet'!N91 -> 1.6114794 | H81: =+'Pricing sheet'!O91 -> 1.7743228 | I81: =IF(SUM(S81:AC81)<>0,SUM(S81:AC81),"") | S81: =IF($C81=S$10,IF(AND(ISNUMBER(SEARCH($F$2,$B81)),ISNUMBER(SEARCH($N$2,$B81)),ISNUMBER(SEARCH($N$2,$B81))),1,""),"") | T81: =IF($C81=T$10,IF(AND(ISNUMBER(SEARCH($F$2,$B81)),ISNUMBER(SEARCH($N$2,$B81)),ISNUMBER(SEARCH($I$2,$B81))),1,""),"") | U81: =IF($C81=U$10,IF(AND(ISNUMBER(SEARCH($M$2,$B81)),ISNUMBER(SEARCH($L$2,$B81)),ISNUMBER(SEARCH($J$2,$B81)),ISNUMBER(SEARCH($K$2,$B81))),$H$2,""),"") | V81: =IF($C81=V$10,IF(AND(ISNUMBER(SEARCH($M$2,$B81)),ISNUMBER(SEARCH($J$2,$B81))),1,""),"")
A82: =+'Pricing sheet'!A92 -> IT.39 | B82: =+'Pricing sheet'!B92 -> GOSE 96 CM (50 KG) | C82: =+'Pricing sheet'!C92 -> GOSE | D82: =+'Pricing sheet'!D92 -> Pc | E82: =+'Pricing sheet'!E92 -> 50 | F82: =+'Pricing sheet'!M92 -> 90.808933 | G82: =+'Pricing sheet'!N92 -> 96.688933 | H82: =+'Pricing sheet'!O92 -> 106.45971 | I82: =IF(SUM(S82:AC82)<>0,SUM(S82:AC82),"") -> 3 | S82: =IF($C82=S$10,IF(AND(ISNUMBER(SEARCH($F$2,$B82)),ISNUMBER(SEARCH($N$2,$B82)),ISNUMBER(SEARCH($N$2,$B82))),1,""),"") | T82: =IF($C82=T$10,IF(AND(ISNUMBER(SEARCH($F$2,$B82)),ISNUMBER(SEARCH($N$2,$B82)),ISNUMBER(SEARCH($I$2,$B82))),1,""),"") | U82: =IF($C82=U$10,IF(AND(ISNUMBER(SEARCH($M$2,$B82)),ISNUMBER(SEARCH($L$2,$B82)),ISNUMBER(SEARCH($J$2,$B82)),ISNUMBER(SEARCH($K$2,$B82))),$H$2,""),"") | V82: =IF($C82=V$10,IF(AND(ISNUMBER(SEARCH($M$2,$B82)),ISNUMBER(SEARCH($J$2,$B82))),1,""),"") | AC82: 3
A83: =+'Pricing sheet'!A93 -> IT.40 | B83: =+'Pricing sheet'!B93 -> COLLECTEUR D'HUILE | C83: =+'Pricing sheet'!C93 -> AUTRES | D83: =+'Pricing sheet'!D93 -> Pc | E83: =+'Pricing sheet'!E93 -> 0.07 | F83: =+'Pricing sheet'!M93 -> 3.7836986 | G83: =+'Pricing sheet'!N93 -> 4.0286986 | H83: =+'Pricing sheet'!O93 -> 4.4358073 | I83: =IF(SUM(S83:AC83)<>0,SUM(S83:AC83),"") | S83: =IF($C83=S$10,IF(AND(ISNUMBER(SEARCH($F$2,$B83)),ISNUMBER(SEARCH($N$2,$B83)),ISNUMBER(SEARCH($N$2,$B83))),1,""),"") | T83: =IF($C83=T$10,IF(AND(ISNUMBER(SEARCH($F$2,$B83)),ISNUMBER(SEARCH($N$2,$B83)),ISNUMBER(SEARCH($I$2,$B83))),1,""),"") | U83: =IF($C83=U$10,IF(AND(ISNUMBER(SEARCH($M$2,$B83)),ISNUMBER(SEARCH($L$2,$B83)),ISNUMBER(SEARCH($J$2,$B83)),ISNUMBER(SEARCH($K$2,$B83))),$H$2,""),"") | V83: =IF($C83=V$10,IF(AND(ISNUMBER(SEARCH($M$2,$B83)),ISNUMBER(SEARCH($J$2,$B83))),1,""),"")
A84: =+'Pricing sheet'!A94 -> IT.41 | B84: =+'Pricing sheet'!B94 -> BOITE DE LUBRIFICATION | C84: =+'Pricing sheet'!C94 -> AUTRES | D84: =+'Pricing sheet'!D94 -> Pc | E84: =+'Pricing sheet'!E94 -> 0.3 | F84: =+'Pricing sheet'!M94 -> 15.134798 | G84: =+'Pricing sheet'!N94 -> 16.114798 | H84: =+'Pricing sheet'!O94 -> 17.743236 | I84: =IF(SUM(S84:AC84)<>0,SUM(S84:AC84),"") -> 1 | S84: =IF($C84=S$10,IF(AND(ISNUMBER(SEARCH($F$2,$B84)),ISNUMBER(SEARCH($N$2,$B84)),ISNUMBER(SEARCH($N$2,$B84))),1,""),"") | T84: =IF($C84=T$10,IF(AND(ISNUMBER(SEARCH($F$2,$B84)),ISNUMBER(SEARCH($N$2,$B84)),ISNUMBER(SEARCH($I$2,$B84))),1,""),"") | U84: =IF($C84=U$10,IF(AND(ISNUMBER(SEARCH($M$2,$B84)),ISNUMBER(SEARCH($L$2,$B84)),ISNUMBER(SEARCH($J$2,$B84)),ISNUMBER(SEARCH($K$2,$B84))),$H$2,""),"") | V84: =IF($C84=V$10,IF(AND(ISNUMBER(SEARCH($M$2,$B84)),ISNUMBER(SEARCH($J$2,$B84))),1,""),"") | AC84: 1
A85: =+'Pricing sheet'!A95 -> IT.42 | B85: =+'Pricing sheet'!B95 -> COULISSEAUX CABIN | C85: =+'Pricing sheet'!C95 -> AUTRES | D85: =+'Pricing sheet'!D95 -> Pc | E85: =+'Pricing sheet'!E95 -> 1 | F85: =+'Pricing sheet'!M95 -> 90.808933 | G85: =+'Pricing sheet'!N95 -> 96.688933 | H85: =+'Pricing sheet'!O95 -> 106.45971 | I85: =IF(SUM(S85:AC85)<>0,SUM(S85:AC85),"") -> 1 | S85: =IF($C85=S$10,IF(AND(ISNUMBER(SEARCH($F$2,$B85)),ISNUMBER(SEARCH($N$2,$B85)),ISNUMBER(SEARCH($N$2,$B85))),1,""),"") | T85: =IF($C85=T$10,IF(AND(ISNUMBER(SEARCH($F$2,$B85)),ISNUMBER(SEARCH($N$2,$B85)),ISNUMBER(SEARCH($I$2,$B85))),1,""),"") | U85: =IF($C85=U$10,IF(AND(ISNUMBER(SEARCH($M$2,$B85)),ISNUMBER(SEARCH($L$2,$B85)),ISNUMBER(SEARCH($J$2,$B85)),ISNUMBER(SEARCH($K$2,$B85))),$H$2,""),"") | V85: =IF($C85=V$10,IF(AND(ISNUMBER(SEARCH($M$2,$B85)),ISNUMBER(SEARCH($J$2,$B85))),1,""),"") | AC85: 1
A86: =+'Pricing sheet'!A96 -> IT.43 | B86: =+'Pricing sheet'!B96 -> COULISSEAUX CONTRE-POIDS | C86: =+'Pricing sheet'!C96 -> AUTRES | D86: =+'Pricing sheet'!D96 -> Pc | E86: =+'Pricing sheet'!E96 -> 0.6 | F86: =+'Pricing sheet'!M96 -> 52.971835 | G86: =+'Pricing sheet'!N96 -> 56.401835 | H86: =+'Pricing sheet'!O96 -> 62.101411 | I86: =IF(SUM(S86:AC86)<>0,SUM(S86:AC86),"") -> 1 | S86: =IF($C86=S$10,IF(AND(ISNUMBER(SEARCH($F$2,$B86)),ISNUMBER(SEARCH($N$2,$B86)),ISNUMBER(SEARCH($N$2,$B86))),1,""),"") | U86: =IF($C86=U$10,IF(AND(ISNUMBER(SEARCH($M$2,$B86)),ISNUMBER(SEARCH($L$2,$B86)),ISNUMBER(SEARCH($J$2,$B86)),ISNUMBER(SEARCH($K$2,$B86))),$H$2,""),"") | V86: =IF($C86=V$10,IF(AND(ISNUMBER(SEARCH($M$2,$B86)),ISNUMBER(SEARCH($J$2,$B86))),1,""),"") | AC86: 1
A87: =+'Pricing sheet'!A97 -> IT.44 | B87: =+'Pricing sheet'!B97 -> GARNITURE COULISSEAU 70 | C87: =+'Pricing sheet'!C97 -> AUTRES | D87: =+'Pricing sheet'!D97 -> Pc | E87: =+'Pricing sheet'!E97 -> 0.14 | F87: =+'Pricing sheet'!M97 -> 7.5673979 | G87: =+'Pricing sheet'!N97 -> 8.0573979 | H87: =+'Pricing sheet'!O97 -> 8.8716157 | I87: =IF(SUM(S87:AC87)<>0,SUM(S87:AC87),"") | S87: =IF($C87=S$10,IF(AND(ISNUMBER(SEARCH($F$2,$B87)),ISNUMBER(SEARCH($N$2,$B87)),ISNUMBER(SEARCH($N$2,$B87))),1,""),"") | U87: =IF($C87=U$10,IF(AND(ISNUMBER(SEARCH($M$2,$B87)),ISNUMBER(SEARCH($L$2,$B87)),ISNUMBER(SEARCH($J$2,$B87)),ISNUMBER(SEARCH($K$2,$B87))),$H$2,""),"") | V87: =IF($C87=V$10,IF(AND(ISNUMBER(SEARCH($M$2,$B87)),ISNUMBER(SEARCH($J$2,$B87))),1,""),"")
A88: =+'Pricing sheet'!A98 -> IT.45 | B88: =+'Pricing sheet'!B98 -> POULIE RENVOI 5*10 GEARBOX | C88: =+'Pricing sheet'!C98 -> AUTRES | D88: =+'Pricing sheet'!D98 -> Pc | E88: =+'Pricing sheet'!E98 -> 20 | F88: =+'Pricing sheet'!M98 -> #REF! | G88: =+'Pricing sheet'!N98 -> #REF! | H88: =+'Pricing sheet'!O98 -> #REF! | I88: =IF(SUM(S88:AC88)<>0,SUM(S88:AC88),"") | S88: =IF($C88=S$10,IF(AND(ISNUMBER(SEARCH($F$2,$B88)),ISNUMBER(SEARCH($N$2,$B88)),ISNUMBER(SEARCH($N$2,$B88))),1,""),"") | U88: =IF($C88=U$10,IF(AND(ISNUMBER(SEARCH($M$2,$B88)),ISNUMBER(SEARCH($L$2,$B88)),ISNUMBER(SEARCH($J$2,$B88)),ISNUMBER(SEARCH($K$2,$B88))),$H$2,""),"") | V88: =IF($C88=V$10,IF(AND(ISNUMBER(SEARCH($M$2,$B88)),ISNUMBER(SEARCH($J$2,$B88))),1,""),"")
A89: =+'Pricing sheet'!A99 -> IT.46 | B89: =+'Pricing sheet'!B99 -> BUFFER CABIN/C,P / LES BOUDINS SET COMPLET | C89: =+'Pricing sheet'!C99 -> AUTRES | D89: =+'Pricing sheet'!D99 -> SET | E89: =+'Pricing sheet'!E99 -> 22 | F89: =+'Pricing sheet'!M99 -> 540.88491 | G89: =+'Pricing sheet'!N99 -> 573.22491 | H89: =+'Pricing sheet'!O99 -> 626.96844 | I89: =IF(SUM(S89:AC89)<>0,SUM(S89:AC89),"") -> 1 | S89: =IF($C89=S$10,IF(AND(ISNUMBER(SEARCH($F$2,$B89)),ISNUMBER(SEARCH($N$2,$B89)),ISNUMBER(SEARCH($N$2,$B89))),1,""),"") | U89: =IF($C89=U$10,IF(AND(ISNUMBER(SEARCH($M$2,$B89)),ISNUMBER(SEARCH($L$2,$B89)),ISNUMBER(SEARCH($J$2,$B89)),ISNUMBER(SEARCH($K$2,$B89))),$H$2,""),"") | V89: =IF($C89=V$10,IF(AND(ISNUMBER(SEARCH($M$2,$B89)),ISNUMBER(SEARCH($J$2,$B89))),1,""),"") | AC89: =IF(F2="2V","",1) -> 1
A90: =+'Pricing sheet'!A100 -> IT.47 | B90: =+'Pricing sheet'!B100 -> CABLE 0,75MM | C90: =+'Pricing sheet'!C100 -> CABLES ELECTRIQUES & ACCESSOIRES | D90: =+'Pricing sheet'!D100 -> M | E90: =+'Pricing sheet'!E100 -> 0.02 | F90: =+'Pricing sheet'!M100 -> 0.54545675 | G90: =+'Pricing sheet'!N100 -> 0.56799675 | H90: =+'Pricing sheet'!O100 -> 0.60545072 | I90: =IF(SUM(S90:AC90)<>0,SUM(S90:AC90),"") | S90: =IF($C90=S$10,IF(AND(ISNUMBER(SEARCH($F$2,$B90)),ISNUMBER(SEARCH($N$2,$B90)),ISNUMBER(SEARCH($N$2,$B90))),1,""),"") | U90: =IF($C90=U$10,IF(AND(ISNUMBER(SEARCH($M$2,$B90)),ISNUMBER(SEARCH($L$2,$B90)),ISNUMBER(SEARCH($J$2,$B90)),ISNUMBER(SEARCH($K$2,$B90))),$H$2,""),"") | V90: =IF($C90=V$10,IF(AND(ISNUMBER(SEARCH($M$2,$B90)),ISNUMBER(SEARCH($J$2,$B90))),1,""),"") | AC90: =IF(F2="2V",1,"")
A91: =+'Pricing sheet'!A101 -> IT.48 | B91: =+'Pricing sheet'!B101 -> CABLE 4MM | C91: =+'Pricing sheet'!C101 -> CABLES ELECTRIQUES & ACCESSOIRES | D91: =+'Pricing sheet'!D101 -> M | E91: =+'Pricing sheet'!E101 -> 0.03 | F91: =+'Pricing sheet'!M101 -> 1.7715814 | G91: =+'Pricing sheet'!N101 -> 1.8764414 | H91: =+'Pricing sheet'!O101 -> 2.0506839 | I91: =IF(SUM(S91:AC91)<>0,SUM(S91:AC91),"") | S91: =IF($C91=S$10,IF(AND(ISNUMBER(SEARCH($F$2,$B91)),ISNUMBER(SEARCH($N$2,$B91)),ISNUMBER(SEARCH($N$2,$B91))),1,""),"") | U91: =IF($C91=U$10,IF(AND(ISNUMBER(SEARCH($M$2,$B91)),ISNUMBER(SEARCH($L$2,$B91)),ISNUMBER(SEARCH($J$2,$B91)),ISNUMBER(SEARCH($K$2,$B91))),$H$2,""),"") | V91: =IF($C91=V$10,IF(AND(ISNUMBER(SEARCH($M$2,$B91)),ISNUMBER(SEARCH($J$2,$B91))),1,""),"")
A92: =+'Pricing sheet'!A102 -> IT.49 | B92: =+'Pricing sheet'!B102 -> CÂBLE NUMÉRIQUE DT/13 | C92: =+'Pricing sheet'!C102 -> CABLES ELECTRIQUES & ACCESSOIRES | D92: =+'Pricing sheet'!D102 -> M | E92: =+'Pricing sheet'!E102 -> 0.04 | F92: =+'Pricing sheet'!M102 -> 2.0903359 | G92: =+'Pricing sheet'!N102 -> 2.2098959 | H92: =+'Pricing sheet'!O102 -> 2.4085648 | I92: =IF(SUM(S92:AC92)<>0,SUM(S92:AC92),"") | S92: =IF($C92=S$10,IF(AND(ISNUMBER(SEARCH($F$2,$B92)),ISNUMBER(SEARCH($N$2,$B92)),ISNUMBER(SEARCH($N$2,$B92))),1,""),"") | U92: =IF($C92=U$10,IF(AND(ISNUMBER(SEARCH($M$2,$B92)),ISNUMBER(SEARCH($L$2,$B92)),ISNUMBER(SEARCH($J$2,$B92)),ISNUMBER(SEARCH($K$2,$B92))),$H$2,""),"") | V92: =IF($C92=V$10,IF(AND(ISNUMBER(SEARCH($M$2,$B92)),ISNUMBER(SEARCH($J$2,$B92))),1,""),"")
A93: =+'Pricing sheet'!A103 -> IT.50 | B93: =+'Pricing sheet'!B103 -> TTR CABLE 3*0,75MM | C93: =+'Pricing sheet'!C103 -> CABLES ELECTRIQUES & ACCESSOIRES | D93: =+'Pricing sheet'!D103 -> M | E93: =+'Pricing sheet'!E103 -> 0.05 | F93: =+'Pricing sheet'!M103 -> 2.4090903 | G93: =+'Pricing sheet'!N103 -> 2.5433503 | H93: =+'Pricing sheet'!O103 -> 2.7664457 | I93: =IF(SUM(S93:AC93)<>0,SUM(S93:AC93),"") | S93: =IF($C93=S$10,IF(AND(ISNUMBER(SEARCH($F$2,$B93)),ISNUMBER(SEARCH($N$2,$B93)),ISNUMBER(SEARCH($N$2,$B93))),1,""),"") | U93: =IF($C93=U$10,IF(AND(ISNUMBER(SEARCH($M$2,$B93)),ISNUMBER(SEARCH($L$2,$B93)),ISNUMBER(SEARCH($J$2,$B93)),ISNUMBER(SEARCH($K$2,$B93))),$H$2,""),"") | V93: =IF($C93=V$10,IF(AND(ISNUMBER(SEARCH($M$2,$B93)),ISNUMBER(SEARCH($J$2,$B93))),1,""),"")
A94: =+'Pricing sheet'!A104 -> IT.51 | B94: =+'Pricing sheet'!B104 -> CABLE SOUPLE 24 36 -> 75 DH / 24 -> 55 À 60 DH | C94: =+'Pricing sheet'!C104 -> CABLES ELECTRIQUES & ACCESSOIRES | D94: =+'Pricing sheet'!D104 -> M | E94: =+'Pricing sheet'!E104 -> 1.2 | F94: =+'Pricing sheet'!M104 -> 34.874859 | G94: =+'Pricing sheet'!N104 -> 36.387293 | H94: =+'Pricing sheet'!O104 -> 38.900466 | I94: =IF(SUM(S94:AC94)<>0,SUM(S94:AC94),"") | S94: =IF($C94=S$10,IF(AND(ISNUMBER(SEARCH($F$2,$B94)),ISNUMBER(SEARCH($N$2,$B94)),ISNUMBER(SEARCH($N$2,$B94))),1,""),"") | U94: =IF($C94=U$10,IF(AND(ISNUMBER(SEARCH($M$2,$B94)),ISNUMBER(SEARCH($L$2,$B94)),ISNUMBER(SEARCH($J$2,$B94)),ISNUMBER(SEARCH($K$2,$B94))),$H$2,""),"") | V94: =IF($C94=V$10,IF(AND(ISNUMBER(SEARCH($M$2,$B94)),ISNUMBER(SEARCH($J$2,$B94))),1,""),"")
A95: =+'Pricing sheet'!A105 -> IT.52 | B95: =+'Pricing sheet'!B105 -> SUPPORT CABLE SOUPLE TYPE RECTANGLE | C95: =+'Pricing sheet'!C105 -> CABLES ELECTRIQUES & ACCESSOIRES | D95: =+'Pricing sheet'!D105 -> M | E95: =+'Pricing sheet'!E105 -> 0.3 | F95: =+'Pricing sheet'!M105 -> 14.165238 | G95: =+'Pricing sheet'!N105 -> 14.949238 | H95: =+'Pricing sheet'!O105 -> 16.251987 | I95: =IF(SUM(S95:AC95)<>0,SUM(S95:AC95),"") -> 1 | S95: =IF($C95=S$10,IF(AND(ISNUMBER(SEARCH($F$2,$B95)),ISNUMBER(SEARCH($N$2,$B95)),ISNUMBER(SEARCH($N$2,$B95))),1,""),"") | U95: =IF($C95=U$10,IF(AND(ISNUMBER(SEARCH($M$2,$B95)),ISNUMBER(SEARCH($L$2,$B95)),ISNUMBER(SEARCH($J$2,$B95)),ISNUMBER(SEARCH($K$2,$B95))),$H$2,""),"") | V95: =IF($C95=V$10,IF(AND(ISNUMBER(SEARCH($M$2,$B95)),ISNUMBER(SEARCH($J$2,$B95))),1,""),"") | AC95: 1
A96: =+'Pricing sheet'!A106 -> IT.53 | B96: =+'Pricing sheet'!B106 -> WIRE DUCT GOULLOTTE 40X40 | C96: =+'Pricing sheet'!C106 -> CABLES ELECTRIQUES & ACCESSOIRES | D96: =+'Pricing sheet'!D106 -> M | E96: =+'Pricing sheet'!E106 -> 0.5 | F96: =+'Pricing sheet'!M106 -> 11.335118 | G96: =+'Pricing sheet'!N106 -> 11.727118 | H96: =+'Pricing sheet'!O106 -> 12.378492 | I96: =IF(SUM(S96:AC96)<>0,SUM(S96:AC96),"") -> 1 | S96: =IF($C96=S$10,IF(AND(ISNUMBER(SEARCH($F$2,$B96)),ISNUMBER(SEARCH($N$2,$B96)),ISNUMBER(SEARCH($N$2,$B96))),1,""),"") | U96: =IF($C96=U$10,IF(AND(ISNUMBER(SEARCH($M$2,$B96)),ISNUMBER(SEARCH($L$2,$B96)),ISNUMBER(SEARCH($J$2,$B96)),ISNUMBER(SEARCH($K$2,$B96))),$H$2,""),"") | V96: =IF($C96=V$10,IF(AND(ISNUMBER(SEARCH($M$2,$B96)),ISNUMBER(SEARCH($J$2,$B96))),1,""),"") | AC96: =IF(I2<>"PRIMO",1,"") -> 1
A97: =+'Pricing sheet'!A107 -> IT.54 | B97: =+'Pricing sheet'!B107 -> TUBE SPIRALÉ 14MM | C97: =+'Pricing sheet'!C107 -> CABLES ELECTRIQUES & ACCESSOIRES | D97: =+'Pricing sheet'!D107 -> M | E97: =+'Pricing sheet'!E107 -> 1 | F97: =+'Pricing sheet'!M107 -> 13.333526 | G97: =+'Pricing sheet'!N107 -> 13.421726 | H97: =+'Pricing sheet'!O107 -> 13.568285 | I97: =IF(SUM(S97:AC97)<>0,SUM(S97:AC97),"") | S97: =IF($C97=S$10,IF(AND(ISNUMBER(SEARCH($F$2,$B97)),ISNUMBER(SEARCH($N$2,$B97)),ISNUMBER(SEARCH($N$2,$B97))),1,""),"") | U97: =IF($C97=U$10,IF(AND(ISNUMBER(SEARCH($M$2,$B97)),ISNUMBER(SEARCH($L$2,$B97)),ISNUMBER(SEARCH($J$2,$B97)),ISNUMBER(SEARCH($K$2,$B97))),$H$2,""),"") | V97: =IF($C97=V$10,IF(AND(ISNUMBER(SEARCH($M$2,$B97)),ISNUMBER(SEARCH($J$2,$B97))),1,""),"")
A98: =+'Pricing sheet'!A108 -> IT.55 | B98: =+'Pricing sheet'!B108 -> BOUTONS DE CABINE D’ASCENSEUR 2M | C98: =+'Pricing sheet'!C108 -> BOUTONS | D98: =+'Pricing sheet'!D108 -> Pc | E98: =+'Pricing sheet'!E108 -> 1.8 | F98: =+'Pricing sheet'!M108 -> 1437.8487 | G98: =+'Pricing sheet'!N108 -> 1530.9487 | H98: =+'Pricing sheet'!O108 -> 1685.6932 | I98: =IF(SUM(S98:AC98)<>0,SUM(S98:AC98),"") | S98: =IF($C98=S$10,IF(AND(ISNUMBER(SEARCH($F$2,$B98)),ISNUMBER(SEARCH($N$2,$B98)),ISNUMBER(SEARCH($N$2,$B98))),1,""),"") | U98: =IF($C98=U$10,IF(AND(ISNUMBER(SEARCH($M$2,$B98)),ISNUMBER(SEARCH($L$2,$B98)),ISNUMBER(SEARCH($J$2,$B98)),ISNUMBER(SEARCH($K$2,$B98))),$H$2,""),"") | V98: =IF($C98=V$10,IF(AND(ISNUMBER(SEARCH($M$2,$B98)),ISNUMBER(SEARCH($J$2,$B98))),1,""),"")
A99: =+'Pricing sheet'!A109 -> IT.56 | B99: =+'Pricing sheet'!B109 -> BOUTONS DE CABINE D’ASCENSEUR 1M | C99: =+'Pricing sheet'!C109 -> BOUTONS | D99: =+'Pricing sheet'!D109 -> Pc | E99: =+'Pricing sheet'!E109 -> 1.2 | F99: =+'Pricing sheet'!M109 -> 1210.8142 | G99: =+'Pricing sheet'!N109 -> 1289.2142 | H99: =+'Pricing sheet'!O109 -> 1419.5196 | I99: =IF(SUM(S99:AC99)<>0,SUM(S99:AC99),"") | S99: =IF($C99=S$10,IF(AND(ISNUMBER(SEARCH($F$2,$B99)),ISNUMBER(SEARCH($N$2,$B99)),ISNUMBER(SEARCH($N$2,$B99))),1,""),"") | U99: =IF($C99=U$10,IF(AND(ISNUMBER(SEARCH($M$2,$B99)),ISNUMBER(SEARCH($L$2,$B99)),ISNUMBER(SEARCH($J$2,$B99)),ISNUMBER(SEARCH($K$2,$B99))),$H$2,""),"") | V99: =IF($C99=V$10,IF(AND(ISNUMBER(SEARCH($M$2,$B99)),ISNUMBER(SEARCH($J$2,$B99))),1,""),"")
A100: =+'Pricing sheet'!A110 -> IT.57 | B100: =+'Pricing sheet'!B110 -> BOUTON PALIER AVEC AFFICHEUR | C100: =+'Pricing sheet'!C110 -> BOUTONS | D100: =+'Pricing sheet'!D110 -> Pc | E100: =+'Pricing sheet'!E110 -> 1.5 | F100: =+'Pricing sheet'!M110 -> 96.862874 | G100: =+'Pricing sheet'!N110 -> 103.13487 | H100: =+'Pricing sheet'!O110 -> 113.55704 | I100: =IF(SUM(S100:AC100)<>0,SUM(S100:AC100),"") | S100: =IF($C100=S$10,IF(AND(ISNUMBER(SEARCH($F$2,$B100)),ISNUMBER(SEARCH($N$2,$B100)),ISNUMBER(SEARCH($N$2,$B100))),1,""),"") | U100: =IF($C100=U$10,IF(AND(ISNUMBER(SEARCH($M$2,$B100)),ISNUMBER(SEARCH($L$2,$B100)),ISNUMBER(SEARCH($J$2,$B100)),ISNUMBER(SEARCH($K$2,$B100))),$H$2,""),"") | V100: =IF($C100=V$10,IF(AND(ISNUMBER(SEARCH($M$2,$B100)),ISNUMBER(SEARCH($J$2,$B100))),1,""),"")
A101: =+'Pricing sheet'!A111 -> IT.58 | B101: =+'Pricing sheet'!B111 -> BOUTON PALIER | C101: =+'Pricing sheet'!C111 -> BOUTONS | D101: =+'Pricing sheet'!D111 -> Pc | E101: =+'Pricing sheet'!E111 -> 1 | F101: =+'Pricing sheet'!M111 -> 62.052733 | G101: =+'Pricing sheet'!N111 -> 66.070733 | H101: =+'Pricing sheet'!O111 -> 72.747391 | I101: =IF(SUM(S101:AC101)<>0,SUM(S101:AC101),"") | S101: =IF($C101=S$10,IF(AND(ISNUMBER(SEARCH($F$2,$B101)),ISNUMBER(SEARCH($N$2,$B101)),ISNUMBER(SEARCH($N$2,$B101))),1,""),"") | U101: =IF($C101=U$10,IF(AND(ISNUMBER(SEARCH($M$2,$B101)),ISNUMBER(SEARCH($L$2,$B101)),ISNUMBER(SEARCH($J$2,$B101)),ISNUMBER(SEARCH($K$2,$B101))),$H$2,""),"") | V101: =IF($C101=V$10,IF(AND(ISNUMBER(SEARCH($M$2,$B101)),ISNUMBER(SEARCH($J$2,$B101))),1,""),"")
A102: =+'Pricing sheet'!A112 -> IT.59 | B102: =+'Pricing sheet'!B112 -> INDICATEURS D’ATTERISSAGE | C102: =+'Pricing sheet'!C112 -> AUTRES | D102: =+'Pricing sheet'!D112 -> Pc | E102: =+'Pricing sheet'!E112 -> 1.2 | F102: =+'Pricing sheet'!M112 -> 118.05168 | G102: =+'Pricing sheet'!N112 -> 125.69568 | H102: =+'Pricing sheet'!O112 -> 138.39775 | I102: =IF(SUM(S102:AC102)<>0,SUM(S102:AC102),"") -> 1 | S102: =IF($C102=S$10,IF(AND(ISNUMBER(SEARCH($F$2,$B102)),ISNUMBER(SEARCH($N$2,$B102)),ISNUMBER(SEARCH($N$2,$B102))),1,""),"") | U102: =IF($C102=U$10,IF(AND(ISNUMBER(SEARCH($M$2,$B102)),ISNUMBER(SEARCH($L$2,$B102)),ISNUMBER(SEARCH($J$2,$B102)),ISNUMBER(SEARCH($K$2,$B102))),$H$2,""),"") | V102: =IF($C102=V$10,IF(AND(ISNUMBER(SEARCH($M$2,$B102)),ISNUMBER(SEARCH($J$2,$B102))),1,""),"") | AC102: 1
A103: =+'Pricing sheet'!A113 -> IT.60 | B103: =+'Pricing sheet'!B113 -> BOÎTE D'ALARME | C103: =+'Pricing sheet'!C113 -> AUTRES | D103: =+'Pricing sheet'!D113 -> Pc | E103: =+'Pricing sheet'!E113 -> 1 | F103: =+'Pricing sheet'!M113 -> 30.269606 | G103: =+'Pricing sheet'!N113 -> 32.229606 | H103: =+'Pricing sheet'!O113 -> 35.486492 | I103: =IF(SUM(S103:AC103)<>0,SUM(S103:AC103),"") -> 25 | S103: =IF($C103=S$10,IF(AND(ISNUMBER(SEARCH($F$2,$B103)),ISNUMBER(SEARCH($N$2,$B103)),ISNUMBER(SEARCH($N$2,$B103))),1,""),"") | U103: =IF($C103=U$10,IF(AND(ISNUMBER(SEARCH($M$2,$B103)),ISNUMBER(SEARCH($L$2,$B103)),ISNUMBER(SEARCH($J$2,$B103)),ISNUMBER(SEARCH($K$2,$B103))),$H$2,""),"") | V103: =IF($C103=V$10,IF(AND(ISNUMBER(SEARCH($M$2,$B103)),ISNUMBER(SEARCH($J$2,$B103))),1,""),"") | AB103: =+INT((450+G2*40)/31)+1 -> 25
A104: =+'Pricing sheet'!A114 -> IT.61 | B104: =+'Pricing sheet'!B114 -> BOUTON DE SECOURS | C104: =+'Pricing sheet'!C114 -> AUTRES | D104: =+'Pricing sheet'!D114 -> Pc | E104: =+'Pricing sheet'!E114 -> 0.4 | F104: =+'Pricing sheet'!M114 -> 24.215682 | G104: =+'Pricing sheet'!N114 -> 25.783682 | H104: =+'Pricing sheet'!O114 -> 28.389187 | I104: =IF(SUM(S104:AC104)<>0,SUM(S104:AC104),"") | S104: =IF($C104=S$10,IF(AND(ISNUMBER(SEARCH($F$2,$B104)),ISNUMBER(SEARCH($N$2,$B104)),ISNUMBER(SEARCH($N$2,$B104))),1,""),"") | U104: =IF($C104=U$10,IF(AND(ISNUMBER(SEARCH($M$2,$B104)),ISNUMBER(SEARCH($L$2,$B104)),ISNUMBER(SEARCH($J$2,$B104)),ISNUMBER(SEARCH($K$2,$B104))),$H$2,""),"") | V104: =IF($C104=V$10,IF(AND(ISNUMBER(SEARCH($M$2,$B104)),ISNUMBER(SEARCH($J$2,$B104))),1,""),"")
...

Sheet Comparison
A2: OUR REF | B2: OUR NAME | C2: TURKISH NAME | D2: PREVIOUS PRICE | E2: ACTUAL PRICE | F2: Difference | G2: IN %
A3: IT.14 | B3: CLASSIC BRACKET 60X60 (PATE) | C3: 6*6*18 KONSOL (4mm) | D3: 0.6 | E3: 0.782 | F3: 1.3033333 | G3: =+F3-1 -> 0.30333333
A4: IT.15 | B4: CLASSIC BRACKET 60X80 (PATE) | C4: 6*8*18 KONSOL (4mm) | D4: 0.9 | E4: 0.9085 | F4: 1.0094444 | G4: =+F4-1 -> 0.0094444444
A5: IT.16 | B5: CROMPO 50 | C5: Coulisseau rail 50 | D5: 0.28 | E5: 0.322 | F5: 1.15 | G5: =+F5-1 -> 0.15
A6: IT.17 | B6: CROMPO 70 | C6: Coulisseau rail 70 | D6: 0.37 | E6: 0.437 | F6: 1.1810811 | G6: =+F6-1 -> 0.18108108
A7: IT.19 | B7: CROMPO 90 | C7: Coulisseau rail 90 | D7: 0.47 | E7: 0.5635 | F7: 1.1989362 | G7: =+F7-1 -> 0.19893617
A8: IT.25 | B8: CHEVEILLE 12/100 | C8: KLİPSLİ ÇELİK DÜBEL M-12*109 | D8: 0.21 | E8: 0.2645 | F8: 1.2595238 | G8: =+F8-1 -> 0.25952381
A9: IT.30 | B9: GARNITURE COULISSEAU 50 | C9: PLASTİK PATEN T50 5mm | D9: 0.5 | E9: 0.69 | F9: 1.38 | G9: =+F9-1 -> 0.38
A10: IT.31 | B10: CABLE TRACTION (10mm) | C10: Câble traction Ø10mm | D10: 0.92 | E10: 0.943 | F10: 1.025 | G10: =+F10-1 -> 0.025
A11: IT.32 | B11: CABLE GEARLESS (6,5mm) | C11: Câble gearless Ø6,5mm | D11: 0.87 | E11: 0.7475 | F11: 0.8591954 | G11: =+F11-1 -> -0.1408046
A12: IT.33 | B12: CABLE REGULATEUR (6mm) | C12: Câble régulateur Ø6mm | D12: 0.28 | E12: 0.2875 | F12: 1.0267857 | G12: =+F12-1 -> 0.026785714
A13: IT.36 | B13: SERRE CABLE DIAM 10mm * | C13: Serre-câble Ø10mm | D13: 0.2 | E13: 0.2415 | F13: 1.2075 | G13: =+F13-1 -> 0.2075
A14: IT.37 | B14: SERRE CABLE DIAM 6,5mm * | C14: Serre-câble Ø6,5–8mm | D14: 0.15 | E14: 0.138 | F14: 0.92 | G14: =+F14-1 -> -0.08
... A17: IT.41 | B17: BOITE DE LUBRIFICATION | C17: Boîte de lubrification | D17: 1 | E17: 1.495 | F17: 1.495 | G17: =+F17-1 -> 0.495
A18: IT.42 | B18: COULISSEAUX CABIN | C18: ALUMİNYÜM PATEN T70 - 9mm | D18: 6 | E18: 7.475 | F18: 1.2458333 | G18: =+F18-1 -> 0.24583333 | H18: KABİN SAC PATENİ T90 - 16mm | I18: 8.28 | J18: 1.38 | K18: =+J18-1 -> 0.38
A19: IT.43 | B19: COULISSEAUX CONTRE-POIDS | C19: ALUMİNYÜM PATEN T50 - 5mm | D19: 3.5 | E19: 7.475 | F19: 2.1357143 | G19: =+F19-1 -> 1.1357143 | H19: AĞIRLIK SAC PATENİ T50 - 5mm | I19: 4.3125 | J19: 1.2321429 | K19: =+J19-1 -> 0.23214286
A20: IT.46 | B20: BUFFER CABIN/C,P / LES BOUDINS SET COMPLET | C20: Kit tampon cabine & CP | D20: 33 | E20: 34.5 | F20: 1.0454545 | G20: =+F20-1 -> 0.045454545
A21: IT.53 | B21: WIRE DUCT GOULLOTTE 40X40 | C21: Goulotte câble 40×40 (2m) | D21: 0.4 | E21: 0.437 | F21: 1.0925 | G21: =+F21-1 -> 0.0925
A22: IT.54 | B22: TUBE SPIRALÉ 14MM | C22: Tube spiralé Ø14mm | D22: 0.09 | E22: 0.1035 | F22: 1.15 | G22: =+F22-1 -> 0.15
A23: IT.60 | B23: BOÎTE D'ALARME | C23: BATARYALI ALARM BUTONU | D23: 2 | E23: 5.175 | F23: 2.5875 | G23: =+F23-1 -> 1.5875
A24: IT.61 | B24: BOUTON DE SECOURS | C24: MANTAR STOP | D24: 1.6 | E24: 1.61 | F24: 1.00625 | G24: =+F24-1 -> 0.00625 | H24: ALARM BUTONU | I24: 1.495 | J24: 0.934375 | K24: =+J24-1 -> -0.065625
